Workbook

Sheet Analysis
B1: NAV Build-up
C2: Year 1 | D2: Year 2 | E2: Year 3 | F2: Year 4 | G2: Year 5 | H2: Year 6 | I2: Year 7 | J2: Year 8 | K2: Year 9 | L2: Year 10 | M2: Year 11 | N2: Year 12 | O2: Year 13 | P2: Year 14 | Q2: Year 15
B3: Drawdown only | C3: ='Drawdown only'!D208 -> 0.61979885 | D3: ='Drawdown only'!E208 -> 1.9975294 | E3: ='Drawdown only'!F208 -> 4.2384224 | F3: ='Drawdown only'!G208 -> 7.1673385 | G3: ='Drawdown only'!H208 -> 10.451436 | H3: ='Drawdown only'!I208 -> 13.593923 | I3: ='Drawdown only'!J208 -> 16.455815 | J3: ='Drawdown only'!K208 -> 18.881824 | ... Q3: ='Drawdown only'!R208 -> 26.296312
B4: Evergreen only | C4: ='Evergreen only'!D208 -> 10.939 | D4: ='Evergreen only'!E208 -> 11.966172 | E4: ='Evergreen only'!F208 -> 13.089796 | F4: ='Evergreen only'!G208 -> 14.318927 | G4: ='Evergreen only'!H208 -> 15.663475 | H4: ='Evergreen only'!I208 -> 17.134275 | I4: ='Evergreen only'!J208 -> 18.743183 | J4: ='Evergreen only'!K208 -> 20.503168 | ... Q4: ='Evergreen only'!R208 -> 38.429465
B5: Drawdown with re-investment | C5: ='Drawdown+reinvestment'!D208 -> 10.600656 | D5: ='Drawdown+reinvestment'!E208 -> 11.132372 | E5: ='Drawdown+reinvestment'!F208 -> 11.668652 | F5: ='Drawdown+reinvestment'!G208 -> 12.356559 | G5: ='Drawdown+reinvestment'!H208 -> 13.4591 | H5: ='Drawdown+reinvestment'!I208 -> 14.787801 | I5: ='Drawdown+reinvestment'!J208 -> 16.636856 | J5: ='Drawdown+reinvestment'!K208 -> 18.924892 | ... Q5: ='Drawdown+reinvestment'!R208 -> 42.613909
B6: Drawdown and Evergreen | C6: ='Drawdown+Evergreen from start'!D208 -> 10.769828 | D6: ='Drawdown+Evergreen from start'!E208 -> 11.549272 | E6: ='Drawdown+Evergreen from start'!F208 -> 12.379224 | F6: ='Drawdown+Evergreen from start'!G208 -> 13.337743 | G6: ='Drawdown+Evergreen from start'!H208 -> 14.561287 | H6: ='Drawdown+Evergreen from start'!I208 -> 15.961038 | I6: ='Drawdown+Evergreen from start'!J208 -> 17.69002 | J6: ='Drawdown+Evergreen from start'!K208 -> 19.71403 | ... Q6: ='Drawdown+Evergreen from start'!R208 -> 40.521687

Sheet Drawdown only
A1: After-tax annualized investment return: | B1: 0.064
A3: Year | B3: Current Market Value | C3: New Money Ins/Outs | D3: Total Assets | E3: PE Target (%) | F3: PE Target ($) | H3: Compounding Open-ended PE Commitments | I3: Compounding Rate | K3: Yielding Open-ended PE Commitments | L3: Yield Rate | N3: New Drawdown Target Portfolio | O3: **Make sure this sums to 100%
A4: 2025 | B4: 10000000 | C4: 0 | D4: =SUM(B4:C4) -> 10000000 | E4: 1 | F4: =D4*E4 -> 10000000 | H4: 0 | I4: 0.09 | K4: 0 | L4: 0.06 | N4: Buyout | O4: 1
A5: =A4+1 -> 2026 | D5: =(D4*(1+$B$1))+C5 -> 10640000 | E5: =E4 -> 1 | F5: =D5*E5 -> 10640000 | H5: 0 | K5: 0 | N5: Growth Equity | O5: 0
A6: =A5+1 -> 2027 | D6: =(D5*(1+$B$1))+C6 -> 11320960 | E6: =E5 -> 1 | F6: =D6*E6 -> 11320960 | H6: 0 | K6: 0 | N6: Venture Capital | O6: 0
A7: =A6+1 -> 2028 | D7: =(D6*(1+$B$1))+C7 -> 12045501 | E7: =E6 -> 1 | F7: =D7*E7 -> 12045501 | H7: 0 | K7: 0 | N7: Fund of Funds | O7: 0
A8: =A7+1 -> 2029 | D8: =(D7*(1+$B$1))+C8 -> 12816414 | E8: =E7 -> 1 | F8: =D8*E8 -> 12816414 | H8: 0 | K8: 0 | N8: Secondary Funds | O8: 0
A9: =A8+1 -> 2030 | D9: =(D8*(1+$B$1))+C9 -> 13636664 | E9: =E8 -> 1 | F9: =D9*E9 -> 13636664 | H9: 0 | K9: 0 | N9: Private Credit | O9: 0
A10: =A9+1 -> 2031 | D10: =(D9*(1+$B$1))+C10 -> 14509410 | E10: =E9 -> 1 | F10: =D10*E10 -> 14509410 | H10: 0 | K10: 0 | N10: Real Estate | O10: 0
A11: =A10+1 -> 2032 | D11: =(D10*(1+$B$1))+C11 -> 15438013 | E11: =E10 -> 1 | F11: =D11*E11 -> 15438013 | H11: 0 | K11: 0
A12: =A11+1 -> 2033 | D12: =(D11*(1+$B$1))+C12 -> 16426046 | E12: =E11 -> 1 | F12: =D12*E12 -> 16426046 | H12: 0 | K12: 0 | N12: Total | O12: =SUM(O4:O10) -> 1
A13: =A12+1 -> 2034 | D13: =(D12*(1+$B$1))+C13 -> 17477313 | E13: =E12 -> 1 | F13: =D13*E13 -> 17477313 | H13: 0 | K13: 0
A14: =A13+1 -> 2035 | D14: =(D13*(1+$B$1))+C14 -> 18595861 | E14: =E13 -> 1 | F14: =D14*E14 -> 18595861 | H14: 0 | K14: 0
A15: =A14+1 -> 2036 | D15: =(D14*(1+$B$1))+C15 -> 19785996 | E15: =E14 -> 1 | F15: =D15*E15 -> 19785996 | H15: 0 | K15: 0
A16: =A15+1 -> 2037 | D16: =(D15*(1+$B$1))+C16 -> 21052299 | E16: =E15 -> 1 | F16: =D16*E16 -> 21052299 | H16: 0 | K16: 0
A17: =A16+1 -> 2038 | D17: =(D16*(1+$B$1))+C17 -> 22399646 | E17: =E16 -> 1 | F17: =D17*E17 -> 22399646 | H17: 0 | K17: 0
A18: =A17+1 -> 2039 | D18: =(D17*(1+$B$1))+C18 -> 23833224 | E18: =E17 -> 1 | F18: =D18*E18 -> 23833224 | H18: 0 | K18: 0
A27: EXISTING PORTFOLIO | B27: TO FILL IN WITH CONNECT OUTPUT | D27: Net Asset Value
A28: New Commitments | B28: Commitment | C28: % of Total Portfolio Value | D28: 2025 | E28: =D28+1 -> 2026 | F28: =E28+1 -> 2027 | G28: =F28+1 -> 2028 | H28: =G28+1 -> 2029 | I28: =H28+1 -> 2030 | J28: =I28+1 -> 2031 | K28: =J28+1 -> 2032 | L28: =K28+1 -> 2033 | ... R28: =Q28+1 -> 2039
B30: 0 | D30: 0 | E30: 0 | F30: 0 | G30: 0 | H30: 0 | I30: 0 | J30: 0 | K30: 0 | L30: 0 | M30: 0 | N30: 0 | O30: 0 | P30: 0 | Q30: 0 | R30: 0
D33: Annual Capital Called
A34: New Commitments | B34: Commitment | D34: =D$100 -> 2025 | E34: =E$100 -> 2026 | F34: =F$100 -> 2027 | G34: =G$100 -> 2028 | H34: =H$100 -> 2029 | I34: =I$100 -> 2030 | J34: =J$100 -> 2031 | K34: =K$100 -> 2032 | ... R34: =R$100 -> 2039
B36: 0 | D36: 0 | E36: 0 | F36: 0 | G36: 0 | H36: 0 | I36: 0 | J36: 0 | K36: 0 | L36: 0 | M36: 0 | N36: 0 | O36: 0 | P36: 0 | Q36: 0 | R36: 0
D38: Annual Distributions
A39: New Commitments | B39: Commitment | D39: =D$100 -> 2025 | E39: =E$100 -> 2026 | F39: =F$100 -> 2027 | G39: =G$100 -> 2028 | H39: =H$100 -> 2029 | I39: =I$100 -> 2030 | J39: =J$100 -> 2031 | K39: =K$100 -> 2032 | ... R39: =R$100 -> 2039
B41: 0 | D41: 0 | E41: 0 | F41: 0 | G41: 0 | H41: 0 | I41: 0 | J41: 0 | K41: 0 | L41: 0 | M41: 0 | N41: 0 | O41: 0 | P41: 0 | Q41: 0 | R41: 0
D43: Net Cash Flow
A44: New Commitments | B44: Commitment | D44: =D$100 -> 2025 | E44: =E$100 -> 2026 | F44: =F$100 -> 2027 | G44: =G$100 -> 2028 | H44: =H$100 -> 2029 | I44: =I$100 -> 2030 | J44: =J$100 -> 2031 | K44: =K$100 -> 2032 | ... R44: =R$100 -> 2039
B46: 0 | D46: =D36+D41 -> 0 | E46: =E36+E41 -> 0 | F46: =F36+F41 -> 0 | G46: =G36+G41 -> 0 | H46: =H36+H41 -> 0 | I46: =I36+I41 -> 0 | J46: =J36+J41 -> 0 | K46: =K36+K41 -> 0 | ... R46: =R36+R41 -> 0
A49: Net Cash Flow Cumulative | D49: =D46 -> 0 | E49: =D49+E46 -> 0 | F49: =E49+F46 -> 0 | G49: =F49+G46 -> 0 | H49: =G49+H46 -> 0 | I49: =H49+I46 -> 0 | J49: =I49+J46 -> 0 | K49: =J49+K46 -> 0 | L49: =K49+L46 -> 0 | ... R49: =Q49+R46 -> 0
A51: Cash invested | D51: Net Asset Value
A52: New Commitments | B52: Commitment | C52: % of Total Portfolio Value | D52: 2025 | E52: =D52+1 -> 2026 | F52: =E52+1 -> 2027 | G52: =F52+1 -> 2028 | H52: =G52+1 -> 2029 | I52: =H52+1 -> 2030 | J52: =I52+1 -> 2031 | K52: =J52+1 -> 2032 | L52: =K52+1 -> 2033 | ... R52: =Q52+1 -> 2039
B54: =SUM(K4:K18) -> 0 | C54: =B4 -> 10000000 | D54: =$K4 -> 0 | E54: =K4+K5 -> 0 | F54: =K4+K6+K5 -> 0 | G54: =K4+K5+K6+K7 -> 0 | H54: =K4+K5+K6+K7+K8 -> 0 | I54: =K4+K5+K6+K7+K8+K9 -> 0 | J54: =K4+K5+K6+K7+K8+K9+K10 -> 0 | K54: =K4+K5+K6+K7+K8+K9+K10+K11 -> 0 | L54: =K4+K5+K6+K7+K8+K9+K10+K11+K12 -> 0 | M54: =K4+K5+K6+K7+K8+K9+K10+K11+K12+K13 -> 0 | N54: =K4+K5+K6+K7+K8+K9+K10+K11+K12+K13+K14 -> 0 | O54: =K4+K5+K6+K7+K8+K9+K10+K11+K12+K13+K14+K15 -> 0 | P54: =K4+K5+K6+K7+K8+K9+K10+K11+K12+K13+K14+K15+K16 -> 0 | Q54: =K4+K5+K6+K7+K8+K9+K10+K11+K12+K13+K14+K15+K16+K17 -> 0 | R54: =K4+K5+K6+K7+K8+K9+K10+K11+K12+K13+K14+K15+K16+K17+K18 -> 0
D57: Annual Capital Called
A58: New Commitments | B58: Commitment | D58: =D$100 -> 2025 | E58: =E$100 -> 2026 | F58: =F$100 -> 2027 | G58: =G$100 -> 2028 | H58: =H$100 -> 2029 | I58: =I$100 -> 2030 | J58: =J$100 -> 2031 | K58: =K$100 -> 2032 | ... R58: =R$100 -> 2039
B60: =SUM(K4:K18) -> 0 | D60: =-K4 -> 0 | E60: =-$K5 -> 0 | F60: =-$K6 -> 0 | G60: =-$K7 -> 0 | H60: =-$K8 -> 0 | I60: =-$K9 -> 0 | J60: =-$K10 -> 0 | K60: =-$K11 -> 0 | L60: =-$K12 -> 0 | M60: =-$K13 -> 0 | N60: =-$K14 -> 0 | O60: =-$K15 -> 0 | P60: =-$K16 -> 0 | Q60: =-$K17 -> 0 | R60: =-$K18 -> 0
D62: Annual Distributions
A63: New Commitments | B63: Commitment | D63: =D$100 -> 2025 | E63: =E$100 -> 2026 | F63: =F$100 -> 2027 | G63: =G$100 -> 2028 | H63: =H$100 -> 2029 | I63: =I$100 -> 2030 | J63: =J$100 -> 2031 | K63: =K$100 -> 2032 | ... R63: =R$100 -> 2039
B65: =SUM(K4:K18) -> 0 | D65: =K4*$L$4 -> 0 | E65: =SUM($K4:$K5)*$L$4 -> 0 | F65: =SUM($K4:$K6)*$L$4 -> 0 | G65: =SUM($K4:$K7)*$L$4 -> 0 | H65: =SUM($K4:$K8)*$L$4 -> 0 | I65: =SUM($K4:$K9)*$L$4 -> 0 | J65: =SUM($K4:$K10)*$L$4 -> 0 | K65: =SUM($K4:$K11)*$L$4 -> 0 | L65: =SUM($K4:$K12)*$L$4 -> 0 | M65: =SUM($K4:$K13)*$L$4 -> 0 | N65: =SUM($K4:$K14)*$L$4 -> 0 | O65: =SUM($K4:$K15)*$L$4 -> 0 | P65: =SUM($K4:$K16)*$L$4 -> 0 | Q65: =SUM($K4:$K17)*$L$4 -> 0 | R65: =SUM($K4:$K18)*$L$4 -> 0
D67: Net Cash Flow
A68: New Commitments | B68: Commitment | D68: =D$100 -> 2025 | E68: =E$100 -> 2026 | F68: =F$100 -> 2027 | G68: =G$100 -> 2028 | H68: =H$100 -> 2029 | I68: =I$100 -> 2030 | J68: =J$100 -> 2031 | K68: =K$100 -> 2032 | ... R68: =R$100 -> 2039
B70: =SUM(K4:K18) -> 0 | D70: =D60+D65 -> 0 | E70: =E60+E65 -> 0 | F70: =F60+F65 -> 0 | G70: =G60+G65 -> 0 | H70: =H60+H65 -> 0 | I70: =I60+I65 -> 0 | J70: =J60+J65 -> 0 | K70: =K60+K65 -> 0 | ... R70: =R60+R65 -> 0
A73: Net Cash Flow Cumulative | D73: =D70 -> 0 | E73: =D73+E70 -> 0 | F73: =E73+F70 -> 0 | G73: =F73+G70 -> 0 | H73: =G73+H70 -> 0 | I73: =H73+I70 -> 0 | J73: =I73+J70 -> 0 | K73: =J73+K70 -> 0 | L73: =K73+L70 -> 0 | ... R73: =Q73+R70 -> 0
A75: NEW COMPOUNDING OPEN-ENDED PORTFOLIO | D75: Net Asset Value
A76: New Commitments | B76: Commitment | C76: % of Total Portfolio Value | D76: 2025 | E76: =D76+1 -> 2026 | F76: =E76+1 -> 2027 | G76: =F76+1 -> 2028 | H76: =G76+1 -> 2029 | I76: =H76+1 -> 2030 | J76: =I76+1 -> 2031 | K76: =J76+1 -> 2032 | L76: =K76+1 -> 2033 | ... R76: =Q76+1 -> 2039
B78: =SUM(H4:H18) -> 0 | D78: =H4*(1+$I$4) -> 0 | E78: =D78*(1+$I$4)+E$84*(1+$I$4) -> 0 | F78: =E78*(1+$I$4)+F$84*(1+$I$4) -> 0 | G78: =F78*(1+$I$4)+G$84*(1+$I$4) -> 0 | H78: =G78*(1+$I$4)+H$84*(1+$I$4) -> 0 | I78: =H78*(1+$I$4)+I$84*(1+$I$4) -> 0 | J78: =I78*(1+$I$4)+J$84*(1+$I$4) -> 0 | K78: =J78*(1+$I$4)+K$84*(1+$I$4) -> 0 | L78: =K78*(1+$I$4)+L$84*(1+$I$4) -> 0 | ... R78: =Q78*(1+$I$4)+R$84*(1+$I$4) -> 0
D81: Annual Capital Called
A82: New Commitments | B82: Commitment | D82: =D$100 -> 2025 | E82: =E$100 -> 2026 | F82: =F$100 -> 2027 | G82: =G$100 -> 2028 | H82: =H$100 -> 2029 | I82: =I$100 -> 2030 | J82: =J$100 -> 2031 | K82: =K$100 -> 2032 | ... R82: =R$100 -> 2039
B84: =SUM(H4:H18) -> 0 | D84: =-$H4 -> 0 | E84: =-$H5 -> 0 | F84: =-$H6 -> 0 | G84: =-$H7 -> 0 | H84: =-$H8 -> 0 | I84: =-$H9 -> 0 | J84: =-$H10 -> 0 | K84: =-$H11 -> 0 | L84: =-H12 -> 0 | M84: =-H13 -> 0 | N84: =-H14 -> 0 | O84: =-H15 -> 0 | P84: =-H16 -> 0 | Q84: =-H17 -> 0 | R84: =-H18 -> 0
D86: Annual Distributions
A87: New Commitments | B87: Commitment | D87: =D$100 -> 2025 | E87: =E$100 -> 2026 | F87: =F$100 -> 2027 | G87: =G$100 -> 2028 | H87: =H$100 -> 2029 | I87: =I$100 -> 2030 | J87: =J$100 -> 2031 | K87: =K$100 -> 2032 | ... R87: =R$100 -> 2039
B89: =SUM(H4:H18) -> 0 | D89: 0 | E89: 0 | F89: 0 | G89: 0 | H89: 0 | I89: 0 | J89: 0 | K89: 0 | L89: 0 | M89: 0 | N89: 0 | O89: 0 | P89: 0 | Q89: 0 | R89: 0
D91: Net Cash Flow
A92: New Commitments | B92: Commitment | D92: =D$100 -> 2025 | E92: =E$100 -> 2026 | F92: =F$100 -> 2027 | G92: =G$100 -> 2028 | H92: =H$100 -> 2029 | I92: =I$100 -> 2030 | J92: =J$100 -> 2031 | K92: =K$100 -> 2032 | ... R92: =R$100 -> 2039
B94: =SUM(H4:H18) -> 0 | D94: =D84+D89 -> 0 | E94: =E84+E89 -> 0 | F94: =F84+F89 -> 0 | G94: =G84+G89 -> 0 | H94: =H84+H89 -> 0 | I94: =I84+I89 -> 0 | J94: =J84+J89 -> 0 | K94: =K84+K89 -> 0 | ... R94: =R84+R89 -> 0
A97: Net Cash Flow Cumulative | D97: =SUM($D$94:D94) -> 0 | E97: =SUM($D$94:E94) -> 0 | F97: =SUM($D$94:F94) -> 0 | G97: =SUM($D$94:G94) -> 0 | H97: =SUM($D$94:H94) -> 0 | I97: =SUM($D$94:I94) -> 0 | J97: =SUM($D$94:J94) -> 0 | K97: =SUM($D$94:K94) -> 0 | ... R97: =SUM($D$94:R94) -> 0
A99: NEW DRAWDOWN PORTFOLIO | D99: Net Asset Value
A100: New Commitments | B100: Commitment | C100: % of Total Portfolio Value | D100: 2025 | E100: =D100+1 -> 2026 | F100: =E100+1 -> 2027 | G100: =F100+1 -> 2028 | H100: =G100+1 -> 2029 | I100: =H100+1 -> 2030 | J100: =I100+1 -> 2031 | K100: =J100+1 -> 2032 | L100: =K100+1 -> 2033 | ... R100: =Q100+1 -> 2039
A101: 2025 | B101: 3900000 | C101: =B101/$D4 -> 0.39 | D101: =VLOOKUP(D$100,'Aggregated Median CA data'!$D$126:$M$140,5,0)*$B101 -> 619798.85 | E101: =VLOOKUP(E$100,'Aggregated Median CA data'!$D$126:$M$140,5,0)*$B101 -> 1377730.5 | F101: =VLOOKUP(F$100,'Aggregated Median CA data'!$D$126:$M$140,5,0)*$B101 -> 2240893 | G101: =VLOOKUP(G$100,'Aggregated Median CA data'!$D$126:$M$140,5,0)*$B101 -> 2928916.1 | H101: =VLOOKUP(H$100,'Aggregated Median CA data'!$D$126:$M$140,5,0)*$B101 -> 3284097.9 | I101: =VLOOKUP(I$100,'Aggregated Median CA data'!$D$126:$M$140,5,0)*$B101 -> 3142486.4 | J101: =VLOOKUP(J$100,'Aggregated Median CA data'!$D$126:$M$140,5,0)*$B101 -> 2861892.1 | K101: =VLOOKUP(K$100,'Aggregated Median CA data'!$D$126:$M$140,5,0)*$B101 -> 2426009.3 | ... R101: =VLOOKUP(R$100,'Aggregated Median CA data'!$D$126:$M$140,5,0)*$B101 -> 549638.68
A102: =A101+1 -> 2026 | B102: 3900000 | C102: =B102/$D5 -> 0.36654135 | E102: =IF($B102=0,0,(D101/$B101)*$B102) -> 619798.85 | F102: =IF($B102=0,0,(E101/$B101)*$B102) -> 1377730.5 | G102: =IF($B102=0,0,(F101/$B101)*$B102) -> 2240893 | H102: =IF($B102=0,0,(G101/$B101)*$B102) -> 2928916.1 | I102: =IF($B102=0,0,(H101/$B101)*$B102) -> 3284097.9 | J102: =IF($B102=0,0,(I101/$B101)*$B102) -> 3142486.4 | K102: =IF($B102=0,0,(J101/$B101)*$B102) -> 2861892.1 | L102: =IF($B102=0,0,(K101/$B101)*$B102) -> 2426009.3 | ... R102: =IF($B102=0,0,(Q101/$B101)*$B102) -> 603071.2
A103: =A102+1 -> 2027 | B103: 3900000 | C103: =B103/$D6 -> 0.34449375 | F103: =IF($B103=0,0,(E102/$B102)*$B103) -> 619798.85 | G103: =IF($B103=0,0,(F102/$B102)*$B103) -> 1377730.5 | H103: =IF($B103=0,0,(G102/$B102)*$B103) -> 2240893 | I103: =IF($B103=0,0,(H102/$B102)*$B103) -> 2928916.1 | J103: =IF($B103=0,0,(I102/$B102)*$B103) -> 3284097.9 | K103: =IF($B103=0,0,(J102/$B102)*$B103) -> 3142486.4 | L103: =IF($B103=0,0,(K102/$B102)*$B103) -> 2861892.1 | M103: =IF($B103=0,0,(L102/$B102)*$B103) -> 2426009.3 | ... R103: =IF($B103=0,0,(Q102/$B102)*$B103) -> 698711.62
A104: =A103+1 -> 2028 | B104: 3900000 | C104: =B104/$D7 -> 0.32377232 | G104: =IF($B104=0,0,(F103/$B103)*$B104) -> 619798.85 | H104: =IF($B104=0,0,(G103/$B103)*$B104) -> 1377730.5 | I104: =IF($B104=0,0,(H103/$B103)*$B104) -> 2240893 | J104: =IF($B104=0,0,(I103/$B103)*$B104) -> 2928916.1 | K104: =IF($B104=0,0,(J103/$B103)*$B104) -> 3284097.9 | L104: =IF($B104=0,0,(K103/$B103)*$B104) -> 3142486.4 | M104: =IF($B104=0,0,(L103/$B103)*$B104) -> 2861892.1 | N104: =IF($B104=0,0,(M103/$B103)*$B104) -> 2426009.3 | ... R104: =IF($B104=0,0,(Q103/$B103)*$B104) -> 902056.17
A105: =A104+1 -> 2029 | B105: 3900000 | C105: =B105/$D8 -> 0.3042973 | H105: =IF($B105=0,0,(G104/$B104)*$B105) -> 619798.85 | I105: =IF($B105=0,0,(H104/$B104)*$B105) -> 1377730.5 | J105: =IF($B105=0,0,(I104/$B104)*$B105) -> 2240893 | K105: =IF($B105=0,0,(J104/$B104)*$B105) -> 2928916.1 | L105: =IF($B105=0,0,(K104/$B104)*$B105) -> 3284097.9 | M105: =IF($B105=0,0,(L104/$B104)*$B105) -> 3142486.4 | N105: =IF($B105=0,0,(M104/$B104)*$B105) -> 2861892.1 | O105: =IF($B105=0,0,(N104/$B104)*$B105) -> 2426009.3 | ... R105: =IF($B105=0,0,(Q104/$B104)*$B105) -> 1174462.8
A106: =A105+1 -> 2030 | B106: 3900000 | C106: =B106/$D9 -> 0.2859937 | I106: =IF($B106=0,0,(H105/$B105)*$B106) -> 619798.85 | J106: =IF($B106=0,0,(I105/$B105)*$B106) -> 1377730.5 | K106: =IF($B106=0,0,(J105/$B105)*$B106) -> 2240893 | L106: =IF($B106=0,0,(K105/$B105)*$B106) -> 2928916.1 | M106: =IF($B106=0,0,(L105/$B105)*$B106) -> 3284097.9 | N106: =IF($B106=0,0,(M105/$B105)*$B106) -> 3142486.4 | O106: =IF($B106=0,0,(N105/$B105)*$B106) -> 2861892.1 | P106: =IF($B106=0,0,(O105/$B105)*$B106) -> 2426009.3 | ... R106: =IF($B106=0,0,(Q105/$B105)*$B106) -> 1564270.3
A107: =A106+1 -> 2031 | B107: 3900000 | C107: =B107/$D10 -> 0.26879107 | J107: =IF($B107=0,0,(I106/$B106)*$B107) -> 619798.85 | K107: =IF($B107=0,0,(J106/$B106)*$B107) -> 1377730.5 | L107: =IF($B107=0,0,(K106/$B106)*$B107) -> 2240893 | M107: =IF($B107=0,0,(L106/$B106)*$B107) -> 2928916.1 | N107: =IF($B107=0,0,(M106/$B106)*$B107) -> 3284097.9 | O107: =IF($B107=0,0,(N106/$B106)*$B107) -> 3142486.4 | P107: =IF($B107=0,0,(O106/$B106)*$B107) -> 2861892.1 | Q107: =IF($B107=0,0,(P106/$B106)*$B107) -> 2426009.3 | R107: =IF($B107=0,0,(Q106/$B106)*$B107) -> 1922276.8
A108: =A107+1 -> 2032 | B108: 3900000 | C108: =B108/$D11 -> 0.25262319 | K108: =IF($B108=0,0,(J107/$B107)*$B108) -> 619798.85 | L108: =IF($B108=0,0,(K107/$B107)*$B108) -> 1377730.5 | M108: =IF($B108=0,0,(L107/$B107)*$B108) -> 2240893 | N108: =IF($B108=0,0,(M107/$B107)*$B108) -> 2928916.1 | O108: =IF($B108=0,0,(N107/$B107)*$B108) -> 3284097.9 | P108: =IF($B108=0,0,(O107/$B107)*$B108) -> 3142486.4 | Q108: =IF($B108=0,0,(P107/$B107)*$B108) -> 2861892.1 | R108: =IF($B108=0,0,(Q107/$B107)*$B108) -> 2426009.3
A109: =A108+1 -> 2033 | B109: 3900000 | C109: =B109/$D12 -> 0.23742781 | L109: =IF($B109=0,0,(K108/$B108)*$B109) -> 619798.85 | M109: =IF($B109=0,0,(L108/$B108)*$B109) -> 1377730.5 | N109: =IF($B109=0,0,(M108/$B108)*$B109) -> 2240893 | O109: =IF($B109=0,0,(N108/$B108)*$B109) -> 2928916.1 | P109: =IF($B109=0,0,(O108/$B108)*$B109) -> 3284097.9 | Q109: =IF($B109=0,0,(P108/$B108)*$B109) -> 3142486.4 | R109: =IF($B109=0,0,(Q108/$B108)*$B109) -> 2861892.1
A110: =A109+1 -> 2034 | B110: 3900000 | C110: =B110/$D13 -> 0.22314644 | M110: =IF($B110=0,0,(L109/$B109)*$B110) -> 619798.85 | N110: =IF($B110=0,0,(M109/$B109)*$B110) -> 1377730.5 | O110: =IF($B110=0,0,(N109/$B109)*$B110) -> 2240893 | P110: =IF($B110=0,0,(O109/$B109)*$B110) -> 2928916.1 | Q110: =IF($B110=0,0,(P109/$B109)*$B110) -> 3284097.9 | R110: =IF($B110=0,0,(Q109/$B109)*$B110) -> 3142486.4
A111: =A110+1 -> 2035 | B111: 3900000 | C111: =B111/$D14 -> 0.20972409 | N111: =IF($B111=0,0,(M110/$B110)*$B111) -> 619798.85 | O111: =IF($B111=0,0,(N110/$B110)*$B111) -> 1377730.5 | P111: =IF($B111=0,0,(O110/$B110)*$B111) -> 2240893 | Q111: =IF($B111=0,0,(P110/$B110)*$B111) -> 2928916.1 | R111: =IF($B111=0,0,(Q110/$B110)*$B111) -> 3284097.9
A112: =A111+1 -> 2036 | B112: 3900000 | C112: =B112/$D15 -> 0.19710911 | O112: =IF($B112=0,0,(N111/$B111)*$B112) -> 619798.85 | P112: =IF($B112=0,0,(O111/$B111)*$B112) -> 1377730.5 | Q112: =IF($B112=0,0,(P111/$B111)*$B112) -> 2240893 | R112: =IF($B112=0,0,(Q111/$B111)*$B112) -> 2928916.1
A113: =A112+1 -> 2037 | B113: 3900000 | C113: =B113/$D16 -> 0.18525292 | P113: =IF($B113=0,0,(O112/$B112)*$B113) -> 619798.85 | Q113: =IF($B113=0,0,(P112/$B112)*$B113) -> 1377730.5 | R113: =IF($B113=0,0,(Q112/$B112)*$B113) -> 2240893
A114: =A113+1 -> 2038 | B114: 3900000 | C114: =B114/$D17 -> 0.17410989 | Q114: =IF($B114=0,0,(P113/$B113)*$B114) -> 619798.85 | R114: =IF($B114=0,0,(Q113/$B113)*$B114) -> 1377730.5
A115: =A114+1 -> 2039 | B115: 3900000 | C115: =B115/$D18 -> 0.16363712 | R115: =IF($B115=0,0,(Q114/$B114)*$B115) -> 619798.85
A117: Total New | D117: =SUM(D101:D115) -> 619798.85 | E117: =SUM(E101:E115) -> 1997529.4 | F117: =SUM(F101:F115) -> 4238422.4 | G117: =SUM(G101:G115) -> 7167338.5 | H117: =SUM(H101:H115) -> 10451436 | I117: =SUM(I101:I115) -> 13593923 | J117: =SUM(J101:J115) -> 16455815 | K117: =SUM(K101:K115) -> 18881824 | ... R117: =SUM(R101:R115) -> 26296312
A119: Total New + Open-ended PE | D119: =SUM(D117,D78,D54,D30) -> 619798.85 | E119: =SUM(E117,E78,E54,E30) -> 1997529.4 | F119: =SUM(F117,F78,F54,F30) -> 4238422.4 | G119: =SUM(G117,G78,G54,G30) -> 7167338.5 | H119: =SUM(H117,H78,H54,H30) -> 10451436 | I119: =SUM(I117,I78,I54,I30) -> 13593923 | J119: =SUM(J117,J78,J54,J30) -> 16455815 | K119: =SUM(K117,K78,K54,K30) -> 18881824 | ... R119: =SUM(R117,R78,R54,R30) -> 26296312
A121: Total Mandate MV | D121: =$D$4 -> 10000000 | E121: =$D$5 -> 10640000 | F121: =$D$6 -> 11320960 | G121: =$D$7 -> 12045501 | H121: =$D$8 -> 12816414 | I121: =$D$9 -> 13636664 | J121: =$D$10 -> 14509410 | K121: =$D$11 -> 15438013 | L121: =$D$12 -> 16426046 | M121: =$D$13 -> 17477313 | N121: =$D$14 -> 18595861 | O121: =$D$15 -> 19785996 | P121: =$D$16 -> 21052299 | Q121: =$D$17 -> 22399646 | R121: =$D$18 -> 23833224
A122: % | D122: =D119/D121 -> 0.061979885 | E122: =E119/E121 -> 0.18773772 | F122: =F119/F121 -> 0.37438719 | G122: =G119/G121 -> 0.59502201 | H122: =H119/H121 -> 0.81547278 | I122: =I119/I121 -> 0.99686572 | J122: =J119/J121 -> 1.1341477 | K122: =K119/K121 -> 1.2230735 | ... R122: =R119/R121 -> 1.1033468
C123: Portfolio Value | D123: =D121/1000000 -> 10 | E123: =E121/1000000 -> 10.64 | F123: =F121/1000000 -> 11.32096 | G123: =G121/1000000 -> 12.045501 | H123: =H121/1000000 -> 12.816414 | I123: =I121/1000000 -> 13.636664 | J123: =J121/1000000 -> 14.50941 | K123: =K121/1000000 -> 15.438013 | ... R123: =R121/1000000 -> 23.833224
C124: Commitments | D124: =$B$101/1000000 -> 3.9 | E124: =$B$102/1000000 -> 3.9 | F124: =$B$103/1000000 -> 3.9 | G124: =$B$104/1000000 -> 3.9 | H124: =$B$105/1000000 -> 3.9 | I124: =$B$106/1000000 -> 3.9 | J124: =$B$107/1000000 -> 3.9 | K124: =$B$108/1000000 -> 3.9 | L124: =$B$109/1000000 -> 3.9 | M124: =$B$110/1000000 -> 3.9 | N124: =$B$111/1000000 -> 3.9 | O124: =$B$112/1000000 -> 3.9 | P124: =$B$113/1000000 -> 3.9 | Q124: =$B$114/1000000 -> 3.9 | R124: =$B$115/1000000 -> 3.9
C125: PI Portfolio NAV | D125: =D119/1000000 -> 0.61979885 | E125: =E119/1000000 -> 1.9975294 | F125: =F119/1000000 -> 4.2384224 | G125: =G119/1000000 -> 7.1673385 | H125: =H119/1000000 -> 10.451436 | I125: =I119/1000000 -> 13.593923 | J125: =J119/1000000 -> 16.455815 | K125: =K119/1000000 -> 18.881824 | ... R125: =R119/1000000 -> 26.296312
D126: Annual Capital Called
A127: New Commitments | B127: Commitment | D127: =D$100 -> 2025 | E127: =E$100 -> 2026 | F127: =F$100 -> 2027 | G127: =G$100 -> 2028 | H127: =H$100 -> 2029 | I127: =I$100 -> 2030 | J127: =J$100 -> 2031 | K127: =K$100 -> 2032 | ... R127: =R$100 -> 2039
A128: =A101 -> 2025 | B128: =B101 -> 3900000 | D128: =VLOOKUP(D$100,'Aggregated Median CA data'!$D$126:$M$140,7,0)*$B128 -> -672096.06 | E128: =VLOOKUP(E$100,'Aggregated Median CA data'!$D$126:$M$140,7,0)*$B128 -> -774526.06 | F128: =VLOOKUP(F$100,'Aggregated Median CA data'!$D$126:$M$140,7,0)*$B128 -> -829338.6 | G128: =VLOOKUP(G$100,'Aggregated Median CA data'!$D$126:$M$140,7,0)*$B128 -> -723349.3 | H128: =VLOOKUP(H$100,'Aggregated Median CA data'!$D$126:$M$140,7,0)*$B128 -> -451017.53 | I128: =VLOOKUP(I$100,'Aggregated Median CA data'!$D$126:$M$140,7,0)*$B128 -> -228788.73 | J128: =VLOOKUP(J$100,'Aggregated Median CA data'!$D$126:$M$140,7,0)*$B128 -> -103339.4 | K128: =VLOOKUP(K$100,'Aggregated Median CA data'!$D$126:$M$140,7,0)*$B128 -> -60792.103 | ... R128: =VLOOKUP(R$100,'Aggregated Median CA data'!$D$126:$M$140,7,0)*$B128 -> -1530.3283
A129: =A102 -> 2026 | B129: =B102 -> 3900000 | E129: =IFERROR((D128/$B128)*$B129,0) -> -672096.06 | F129: =IFERROR((E128/$B128)*$B129,0) -> -774526.06 | G129: =IFERROR((F128/$B128)*$B129,0) -> -829338.6 | H129: =IFERROR((G128/$B128)*$B129,0) -> -723349.3 | I129: =IFERROR((H128/$B128)*$B129,0) -> -451017.53 | J129: =IFERROR((I128/$B128)*$B129,0) -> -228788.73 | K129: =IFERROR((J128/$B128)*$B129,0) -> -103339.4 | L129: =IFERROR((K128/$B128)*$B129,0) -> -60792.103 | ... R129: =IFERROR((Q128/$B128)*$B129,0) -> -355.66796
A130: =A103 -> 2027 | B130: =B103 -> 3900000 | F130: =IFERROR((E129/$B129)*$B130,0) -> -672096.06 | G130: =IFERROR((F129/$B129)*$B130,0) -> -774526.06 | H130: =IFERROR((G129/$B129)*$B130,0) -> -829338.6 | I130: =IFERROR((H129/$B129)*$B130,0) -> -723349.3 | J130: =IFERROR((I129/$B129)*$B130,0) -> -451017.53 | K130: =IFERROR((J129/$B129)*$B130,0) -> -228788.73 | L130: =IFERROR((K129/$B129)*$B130,0) -> -103339.4 | M130: =IFERROR((L129/$B129)*$B130,0) -> -60792.103 | ... R130: =IFERROR((Q129/$B129)*$B130,0) -> -4230.8477
A131: =A104 -> 2028 | B131: =B104 -> 3900000 | G131: =IFERROR((F130/$B130)*$B131,0) -> -672096.06 | H131: =IFERROR((G130/$B130)*$B131,0) -> -774526.06 | I131: =IFERROR((H130/$B130)*$B131,0) -> -829338.6 | J131: =IFERROR((I130/$B130)*$B131,0) -> -723349.3 | K131: =IFERROR((J130/$B130)*$B131,0) -> -451017.53 | L131: =IFERROR((K130/$B130)*$B131,0) -> -228788.73 | M131: =IFERROR((L130/$B130)*$B131,0) -> -103339.4 | N131: =IFERROR((M130/$B130)*$B131,0) -> -60792.103 | ... R131: =IFERROR((Q130/$B130)*$B131,0) -> -5834.1943
A132: =A105 -> 2029 | B132: =B105 -> 3900000 | H132: =IFERROR((G131/$B131)*$B132,0) -> -672096.06 | I132: =IFERROR((H131/$B131)*$B132,0) -> -774526.06 | J132: =IFERROR((I131/$B131)*$B132,0) -> -829338.6 | K132: =IFERROR((J131/$B131)*$B132,0) -> -723349.3 | L132: =IFERROR((K131/$B131)*$B132,0) -> -451017.53 | M132: =IFERROR((L131/$B131)*$B132,0) -> -228788.73 | N132: =IFERROR((M131/$B131)*$B132,0) -> -103339.4 | O132: =IFERROR((N131/$B131)*$B132,0) -> -60792.103 | ... R132: =IFERROR((Q131/$B131)*$B132,0) -> -10599.082
A133: =A106 -> 2030 | B133: =B106 -> 3900000 | I133: =IFERROR((H132/$B132)*$B133,0) -> -672096.06 | J133: =IFERROR((I132/$B132)*$B133,0) -> -774526.06 | K133: =IFERROR((J132/$B132)*$B133,0) -> -829338.6 | L133: =IFERROR((K132/$B132)*$B133,0) -> -723349.3 | M133: =IFERROR((L132/$B132)*$B133,0) -> -451017.53 | N133: =IFERROR((M132/$B132)*$B133,0) -> -228788.73 | O133: =IFERROR((N132/$B132)*$B133,0) -> -103339.4 | P133: =IFERROR((O132/$B132)*$B133,0) -> -60792.103 | ... R133: =IFERROR((Q132/$B132)*$B133,0) -> -15950.28
A134: =A107 -> 2031 | B134: =B107 -> 3900000 | J134: =IFERROR((I133/$B133)*$B134,0) -> -672096.06 | K134: =IFERROR((J133/$B133)*$B134,0) -> -774526.06 | L134: =IFERROR((K133/$B133)*$B134,0) -> -829338.6 | M134: =IFERROR((L133/$B133)*$B134,0) -> -723349.3 | N134: =IFERROR((M133/$B133)*$B134,0) -> -451017.53 | O134: =IFERROR((N133/$B133)*$B134,0) -> -228788.73 | P134: =IFERROR((O133/$B133)*$B134,0) -> -103339.4 | Q134: =IFERROR((P133/$B133)*$B134,0) -> -60792.103 | R134: =IFERROR((Q133/$B133)*$B134,0) -> -22944.112
A135: =A108 -> 2032 | B135: =B108 -> 3900000 | K135: =IFERROR((J134/$B134)*$B135,0) -> -672096.06 | L135: =IFERROR((K134/$B134)*$B135,0) -> -774526.06 | M135: =IFERROR((L134/$B134)*$B135,0) -> -829338.6 | N135: =IFERROR((M134/$B134)*$B135,0) -> -723349.3 | O135: =IFERROR((N134/$B134)*$B135,0) -> -451017.53 | P135: =IFERROR((O134/$B134)*$B135,0) -> -228788.73 | Q135: =IFERROR((P134/$B134)*$B135,0) -> -103339.4 | R135: =IFERROR((Q134/$B134)*$B135,0) -> -60792.103
A136: =A109 -> 2033 | B136: =B109 -> 3900000 | L136: =IFERROR((K135/$B135)*$B136,0) -> -672096.06 | M136: =IFERROR((L135/$B135)*$B136,0) -> -774526.06 | N136: =IFERROR((M135/$B135)*$B136,0) -> -829338.6 | O136: =IFERROR((N135/$B135)*$B136,0) -> -723349.3 | P136: =IFERROR((O135/$B135)*$B136,0) -> -451017.53 | Q136: =IFERROR((P135/$B135)*$B136,0) -> -228788.73 | R136: =IFERROR((Q135/$B135)*$B136,0) -> -103339.4
A137: =A110 -> 2034 | B137: =B110 -> 3900000 | M137: =IFERROR((L136/$B136)*$B137,0) -> -672096.06 | N137: =IFERROR((M136/$B136)*$B137,0) -> -774526.06 | O137: =IFERROR((N136/$B136)*$B137,0) -> -829338.6 | P137: =IFERROR((O136/$B136)*$B137,0) -> -723349.3 | Q137: =IFERROR((P136/$B136)*$B137,0) -> -451017.53 | R137: =IFERROR((Q136/$B136)*$B137,0) -> -228788.73
A138: =A111 -> 2035 | B138: =B111 -> 3900000 | N138: =IFERROR((M137/$B137)*$B138,0) -> -672096.06 | O138: =IFERROR((N137/$B137)*$B138,0) -> -774526.06 | P138: =IFERROR((O137/$B137)*$B138,0) -> -829338.6 | Q138: =IFERROR((P137/$B137)*$B138,0) -> -723349.3 | R138: =IFERROR((Q137/$B137)*$B138,0) -> -451017.53
A139: =A112 -> 2036 | B139: =B112 -> 3900000 | O139: =IFERROR((N138/$B138)*$B139,0) -> -672096.06 | P139: =IFERROR((O138/$B138)*$B139,0) -> -774526.06 | Q139: =IFERROR((P138/$B138)*$B139,0) -> -829338.6 | R139: =IFERROR((Q138/$B138)*$B139,0) -> -723349.3
A140: =A113 -> 2037 | B140: =B113 -> 3900000 | P140: =IFERROR((O139/$B139)*$B140,0) -> -672096.06 | Q140: =IFERROR((P139/$B139)*$B140,0) -> -774526.06 | R140: =IFERROR((Q139/$B139)*$B140,0) -> -829338.6
A141: =A114 -> 2038 | B141: =B114 -> 3900000 | Q141: =IFERROR((P140/$B140)*$B141,0) -> -672096.06 | R141: =IFERROR((Q140/$B140)*$B141,0) -> -774526.06
A142: =A115 -> 2039 | B142: =B115 -> 3900000 | R142: =IFERROR((Q141/$B141)*$B142,0) -> -672096.06
A144: Total New | D144: =SUM(D128:D142) -> -672096.06 | E144: =SUM(E128:E142) -> -1446622.1 | F144: =SUM(F128:F142) -> -2275960.7 | G144: =SUM(G128:G142) -> -2999310 | H144: =SUM(H128:H142) -> -3450327.5 | I144: =SUM(I128:I142) -> -3679116.3 | J144: =SUM(J128:J142) -> -3782455.7 | K144: =SUM(K128:K142) -> -3843247.8 | ... R144: =SUM(R128:R142) -> -3904692.3
A146: Total Existing + New + Open-ended PE | D146: =SUM(D144,D84,D60,D36) -> -672096.06 | E146: =SUM(E144,E84,E60,E36) -> -1446622.1 | F146: =SUM(F144,F84,F60,F36) -> -2275960.7 | G146: =SUM(G144,G84,G60,G36) -> -2999310 | H146: =SUM(H144,H84,H60,H36) -> -3450327.5 | I146: =SUM(I144,I84,I60,I36) -> -3679116.3 | J146: =SUM(J144,J84,J60,J36) -> -3782455.7 | K146: =SUM(K144,K84,K60,K36) -> -3843247.8 | ... R146: =SUM(R144,R84,R60,R36) -> -3904692.3
A148: Cumulative called | D148: =D146 -> -672096.06 | E148: =SUM($D$146:E147) -> -2118718.2 | F148: =SUM($D$146:F147) -> -4394678.9 | G148: =SUM($D$146:G147) -> -7393988.9 | H148: =SUM($D$146:H147) -> -10844316 | I148: =SUM($D$146:I147) -> -14523433 | J148: =SUM($D$146:J147) -> -18305888 | K148: =SUM($D$146:K147) -> -22149136 | L148: =SUM($D$146:L147) -> -26015328 | ... R148: =SUM($D$146:R147) -> -49399447
...

Sheet Evergreen only
A1: After-tax annualized investment return: | B1: 0.064
A3: Year | B3: Current Market Value | C3: New Money Ins/Outs | D3: Total Assets | E3: PE Target (%) | F3: PE Target ($) | H3: Compounding Open-ended PE Commitments | I3: Compounding Rate | K3: Yielding Open-ended PE Commitments | L3: Yield Rate | N3: New Drawdown Target Portfolio | O3: **Make sure this sums to 100%
A4: 2025 | B4: 10000000 | C4: 0 | D4: =SUM(B4:C4) -> 10000000 | E4: 1 | F4: =D4*E4 -> 10000000 | H4: 10000000 | I4: =LTCMAs!K11 -> 0.0939 | K4: 0 | L4: 0.06 | N4: Buyout | O4: 1
A5: =A4+1 -> 2026 | D5: =(D4*(1+$B$1))+C5 -> 10640000 | E5: =E4 -> 1 | F5: =D5*E5 -> 10640000 | H5: 0 | K5: 0 | N5: Growth Equity | O5: 0
A6: =A5+1 -> 2027 | D6: =(D5*(1+$B$1))+C6 -> 11320960 | E6: =E5 -> 1 | F6: =D6*E6 -> 11320960 | H6: 0 | K6: 0 | N6: Venture Capital | O6: 0
A7: =A6+1 -> 2028 | D7: =(D6*(1+$B$1))+C7 -> 12045501 | E7: =E6 -> 1 | F7: =D7*E7 -> 12045501 | H7: 0 | K7: 0 | N7: Fund of Funds | O7: 0
A8: =A7+1 -> 2029 | D8: =(D7*(1+$B$1))+C8 -> 12816414 | E8: =E7 -> 1 | F8: =D8*E8 -> 12816414 | H8: 0 | K8: 0 | N8: Secondary Funds | O8: 0
A9: =A8+1 -> 2030 | D9: =(D8*(1+$B$1))+C9 -> 13636664 | E9: =E8 -> 1 | F9: =D9*E9 -> 13636664 | H9: 0 | K9: 0 | N9: Private Credit | O9: 0
A10: =A9+1 -> 2031 | D10: =(D9*(1+$B$1))+C10 -> 14509410 | E10: =E9 -> 1 | F10: =D10*E10 -> 14509410 | H10: 0 | K10: 0 | N10: Real Estate | O10: 0
A11: =A10+1 -> 2032 | D11: =(D10*(1+$B$1))+C11 -> 15438013 | E11: =E10 -> 1 | F11: =D11*E11 -> 15438013 | H11: 0 | K11: 0
A12: =A11+1 -> 2033 | D12: =(D11*(1+$B$1))+C12 -> 16426046 | E12: =E11 -> 1 | F12: =D12*E12 -> 16426046 | H12: 0 | K12: 0 | N12: Total | O12: =SUM(O4:O10) -> 1
A13: =A12+1 -> 2034 | D13: =(D12*(1+$B$1))+C13 -> 17477313 | E13: =E12 -> 1 | F13: =D13*E13 -> 17477313 | H13: 0 | K13: 0
A14: =A13+1 -> 2035 | D14: =(D13*(1+$B$1))+C14 -> 18595861 | E14: =E13 -> 1 | F14: =D14*E14 -> 18595861 | H14: 0 | K14: 0
A15: =A14+1 -> 2036 | D15: =(D14*(1+$B$1))+C15 -> 19785996 | E15: =E14 -> 1 | F15: =D15*E15 -> 19785996 | H15: 0 | K15: 0
A16: =A15+1 -> 2037 | D16: =(D15*(1+$B$1))+C16 -> 21052299 | E16: =E15 -> 1 | F16: =D16*E16 -> 21052299 | H16: 0 | K16: 0
A17: =A16+1 -> 2038 | D17: =(D16*(1+$B$1))+C17 -> 22399646 | E17: =E16 -> 1 | F17: =D17*E17 -> 22399646 | H17: 0 | K17: 0
A18: =A17+1 -> 2039 | D18: =(D17*(1+$B$1))+C18 -> 23833224 | E18: =E17 -> 1 | F18: =D18*E18 -> 23833224 | H18: 0 | K18: 0
A27: EXISTING PORTFOLIO | B27: TO FILL IN WITH CONNECT OUTPUT | D27: Net Asset Value
A28: New Commitments | B28: Commitment | C28: % of Total Portfolio Value | D28: 2025 | E28: =D28+1 -> 2026 | F28: =E28+1 -> 2027 | G28: =F28+1 -> 2028 | H28: =G28+1 -> 2029 | I28: =H28+1 -> 2030 | J28: =I28+1 -> 2031 | K28: =J28+1 -> 2032 | L28: =K28+1 -> 2033 | ... R28: =Q28+1 -> 2039
B30: 0 | D30: 0 | E30: 0 | F30: 0 | G30: 0 | H30: 0 | I30: 0 | J30: 0 | K30: 0 | L30: 0 | M30: 0 | N30: 0 | O30: 0 | P30: 0 | Q30: 0 | R30: 0
D33: Annual Capital Called
A34: New Commitments | B34: Commitment | D34: =D$100 -> 2025 | E34: =E$100 -> 2026 | F34: =F$100 -> 2027 | G34: =G$100 -> 2028 | H34: =H$100 -> 2029 | I34: =I$100 -> 2030 | J34: =J$100 -> 2031 | K34: =K$100 -> 2032 | ... R34: =R$100 -> 2039
B36: 0 | D36: 0 | E36: 0 | F36: 0 | G36: 0 | H36: 0 | I36: 0 | J36: 0 | K36: 0 | L36: 0 | M36: 0 | N36: 0 | O36: 0 | P36: 0 | Q36: 0 | R36: 0
D38: Annual Distributions
A39: New Commitments | B39: Commitment | D39: =D$100 -> 2025 | E39: =E$100 -> 2026 | F39: =F$100 -> 2027 | G39: =G$100 -> 2028 | H39: =H$100 -> 2029 | I39: =I$100 -> 2030 | J39: =J$100 -> 2031 | K39: =K$100 -> 2032 | ... R39: =R$100 -> 2039
B41: 0 | D41: 0 | E41: 0 | F41: 0 | G41: 0 | H41: 0 | I41: 0 | J41: 0 | K41: 0 | L41: 0 | M41: 0 | N41: 0 | O41: 0 | P41: 0 | Q41: 0 | R41: 0
D43: Net Cash Flow
A44: New Commitments | B44: Commitment | D44: =D$100 -> 2025 | E44: =E$100 -> 2026 | F44: =F$100 -> 2027 | G44: =G$100 -> 2028 | H44: =H$100 -> 2029 | I44: =I$100 -> 2030 | J44: =J$100 -> 2031 | K44: =K$100 -> 2032 | ... R44: =R$100 -> 2039
B46: 0 | D46: =D36+D41 -> 0 | E46: =E36+E41 -> 0 | F46: =F36+F41 -> 0 | G46: =G36+G41 -> 0 | H46: =H36+H41 -> 0 | I46: =I36+I41 -> 0 | J46: =J36+J41 -> 0 | K46: =K36+K41 -> 0 | ... R46: =R36+R41 -> 0
A49: Net Cash Flow Cumulative | D49: =D46 -> 0 | E49: =D49+E46 -> 0 | F49: =E49+F46 -> 0 | G49: =F49+G46 -> 0 | H49: =G49+H46 -> 0 | I49: =H49+I46 -> 0 | J49: =I49+J46 -> 0 | K49: =J49+K46 -> 0 | L49: =K49+L46 -> 0 | ... R49: =Q49+R46 -> 0
A51: NEW YIELDING OPEN-ENDED PORTFOLIO | D51: Net Asset Value
A52: New Commitments | B52: Commitment | C52: % of Total Portfolio Value | D52: 2025 | E52: =D52+1 -> 2026 | F52: =E52+1 -> 2027 | G52: =F52+1 -> 2028 | H52: =G52+1 -> 2029 | I52: =H52+1 -> 2030 | J52: =I52+1 -> 2031 | K52: =J52+1 -> 2032 | L52: =K52+1 -> 2033 | ... R52: =Q52+1 -> 2039
B54: =SUM(K4:K18) -> 0 | D54: =$K4 -> 0 | E54: =K4+K5 -> 0 | F54: =K4+K6+K5 -> 0 | G54: =K4+K5+K6+K7 -> 0 | H54: =K4+K5+K6+K7+K8 -> 0 | I54: =K4+K5+K6+K7+K8+K9 -> 0 | J54: =K4+K5+K6+K7+K8+K9+K10 -> 0 | K54: =K4+K5+K6+K7+K8+K9+K10+K11 -> 0 | L54: =K4+K5+K6+K7+K8+K9+K10+K11+K12 -> 0 | M54: =K4+K5+K6+K7+K8+K9+K10+K11+K12+K13 -> 0 | N54: =K4+K5+K6+K7+K8+K9+K10+K11+K12+K13+K14 -> 0 | O54: =K4+K5+K6+K7+K8+K9+K10+K11+K12+K13+K14+K15 -> 0 | P54: =K4+K5+K6+K7+K8+K9+K10+K11+K12+K13+K14+K15+K16 -> 0 | Q54: =K4+K5+K6+K7+K8+K9+K10+K11+K12+K13+K14+K15+K16+K17 -> 0 | R54: =K4+K5+K6+K7+K8+K9+K10+K11+K12+K13+K14+K15+K16+K17+K18 -> 0
D57: Annual Capital Called
A58: New Commitments | B58: Commitment | D58: =D$100 -> 2025 | E58: =E$100 -> 2026 | F58: =F$100 -> 2027 | G58: =G$100 -> 2028 | H58: =H$100 -> 2029 | I58: =I$100 -> 2030 | J58: =J$100 -> 2031 | K58: =K$100 -> 2032 | ... R58: =R$100 -> 2039
B60: =SUM(K4:K18) -> 0 | D60: =-K4 -> 0 | E60: =-$K5 -> 0 | F60: =-$K6 -> 0 | G60: =-$K7 -> 0 | H60: =-$K8 -> 0 | I60: =-$K9 -> 0 | J60: =-$K10 -> 0 | K60: =-$K11 -> 0 | L60: =-$K12 -> 0 | M60: =-$K13 -> 0 | N60: =-$K14 -> 0 | O60: =-$K15 -> 0 | P60: =-$K16 -> 0 | Q60: =-$K17 -> 0 | R60: =-$K18 -> 0
D62: Annual Distributions
A63: New Commitments | B63: Commitment | D63: =D$100 -> 2025 | E63: =E$100 -> 2026 | F63: =F$100 -> 2027 | G63: =G$100 -> 2028 | H63: =H$100 -> 2029 | I63: =I$100 -> 2030 | J63: =J$100 -> 2031 | K63: =K$100 -> 2032 | ... R63: =R$100 -> 2039
B65: =SUM(K4:K18) -> 0 | D65: =K4*$L$4 -> 0 | E65: =SUM($K4:$K5)*$L$4 -> 0 | F65: =SUM($K4:$K6)*$L$4 -> 0 | G65: =SUM($K4:$K7)*$L$4 -> 0 | H65: =SUM($K4:$K8)*$L$4 -> 0 | I65: =SUM($K4:$K9)*$L$4 -> 0 | J65: =SUM($K4:$K10)*$L$4 -> 0 | K65: =SUM($K4:$K11)*$L$4 -> 0 | L65: =SUM($K4:$K12)*$L$4 -> 0 | M65: =SUM($K4:$K13)*$L$4 -> 0 | N65: =SUM($K4:$K14)*$L$4 -> 0 | O65: =SUM($K4:$K15)*$L$4 -> 0 | P65: =SUM($K4:$K16)*$L$4 -> 0 | Q65: =SUM($K4:$K17)*$L$4 -> 0 | R65: =SUM($K4:$K18)*$L$4 -> 0
D67: Net Cash Flow
A68: New Commitments | B68: Commitment | D68: =D$100 -> 2025 | E68: =E$100 -> 2026 | F68: =F$100 -> 2027 | G68: =G$100 -> 2028 | H68: =H$100 -> 2029 | I68: =I$100 -> 2030 | J68: =J$100 -> 2031 | K68: =K$100 -> 2032 | ... R68: =R$100 -> 2039
B70: =SUM(K4:K18) -> 0 | D70: =D60+D65 -> 0 | E70: =E60+E65 -> 0 | F70: =F60+F65 -> 0 | G70: =G60+G65 -> 0 | H70: =H60+H65 -> 0 | I70: =I60+I65 -> 0 | J70: =J60+J65 -> 0 | K70: =K60+K65 -> 0 | ... R70: =R60+R65 -> 0
A73: Net Cash Flow Cumulative | D73: =D70 -> 0 | E73: =D73+E70 -> 0 | F73: =E73+F70 -> 0 | G73: =F73+G70 -> 0 | H73: =G73+H70 -> 0 | I73: =H73+I70 -> 0 | J73: =I73+J70 -> 0 | K73: =J73+K70 -> 0 | L73: =K73+L70 -> 0 | ... R73: =Q73+R70 -> 0
A75: NEW COMPOUNDING OPEN-ENDED PORTFOLIO | D75: Net Asset Value
A76: New Commitments | B76: Commitment | C76: % of Total Portfolio Value | D76: 2025 | E76: =D76+1 -> 2026 | F76: =E76+1 -> 2027 | G76: =F76+1 -> 2028 | H76: =G76+1 -> 2029 | I76: =H76+1 -> 2030 | J76: =I76+1 -> 2031 | K76: =J76+1 -> 2032 | L76: =K76+1 -> 2033 | ... R76: =Q76+1 -> 2039
B78: =SUM(H4:H18) -> 10000000 | D78: =H4*(1+$I$4) -> 10939000 | E78: =D78*(1+$I$4)+E$84*(1+$I$4) -> 11966172 | F78: =E78*(1+$I$4)+F$84*(1+$I$4) -> 13089796 | G78: =F78*(1+$I$4)+G$84*(1+$I$4) -> 14318927 | H78: =G78*(1+$I$4)+H$84*(1+$I$4) -> 15663475 | I78: =H78*(1+$I$4)+I$84*(1+$I$4) -> 17134275 | J78: =I78*(1+$I$4)+J$84*(1+$I$4) -> 18743183 | K78: =J78*(1+$I$4)+K$84*(1+$I$4) -> 20503168 | L78: =K78*(1+$I$4)+L$84*(1+$I$4) -> 22428416 | ... R78: =Q78*(1+$I$4)+R$84*(1+$I$4) -> 38429465
D81: Annual Capital Called
A82: New Commitments | B82: Commitment | D82: =D$100 -> 2025 | E82: =E$100 -> 2026 | F82: =F$100 -> 2027 | G82: =G$100 -> 2028 | H82: =H$100 -> 2029 | I82: =I$100 -> 2030 | J82: =J$100 -> 2031 | K82: =K$100 -> 2032 | ... R82: =R$100 -> 2039
B84: =SUM(H4:H18) -> 10000000 | D84: =-$H4 -> -10000000 | E84: =-$H5 -> 0 | F84: =-$H6 -> 0 | G84: =-$H7 -> 0 | H84: =-$H8 -> 0 | I84: =-$H9 -> 0 | J84: =-$H10 -> 0 | K84: =-$H11 -> 0 | L84: =-H12 -> 0 | M84: =-H13 -> 0 | N84: =-H14 -> 0 | O84: =-H15 -> 0 | P84: =-H16 -> 0 | Q84: =-H17 -> 0 | R84: =-H18 -> 0
D86: Annual Distributions
A87: New Commitments | B87: Commitment | D87: =D$100 -> 2025 | E87: =E$100 -> 2026 | F87: =F$100 -> 2027 | G87: =G$100 -> 2028 | H87: =H$100 -> 2029 | I87: =I$100 -> 2030 | J87: =J$100 -> 2031 | K87: =K$100 -> 2032 | ... R87: =R$100 -> 2039
B89: =SUM(H4:H18) -> 10000000 | D89: 0 | E89: 0 | F89: 0 | G89: 0 | H89: 0 | I89: 0 | J89: 0 | K89: 0 | L89: 0 | M89: 0 | N89: 0 | O89: 0 | P89: 0 | Q89: 0 | R89: 0
D91: Net Cash Flow
A92: New Commitments | B92: Commitment | D92: =D$100 -> 2025 | E92: =E$100 -> 2026 | F92: =F$100 -> 2027 | G92: =G$100 -> 2028 | H92: =H$100 -> 2029 | I92: =I$100 -> 2030 | J92: =J$100 -> 2031 | K92: =K$100 -> 2032 | ... R92: =R$100 -> 2039
B94: =SUM(H4:H18) -> 10000000 | D94: =D84+D89 -> -10000000 | E94: =E84+E89 -> 0 | F94: =F84+F89 -> 0 | G94: =G84+G89 -> 0 | H94: =H84+H89 -> 0 | I94: =I84+I89 -> 0 | J94: =J84+J89 -> 0 | K94: =K84+K89 -> 0 | ... R94: =R84+R89 -> 0
A97: Net Cash Flow Cumulative | D97: =SUM($D$94:D94) -> -10000000 | E97: =SUM($D$94:E94) -> -10000000 | F97: =SUM($D$94:F94) -> -10000000 | G97: =SUM($D$94:G94) -> -10000000 | H97: =SUM($D$94:H94) -> -10000000 | I97: =SUM($D$94:I94) -> -10000000 | J97: =SUM($D$94:J94) -> -10000000 | K97: =SUM($D$94:K94) -> -10000000 | ... R97: =SUM($D$94:R94) -> -10000000
A99: NEW DRAWDOWN PORTFOLIO | D99: Net Asset Value
A100: New Commitments | B100: Commitment | C100: % of Total Portfolio Value | D100: 2025 | E100: =D100+1 -> 2026 | F100: =E100+1 -> 2027 | G100: =F100+1 -> 2028 | H100: =G100+1 -> 2029 | I100: =H100+1 -> 2030 | J100: =I100+1 -> 2031 | K100: =J100+1 -> 2032 | L100: =K100+1 -> 2033 | ... R100: =Q100+1 -> 2039
A101: 2025 | C101: =B101/$D4 -> 0 | D101: =VLOOKUP(D$100,'Aggregated Median CA data'!$D$126:$M$140,5,0)*$B101 -> 0 | E101: =VLOOKUP(E$100,'Aggregated Median CA data'!$D$126:$M$140,5,0)*$B101 -> 0 | F101: =VLOOKUP(F$100,'Aggregated Median CA data'!$D$126:$M$140,5,0)*$B101 -> 0 | G101: =VLOOKUP(G$100,'Aggregated Median CA data'!$D$126:$M$140,5,0)*$B101 -> 0 | H101: =VLOOKUP(H$100,'Aggregated Median CA data'!$D$126:$M$140,5,0)*$B101 -> 0 | I101: =VLOOKUP(I$100,'Aggregated Median CA data'!$D$126:$M$140,5,0)*$B101 -> 0 | J101: =VLOOKUP(J$100,'Aggregated Median CA data'!$D$126:$M$140,5,0)*$B101 -> 0 | K101: =VLOOKUP(K$100,'Aggregated Median CA data'!$D$126:$M$140,5,0)*$B101 -> 0 | ... R101: =VLOOKUP(R$100,'Aggregated Median CA data'!$D$126:$M$140,5,0)*$B101 -> 0
A102: =A101+1 -> 2026 | C102: =B102/$D5 -> 0 | E102: =IF($B102=0,0,(D101/$B101)*$B102) -> 0 | F102: =IF($B102=0,0,(E101/$B101)*$B102) -> 0 | G102: =IF($B102=0,0,(F101/$B101)*$B102) -> 0 | H102: =IF($B102=0,0,(G101/$B101)*$B102) -> 0 | I102: =IF($B102=0,0,(H101/$B101)*$B102) -> 0 | J102: =IF($B102=0,0,(I101/$B101)*$B102) -> 0 | K102: =IF($B102=0,0,(J101/$B101)*$B102) -> 0 | L102: =IF($B102=0,0,(K101/$B101)*$B102) -> 0 | ... R102: =IF($B102=0,0,(Q101/$B101)*$B102) -> 0
A103: =A102+1 -> 2027 | C103: =B103/$D6 -> 0 | F103: =IF($B103=0,0,(E102/$B102)*$B103) -> 0 | G103: =IF($B103=0,0,(F102/$B102)*$B103) -> 0 | H103: =IF($B103=0,0,(G102/$B102)*$B103) -> 0 | I103: =IF($B103=0,0,(H102/$B102)*$B103) -> 0 | J103: =IF($B103=0,0,(I102/$B102)*$B103) -> 0 | K103: =IF($B103=0,0,(J102/$B102)*$B103) -> 0 | L103: =IF($B103=0,0,(K102/$B102)*$B103) -> 0 | M103: =IF($B103=0,0,(L102/$B102)*$B103) -> 0 | ... R103: =IF($B103=0,0,(Q102/$B102)*$B103) -> 0
A104: =A103+1 -> 2028 | C104: =B104/$D7 -> 0 | G104: =IF($B104=0,0,(F103/$B103)*$B104) -> 0 | H104: =IF($B104=0,0,(G103/$B103)*$B104) -> 0 | I104: =IF($B104=0,0,(H103/$B103)*$B104) -> 0 | J104: =IF($B104=0,0,(I103/$B103)*$B104) -> 0 | K104: =IF($B104=0,0,(J103/$B103)*$B104) -> 0 | L104: =IF($B104=0,0,(K103/$B103)*$B104) -> 0 | M104: =IF($B104=0,0,(L103/$B103)*$B104) -> 0 | N104: =IF($B104=0,0,(M103/$B103)*$B104) -> 0 | ... R104: =IF($B104=0,0,(Q103/$B103)*$B104) -> 0
A105: =A104+1 -> 2029 | C105: =B105/$D8 -> 0 | H105: =IF($B105=0,0,(G104/$B104)*$B105) -> 0 | I105: =IF($B105=0,0,(H104/$B104)*$B105) -> 0 | J105: =IF($B105=0,0,(I104/$B104)*$B105) -> 0 | K105: =IF($B105=0,0,(J104/$B104)*$B105) -> 0 | L105: =IF($B105=0,0,(K104/$B104)*$B105) -> 0 | M105: =IF($B105=0,0,(L104/$B104)*$B105) -> 0 | N105: =IF($B105=0,0,(M104/$B104)*$B105) -> 0 | O105: =IF($B105=0,0,(N104/$B104)*$B105) -> 0 | ... R105: =IF($B105=0,0,(Q104/$B104)*$B105) -> 0
A106: =A105+1 -> 2030 | C106: =B106/$D9 -> 0 | I106: =IF($B106=0,0,(H105/$B105)*$B106) -> 0 | J106: =IF($B106=0,0,(I105/$B105)*$B106) -> 0 | K106: =IF($B106=0,0,(J105/$B105)*$B106) -> 0 | L106: =IF($B106=0,0,(K105/$B105)*$B106) -> 0 | M106: =IF($B106=0,0,(L105/$B105)*$B106) -> 0 | N106: =IF($B106=0,0,(M105/$B105)*$B106) -> 0 | O106: =IF($B106=0,0,(N105/$B105)*$B106) -> 0 | P106: =IF($B106=0,0,(O105/$B105)*$B106) -> 0 | ... R106: =IF($B106=0,0,(Q105/$B105)*$B106) -> 0
A107: =A106+1 -> 2031 | C107: =B107/$D10 -> 0 | J107: =IF($B107=0,0,(I106/$B106)*$B107) -> 0 | K107: =IF($B107=0,0,(J106/$B106)*$B107) -> 0 | L107: =IF($B107=0,0,(K106/$B106)*$B107) -> 0 | M107: =IF($B107=0,0,(L106/$B106)*$B107) -> 0 | N107: =IF($B107=0,0,(M106/$B106)*$B107) -> 0 | O107: =IF($B107=0,0,(N106/$B106)*$B107) -> 0 | P107: =IF($B107=0,0,(O106/$B106)*$B107) -> 0 | Q107: =IF($B107=0,0,(P106/$B106)*$B107) -> 0 | R107: =IF($B107=0,0,(Q106/$B106)*$B107) -> 0
A108: =A107+1 -> 2032 | C108: =B108/$D11 -> 0 | K108: =IF($B108=0,0,(J107/$B107)*$B108) -> 0 | L108: =IF($B108=0,0,(K107/$B107)*$B108) -> 0 | M108: =IF($B108=0,0,(L107/$B107)*$B108) -> 0 | N108: =IF($B108=0,0,(M107/$B107)*$B108) -> 0 | O108: =IF($B108=0,0,(N107/$B107)*$B108) -> 0 | P108: =IF($B108=0,0,(O107/$B107)*$B108) -> 0 | Q108: =IF($B108=0,0,(P107/$B107)*$B108) -> 0 | R108: =IF($B108=0,0,(Q107/$B107)*$B108) -> 0
A109: =A108+1 -> 2033 | C109: =B109/$D12 -> 0 | L109: =IF($B109=0,0,(K108/$B108)*$B109) -> 0 | M109: =IF($B109=0,0,(L108/$B108)*$B109) -> 0 | N109: =IF($B109=0,0,(M108/$B108)*$B109) -> 0 | O109: =IF($B109=0,0,(N108/$B108)*$B109) -> 0 | P109: =IF($B109=0,0,(O108/$B108)*$B109) -> 0 | Q109: =IF($B109=0,0,(P108/$B108)*$B109) -> 0 | R109: =IF($B109=0,0,(Q108/$B108)*$B109) -> 0
A110: =A109+1 -> 2034 | C110: =B110/$D13 -> 0 | M110: =IF($B110=0,0,(L109/$B109)*$B110) -> 0 | N110: =IF($B110=0,0,(M109/$B109)*$B110) -> 0 | O110: =IF($B110=0,0,(N109/$B109)*$B110) -> 0 | P110: =IF($B110=0,0,(O109/$B109)*$B110) -> 0 | Q110: =IF($B110=0,0,(P109/$B109)*$B110) -> 0 | R110: =IF($B110=0,0,(Q109/$B109)*$B110) -> 0
A111: =A110+1 -> 2035 | C111: =B111/$D14 -> 0 | N111: =IF($B111=0,0,(M110/$B110)*$B111) -> 0 | O111: =IF($B111=0,0,(N110/$B110)*$B111) -> 0 | P111: =IF($B111=0,0,(O110/$B110)*$B111) -> 0 | Q111: =IF($B111=0,0,(P110/$B110)*$B111) -> 0 | R111: =IF($B111=0,0,(Q110/$B110)*$B111) -> 0
A112: =A111+1 -> 2036 | C112: =B112/$D15 -> 0 | O112: =IF($B112=0,0,(N111/$B111)*$B112) -> 0 | P112: =IF($B112=0,0,(O111/$B111)*$B112) -> 0 | Q112: =IF($B112=0,0,(P111/$B111)*$B112) -> 0 | R112: =IF($B112=0,0,(Q111/$B111)*$B112) -> 0
A113: =A112+1 -> 2037 | C113: =B113/$D16 -> 0 | P113: =IF($B113=0,0,(O112/$B112)*$B113) -> 0 | Q113: =IF($B113=0,0,(P112/$B112)*$B113) -> 0 | R113: =IF($B113=0,0,(Q112/$B112)*$B113) -> 0
A114: =A113+1 -> 2038 | C114: =B114/$D17 -> 0 | Q114: =IF($B114=0,0,(P113/$B113)*$B114) -> 0 | R114: =IF($B114=0,0,(Q113/$B113)*$B114) -> 0
A115: =A114+1 -> 2039 | C115: =B115/$D18 -> 0 | R115: =IF($B115=0,0,(Q114/$B114)*$B115) -> 0
A117: Total New | D117: =SUM(D101:D115) -> 0 | E117: =SUM(E101:E115) -> 0 | F117: =SUM(F101:F115) -> 0 | G117: =SUM(G101:G115) -> 0 | H117: =SUM(H101:H115) -> 0 | I117: =SUM(I101:I115) -> 0 | J117: =SUM(J101:J115) -> 0 | K117: =SUM(K101:K115) -> 0 | ... R117: =SUM(R101:R115) -> 0
A119: Total New + Open-ended PE | D119: =SUM(D117,D78,D54,D30) -> 10939000 | E119: =SUM(E117,E78,E54,E30) -> 11966172 | F119: =SUM(F117,F78,F54,F30) -> 13089796 | G119: =SUM(G117,G78,G54,G30) -> 14318927 | H119: =SUM(H117,H78,H54,H30) -> 15663475 | I119: =SUM(I117,I78,I54,I30) -> 17134275 | J119: =SUM(J117,J78,J54,J30) -> 18743183 | K119: =SUM(K117,K78,K54,K30) -> 20503168 | ... R119: =SUM(R117,R78,R54,R30) -> 38429465
A121: Total Mandate MV | D121: =$D$4 -> 10000000 | E121: =$D$5 -> 10640000 | F121: =$D$6 -> 11320960 | G121: =$D$7 -> 12045501 | H121: =$D$8 -> 12816414 | I121: =$D$9 -> 13636664 | J121: =$D$10 -> 14509410 | K121: =$D$11 -> 15438013 | L121: =$D$12 -> 16426046 | M121: =$D$13 -> 17477313 | N121: =$D$14 -> 18595861 | O121: =$D$15 -> 19785996 | P121: =$D$16 -> 21052299 | Q121: =$D$17 -> 22399646 | R121: =$D$18 -> 23833224
A122: % | D122: =D119/D121 -> 1.0939 | E122: =E119/E121 -> 1.1246402 | F122: =F119/F121 -> 1.1562443 | G122: =G119/G121 -> 1.1887365 | H122: =H119/H121 -> 1.2221418 | I122: =I119/I121 -> 1.2564858 | J122: =J119/J121 -> 1.291795 | K122: =K119/K121 -> 1.3280963 | ... R122: =R119/R121 -> 1.6124325
C123: Portfolio Value | D123: =D121/1000000 -> 10 | E123: =E121/1000000 -> 10.64 | F123: =F121/1000000 -> 11.32096 | G123: =G121/1000000 -> 12.045501 | H123: =H121/1000000 -> 12.816414 | I123: =I121/1000000 -> 13.636664 | J123: =J121/1000000 -> 14.50941 | K123: =K121/1000000 -> 15.438013 | ... R123: =R121/1000000 -> 23.833224
C124: Commitments | D124: =$B$101/1000000 -> 0 | E124: =$B$102/1000000 -> 0 | F124: =$B$103/1000000 -> 0 | G124: =$B$104/1000000 -> 0 | H124: =$B$105/1000000 -> 0 | I124: =$B$106/1000000 -> 0 | J124: =$B$107/1000000 -> 0 | K124: =$B$108/1000000 -> 0 | L124: =$B$109/1000000 -> 0 | M124: =$B$110/1000000 -> 0 | N124: =$B$111/1000000 -> 0 | O124: =$B$112/1000000 -> 0 | P124: =$B$113/1000000 -> 0 | Q124: =$B$114/1000000 -> 0 | R124: =$B$115/1000000 -> 0
C125: PI Portfolio NAV | D125: =D119/1000000 -> 10.939 | E125: =E119/1000000 -> 11.966172 | F125: =F119/1000000 -> 13.089796 | G125: =G119/1000000 -> 14.318927 | H125: =H119/1000000 -> 15.663475 | I125: =I119/1000000 -> 17.134275 | J125: =J119/1000000 -> 18.743183 | K125: =K119/1000000 -> 20.503168 | ... R125: =R119/1000000 -> 38.429465
D126: Annual Capital Called
A127: New Commitments | B127: Commitment | D127: =D$100 -> 2025 | E127: =E$100 -> 2026 | F127: =F$100 -> 2027 | G127: =G$100 -> 2028 | H127: =H$100 -> 2029 | I127: =I$100 -> 2030 | J127: =J$100 -> 2031 | K127: =K$100 -> 2032 | ... R127: =R$100 -> 2039
A128: =A101 -> 2025 | B128: =B101 -> 0 | D128: =VLOOKUP(D$100,'Aggregated Median CA data'!$D$126:$M$140,7,0)*$B128 -> 0 | E128: =VLOOKUP(E$100,'Aggregated Median CA data'!$D$126:$M$140,7,0)*$B128 -> 0 | F128: =VLOOKUP(F$100,'Aggregated Median CA data'!$D$126:$M$140,7,0)*$B128 -> 0 | G128: =VLOOKUP(G$100,'Aggregated Median CA data'!$D$126:$M$140,7,0)*$B128 -> 0 | H128: =VLOOKUP(H$100,'Aggregated Median CA data'!$D$126:$M$140,7,0)*$B128 -> 0 | I128: =VLOOKUP(I$100,'Aggregated Median CA data'!$D$126:$M$140,7,0)*$B128 -> 0 | J128: =VLOOKUP(J$100,'Aggregated Median CA data'!$D$126:$M$140,7,0)*$B128 -> 0 | K128: =VLOOKUP(K$100,'Aggregated Median CA data'!$D$126:$M$140,7,0)*$B128 -> 0 | ... R128: =VLOOKUP(R$100,'Aggregated Median CA data'!$D$126:$M$140,7,0)*$B128 -> 0
A129: =A102 -> 2026 | B129: =B102 -> 0 | E129: =IFERROR((D128/$B128)*$B129,0) -> 0 | F129: =IFERROR((E128/$B128)*$B129,0) -> 0 | G129: =IFERROR((F128/$B128)*$B129,0) -> 0 | H129: =IFERROR((G128/$B128)*$B129,0) -> 0 | I129: =IFERROR((H128/$B128)*$B129,0) -> 0 | J129: =IFERROR((I128/$B128)*$B129,0) -> 0 | K129: =IFERROR((J128/$B128)*$B129,0) -> 0 | L129: =IFERROR((K128/$B128)*$B129,0) -> 0 | ... R129: =IFERROR((Q128/$B128)*$B129,0) -> 0
A130: =A103 -> 2027 | B130: =B103 -> 0 | F130: =IFERROR((E129/$B129)*$B130,0) -> 0 | G130: =IFERROR((F129/$B129)*$B130,0) -> 0 | H130: =IFERROR((G129/$B129)*$B130,0) -> 0 | I130: =IFERROR((H129/$B129)*$B130,0) -> 0 | J130: =IFERROR((I129/$B129)*$B130,0) -> 0 | K130: =IFERROR((J129/$B129)*$B130,0) -> 0 | L130: =IFERROR((K129/$B129)*$B130,0) -> 0 | M130: =IFERROR((L129/$B129)*$B130,0) -> 0 | ... R130: =IFERROR((Q129/$B129)*$B130,0) -> 0
A131: =A104 -> 2028 | B131: =B104 -> 0 | G131: =IFERROR((F130/$B130)*$B131,0) -> 0 | H131: =IFERROR((G130/$B130)*$B131,0) -> 0 | I131: =IFERROR((H130/$B130)*$B131,0) -> 0 | J131: =IFERROR((I130/$B130)*$B131,0) -> 0 | K131: =IFERROR((J130/$B130)*$B131,0) -> 0 | L131: =IFERROR((K130/$B130)*$B131,0) -> 0 | M131: =IFERROR((L130/$B130)*$B131,0) -> 0 | N131: =IFERROR((M130/$B130)*$B131,0) -> 0 | ... R131: =IFERROR((Q130/$B130)*$B131,0) -> 0
A132: =A105 -> 2029 | B132: =B105 -> 0 | H132: =IFERROR((G131/$B131)*$B132,0) -> 0 | I132: =IFERROR((H131/$B131)*$B132,0) -> 0 | J132: =IFERROR((I131/$B131)*$B132,0) -> 0 | K132: =IFERROR((J131/$B131)*$B132,0) -> 0 | L132: =IFERROR((K131/$B131)*$B132,0) -> 0 | M132: =IFERROR((L131/$B131)*$B132,0) -> 0 | N132: =IFERROR((M131/$B131)*$B132,0) -> 0 | O132: =IFERROR((N131/$B131)*$B132,0) -> 0 | ... R132: =IFERROR((Q131/$B131)*$B132,0) -> 0
A133: =A106 -> 2030 | B133: =B106 -> 0 | I133: =IFERROR((H132/$B132)*$B133,0) -> 0 | J133: =IFERROR((I132/$B132)*$B133,0) -> 0 | K133: =IFERROR((J132/$B132)*$B133,0) -> 0 | L133: =IFERROR((K132/$B132)*$B133,0) -> 0 | M133: =IFERROR((L132/$B132)*$B133,0) -> 0 | N133: =IFERROR((M132/$B132)*$B133,0) -> 0 | O133: =IFERROR((N132/$B132)*$B133,0) -> 0 | P133: =IFERROR((O132/$B132)*$B133,0) -> 0 | ... R133: =IFERROR((Q132/$B132)*$B133,0) -> 0
A134: =A107 -> 2031 | B134: =B107 -> 0 | J134: =IFERROR((I133/$B133)*$B134,0) -> 0 | K134: =IFERROR((J133/$B133)*$B134,0) -> 0 | L134: =IFERROR((K133/$B133)*$B134,0) -> 0 | M134: =IFERROR((L133/$B133)*$B134,0) -> 0 | N134: =IFERROR((M133/$B133)*$B134,0) -> 0 | O134: =IFERROR((N133/$B133)*$B134,0) -> 0 | P134: =IFERROR((O133/$B133)*$B134,0) -> 0 | Q134: =IFERROR((P133/$B133)*$B134,0) -> 0 | R134: =IFERROR((Q133/$B133)*$B134,0) -> 0
A135: =A108 -> 2032 | B135: =B108 -> 0 | K135: =IFERROR((J134/$B134)*$B135,0) -> 0 | L135: =IFERROR((K134/$B134)*$B135,0) -> 0 | M135: =IFERROR((L134/$B134)*$B135,0) -> 0 | N135: =IFERROR((M134/$B134)*$B135,0) -> 0 | O135: =IFERROR((N134/$B134)*$B135,0) -> 0 | P135: =IFERROR((O134/$B134)*$B135,0) -> 0 | Q135: =IFERROR((P134/$B134)*$B135,0) -> 0 | R135: =IFERROR((Q134/$B134)*$B135,0) -> 0
A136: =A109 -> 2033 | B136: =B109 -> 0 | L136: =IFERROR((K135/$B135)*$B136,0) -> 0 | M136: =IFERROR((L135/$B135)*$B136,0) -> 0 | N136: =IFERROR((M135/$B135)*$B136,0) -> 0 | O136: =IFERROR((N135/$B135)*$B136,0) -> 0 | P136: =IFERROR((O135/$B135)*$B136,0) -> 0 | Q136: =IFERROR((P135/$B135)*$B136,0) -> 0 | R136: =IFERROR((Q135/$B135)*$B136,0) -> 0
A137: =A110 -> 2034 | B137: =B110 -> 0 | M137: =IFERROR((L136/$B136)*$B137,0) -> 0 | N137: =IFERROR((M136/$B136)*$B137,0) -> 0 | O137: =IFERROR((N136/$B136)*$B137,0) -> 0 | P137: =IFERROR((O136/$B136)*$B137,0) -> 0 | Q137: =IFERROR((P136/$B136)*$B137,0) -> 0 | R137: =IFERROR((Q136/$B136)*$B137,0) -> 0
A138: =A111 -> 2035 | B138: =B111 -> 0 | N138: =IFERROR((M137/$B137)*$B138,0) -> 0 | O138: =IFERROR((N137/$B137)*$B138,0) -> 0 | P138: =IFERROR((O137/$B137)*$B138,0) -> 0 | Q138: =IFERROR((P137/$B137)*$B138,0) -> 0 | R138: =IFERROR((Q137/$B137)*$B138,0) -> 0
A139: =A112 -> 2036 | B139: =B112 -> 0 | O139: =IFERROR((N138/$B138)*$B139,0) -> 0 | P139: =IFERROR((O138/$B138)*$B139,0) -> 0 | Q139: =IFERROR((P138/$B138)*$B139,0) -> 0 | R139: =IFERROR((Q138/$B138)*$B139,0) -> 0
A140: =A113 -> 2037 | B140: =B113 -> 0 | P140: =IFERROR((O139/$B139)*$B140,0) -> 0 | Q140: =IFERROR((P139/$B139)*$B140,0) -> 0 | R140: =IFERROR((Q139/$B139)*$B140,0) -> 0
A141: =A114 -> 2038 | B141: =B114 -> 0 | Q141: =IFERROR((P140/$B140)*$B141,0) -> 0 | R141: =IFERROR((Q140/$B140)*$B141,0) -> 0
A142: =A115 -> 2039 | B142: =B115 -> 0 | R142: =IFERROR((Q141/$B141)*$B142,0) -> 0
A144: Total New | D144: =SUM(D128:D142) -> 0 | E144: =SUM(E128:E142) -> 0 | F144: =SUM(F128:F142) -> 0 | G144: =SUM(G128:G142) -> 0 | H144: =SUM(H128:H142) -> 0 | I144: =SUM(I128:I142) -> 0 | J144: =SUM(J128:J142) -> 0 | K144: =SUM(K128:K142) -> 0 | ... R144: =SUM(R128:R142) -> 0
A146: Total Existing + New + Open-ended PE | D146: =SUM(D144,D84,D60,D36) -> -10000000 | E146: =SUM(E144,E84,E60,E36) -> 0 | F146: =SUM(F144,F84,F60,F36) -> 0 | G146: =SUM(G144,G84,G60,G36) -> 0 | H146: =SUM(H144,H84,H60,H36) -> 0 | I146: =SUM(I144,I84,I60,I36) -> 0 | J146: =SUM(J144,J84,J60,J36) -> 0 | K146: =SUM(K144,K84,K60,K36) -> 0 | ... R146: =SUM(R144,R84,R60,R36) -> 0
A148: Cumulative called | D148: =D146 -> -10000000 | E148: =SUM($D$146:E147) -> -10000000 | F148: =SUM($D$146:F147) -> -10000000 | G148: =SUM($D$146:G147) -> -10000000 | H148: =SUM($D$146:H147) -> -10000000 | I148: =SUM($D$146:I147) -> -10000000 | J148: =SUM($D$146:J147) -> -10000000 | K148: =SUM($D$146:K147) -> -10000000 | L148: =SUM($D$146:L147) -> -10000000 | ... R148: =SUM($D$146:R147) -> -10000000
...

Sheet Drawdown+reinvestment
A1: After-tax annualized investment return: | B1: 0.061
A3: Year | B3: Current Market Value | C3: New Money Ins/Outs | D3: Total Assets | E3: PE Target (%) | F3: PE Target ($) | H3: Compounding Open-ended PE Commitments | I3: Compounding Rate | K3: Yielding Open-ended PE Commitments | L3: Yield Rate | N3: New Drawdown Target Portfolio | O3: **Make sure this sums to 100%
A4: 2024 | B4: 10000000 | C4: 0 | D4: =SUM(B4:C4) -> 10000000 | E4: 1 | F4: =D4*E4 -> 10000000 | H4: 0 | I4: 0.1 | K4: 0 | L4: 0.061 | N4: Buyout | O4: 1
A5: =A4+1 -> 2025 | D5: =(D4*(1+$B$1))+C5 -> 10610000 | E5: =E4 -> 1 | F5: =D5*E5 -> 10610000 | H5: 0 | K5: 0 | N5: Growth Equity | O5: 0
A6: =A5+1 -> 2026 | D6: =(D5*(1+$B$1))+C6 -> 11257210 | E6: =E5 -> 1 | F6: =D6*E6 -> 11257210 | H6: 0 | K6: 0 | N6: Venture Capital | O6: 0
A7: =A6+1 -> 2027 | D7: =(D6*(1+$B$1))+C7 -> 11943900 | E7: =E6 -> 1 | F7: =D7*E7 -> 11943900 | H7: 0 | K7: 0 | N7: Fund of Funds | O7: 0
A8: =A7+1 -> 2028 | D8: =(D7*(1+$B$1))+C8 -> 12672478 | E8: =E7 -> 1 | F8: =D8*E8 -> 12672478 | H8: 0 | K8: 0 | N8: Secondary Funds | O8: 0
A9: =A8+1 -> 2029 | D9: =(D8*(1+$B$1))+C9 -> 13445499 | E9: =E8 -> 1 | F9: =D9*E9 -> 13445499 | H9: 0 | K9: 0 | N9: Private Credit | O9: 0
A10: =A9+1 -> 2030 | D10: =(D9*(1+$B$1))+C10 -> 14265674 | E10: =E9 -> 1 | F10: =D10*E10 -> 14265674 | H10: 0 | K10: 0 | N10: Real Estate | O10: 0
A11: =A10+1 -> 2031 | D11: =(D10*(1+$B$1))+C11 -> 15135880 | E11: =E10 -> 1 | F11: =D11*E11 -> 15135880 | H11: 0 | K11: 0
A12: =A11+1 -> 2032 | D12: =(D11*(1+$B$1))+C12 -> 16059169 | E12: =E11 -> 1 | F12: =D12*E12 -> 16059169 | H12: 0 | K12: 0 | N12: Total | O12: =SUM(O4:O10) -> 1
A13: =A12+1 -> 2033 | D13: =(D12*(1+$B$1))+C13 -> 17038778 | E13: =E12 -> 1 | F13: =D13*E13 -> 17038778 | H13: 0 | K13: 0
A14: =A13+1 -> 2034 | D14: =(D13*(1+$B$1))+C14 -> 18078144 | E14: =E13 -> 1 | F14: =D14*E14 -> 18078144 | H14: 0 | K14: 0
A15: =A14+1 -> 2035 | D15: =(D14*(1+$B$1))+C15 -> 19180911 | E15: =E14 -> 1 | F15: =D15*E15 -> 19180911 | H15: 0 | K15: 0
A16: =A15+1 -> 2036 | D16: =(D15*(1+$B$1))+C16 -> 20350946 | E16: =E15 -> 1 | F16: =D16*E16 -> 20350946 | H16: 0 | K16: 0
A17: =A16+1 -> 2037 | D17: =(D16*(1+$B$1))+C17 -> 21592354 | E17: =E16 -> 1 | F17: =D17*E17 -> 21592354 | H17: 0 | K17: 0
A18: =A17+1 -> 2038 | D18: =(D17*(1+$B$1))+C18 -> 22909488 | E18: =E17 -> 1 | F18: =D18*E18 -> 22909488 | H18: 0 | K18: 0
A27: EXISTING PORTFOLIO | B27: TO FILL IN WITH CONNECT OUTPUT | D27: Net Asset Value
A28: New Commitments | B28: Commitment | C28: % of Total Portfolio Value | D28: 2025 | E28: =D28+1 -> 2026 | F28: =E28+1 -> 2027 | G28: =F28+1 -> 2028 | H28: =G28+1 -> 2029 | I28: =H28+1 -> 2030 | J28: =I28+1 -> 2031 | K28: =J28+1 -> 2032 | L28: =K28+1 -> 2033 | ... R28: =Q28+1 -> 2039
B30: 0 | D30: 0 | E30: 0 | F30: 0 | G30: 0 | H30: 0 | I30: 0 | J30: 0 | K30: 0 | L30: 0 | M30: 0 | N30: 0 | O30: 0 | P30: 0 | Q30: 0 | R30: 0
D33: Annual Capital Called
A34: New Commitments | B34: Commitment | D34: =D$100 -> 2025 | E34: =E$100 -> 2026 | F34: =F$100 -> 2027 | G34: =G$100 -> 2028 | H34: =H$100 -> 2029 | I34: =I$100 -> 2030 | J34: =J$100 -> 2031 | K34: =K$100 -> 2032 | ... R34: =R$100 -> 2039
B36: 0 | D36: 0 | E36: 0 | F36: 0 | G36: 0 | H36: 0 | I36: 0 | J36: 0 | K36: 0 | L36: 0 | M36: 0 | N36: 0 | O36: 0 | P36: 0 | Q36: 0 | R36: 0
D38: Annual Distributions
A39: New Commitments | B39: Commitment | D39: =D$100 -> 2025 | E39: =E$100 -> 2026 | F39: =F$100 -> 2027 | G39: =G$100 -> 2028 | H39: =H$100 -> 2029 | I39: =I$100 -> 2030 | J39: =J$100 -> 2031 | K39: =K$100 -> 2032 | ... R39: =R$100 -> 2039
B41: 0 | D41: 0 | E41: 0 | F41: 0 | G41: 0 | H41: 0 | I41: 0 | J41: 0 | K41: 0 | L41: 0 | M41: 0 | N41: 0 | O41: 0 | P41: 0 | Q41: 0 | R41: 0
D43: Net Cash Flow
A44: New Commitments | B44: Commitment | D44: =D$100 -> 2025 | E44: =E$100 -> 2026 | F44: =F$100 -> 2027 | G44: =G$100 -> 2028 | H44: =H$100 -> 2029 | I44: =I$100 -> 2030 | J44: =J$100 -> 2031 | K44: =K$100 -> 2032 | ... R44: =R$100 -> 2039
B46: 0 | D46: =D36+D41 -> 0 | E46: =E36+E41 -> 0 | F46: =F36+F41 -> 0 | G46: =G36+G41 -> 0 | H46: =H36+H41 -> 0 | I46: =I36+I41 -> 0 | J46: =J36+J41 -> 0 | K46: =K36+K41 -> 0 | ... R46: =R36+R41 -> 0
A49: Net Cash Flow Cumulative | D49: =D46 -> 0 | E49: =D49+E46 -> 0 | F49: =E49+F46 -> 0 | G49: =F49+G46 -> 0 | H49: =G49+H46 -> 0 | I49: =H49+I46 -> 0 | J49: =I49+J46 -> 0 | K49: =J49+K46 -> 0 | L49: =K49+L46 -> 0 | ... R49: =Q49+R46 -> 0
A51: Cash invested | D51: Net Asset Value
A52: New Commitments | B52: Commitment | C52: % of Total Portfolio Value | D52: 2025 | E52: =D52+1 -> 2026 | F52: =E52+1 -> 2027 | G52: =F52+1 -> 2028 | H52: =G52+1 -> 2029 | I52: =H52+1 -> 2030 | J52: =I52+1 -> 2031 | K52: =J52+1 -> 2032 | L52: =K52+1 -> 2033 | ... R52: =Q52+1 -> 2039
B54: =SUM(K4:K18) -> 0 | C54: =B4 -> 10000000 | D54: =(C54+D146+D170)*(1+LTCMAs!$K$10) -> 9980857.2 | E54: =(D54+E146+E170)*(1+LTCMAs!$K$10) -> 9134842.1 | F54: =(E54+F146+F170)*(1+LTCMAs!$K$10) -> 7430230 | G54: =(F54+G146+G170)*(1+LTCMAs!$K$10) -> 5189220.4 | H54: =(G54+H146+H170)*(1+LTCMAs!$K$10) -> 3007663.6 | I54: =(H54+I146+I170)*(1+LTCMAs!$K$10) -> 1193878.3 | J54: =(I54+J146+J170)*(1+LTCMAs!$K$10) -> 181040.82 | K54: =(J54+K146+K170)*(1+LTCMAs!$K$10) -> 43067.34 | ... R54: =(Q54+R146+R170)*(1+LTCMAs!$K$10) -> 16317597
D57: Annual Capital Called
A58: New Commitments | B58: Commitment | D58: =D$100 -> 2025 | E58: =E$100 -> 2026 | F58: =F$100 -> 2027 | G58: =G$100 -> 2028 | H58: =H$100 -> 2029 | I58: =I$100 -> 2030 | J58: =J$100 -> 2031 | K58: =K$100 -> 2032 | ... R58: =R$100 -> 2039
B60: =SUM(K4:K18) -> 0 | D60: =-K4 -> 0 | E60: =-$K5 -> 0 | F60: =-$K6 -> 0 | G60: =-$K7 -> 0 | H60: =-$K8 -> 0 | I60: =-$K9 -> 0 | J60: =-$K10 -> 0 | K60: =-$K11 -> 0 | L60: =-$K12 -> 0 | M60: =-$K13 -> 0 | N60: =-$K14 -> 0 | O60: =-$K15 -> 0 | P60: =-$K16 -> 0 | Q60: =-$K17 -> 0 | R60: =-$K18 -> 0
D62: Annual Distributions
A63: New Commitments | B63: Commitment | D63: =D$100 -> 2025 | E63: =E$100 -> 2026 | F63: =F$100 -> 2027 | G63: =G$100 -> 2028 | H63: =H$100 -> 2029 | I63: =I$100 -> 2030 | J63: =J$100 -> 2031 | K63: =K$100 -> 2032 | ... R63: =R$100 -> 2039
B65: =SUM(K4:K18) -> 0 | D65: =K4*$L$4 -> 0 | E65: =SUM($K4:$K5)*$L$4 -> 0 | F65: =SUM($K4:$K6)*$L$4 -> 0 | G65: =SUM($K4:$K7)*$L$4 -> 0 | H65: =SUM($K4:$K8)*$L$4 -> 0 | I65: =SUM($K4:$K9)*$L$4 -> 0 | J65: =SUM($K4:$K10)*$L$4 -> 0 | K65: =SUM($K4:$K11)*$L$4 -> 0 | L65: =SUM($K4:$K12)*$L$4 -> 0 | M65: =SUM($K4:$K13)*$L$4 -> 0 | N65: =SUM($K4:$K14)*$L$4 -> 0 | O65: =SUM($K4:$K15)*$L$4 -> 0 | P65: =SUM($K4:$K16)*$L$4 -> 0 | Q65: =SUM($K4:$K17)*$L$4 -> 0 | R65: =SUM($K4:$K18)*$L$4 -> 0
D67: Net Cash Flow
A68: New Commitments | B68: Commitment | D68: =D$100 -> 2025 | E68: =E$100 -> 2026 | F68: =F$100 -> 2027 | G68: =G$100 -> 2028 | H68: =H$100 -> 2029 | I68: =I$100 -> 2030 | J68: =J$100 -> 2031 | K68: =K$100 -> 2032 | ... R68: =R$100 -> 2039
B70: =SUM(K4:K18) -> 0 | D70: =D60+D65 -> 0 | E70: =E60+E65 -> 0 | F70: =F60+F65 -> 0 | G70: =G60+G65 -> 0 | H70: =H60+H65 -> 0 | I70: =I60+I65 -> 0 | J70: =J60+J65 -> 0 | K70: =K60+K65 -> 0 | ... R70: =R60+R65 -> 0
A73: Net Cash Flow Cumulative | D73: =D70 -> 0 | E73: =D73+E70 -> 0 | F73: =E73+F70 -> 0 | G73: =F73+G70 -> 0 | H73: =G73+H70 -> 0 | I73: =H73+I70 -> 0 | J73: =I73+J70 -> 0 | K73: =J73+K70 -> 0 | L73: =K73+L70 -> 0 | ... R73: =Q73+R70 -> 0
A75: NEW COMPOUNDING OPEN-ENDED PORTFOLIO | D75: Net Asset Value
A76: New Commitments | B76: Commitment | C76: % of Total Portfolio Value | D76: 2025 | E76: =D76+1 -> 2026 | F76: =E76+1 -> 2027 | G76: =F76+1 -> 2028 | H76: =G76+1 -> 2029 | I76: =H76+1 -> 2030 | J76: =I76+1 -> 2031 | K76: =J76+1 -> 2032 | L76: =K76+1 -> 2033 | ... R76: =Q76+1 -> 2039
B78: =SUM(H4:H18) -> 0 | D78: =H4*(1+$I$4) -> 0 | E78: =D78*(1+$I$4)+E$84*(1+$I$4) -> 0 | F78: =E78*(1+$I$4)+F$84*(1+$I$4) -> 0 | G78: =F78*(1+$I$4)+G$84*(1+$I$4) -> 0 | H78: =G78*(1+$I$4)+H$84*(1+$I$4) -> 0 | I78: =H78*(1+$I$4)+I$84*(1+$I$4) -> 0 | J78: =I78*(1+$I$4)+J$84*(1+$I$4) -> 0 | K78: =J78*(1+$I$4)+K$84*(1+$I$4) -> 0 | L78: =K78*(1+$I$4)+L$84*(1+$I$4) -> 0 | ... R78: =Q78*(1+$I$4)+R$84*(1+$I$4) -> 0
D81: Annual Capital Called
A82: New Commitments | B82: Commitment | D82: =D$100 -> 2025 | E82: =E$100 -> 2026 | F82: =F$100 -> 2027 | G82: =G$100 -> 2028 | H82: =H$100 -> 2029 | I82: =I$100 -> 2030 | J82: =J$100 -> 2031 | K82: =K$100 -> 2032 | ... R82: =R$100 -> 2039
B84: =SUM(H4:H18) -> 0 | D84: =-$H4 -> 0 | E84: =-$H5 -> 0 | F84: =-$H6 -> 0 | G84: =-$H7 -> 0 | H84: =-$H8 -> 0 | I84: =-$H9 -> 0 | J84: =-$H10 -> 0 | K84: =-$H11 -> 0 | L84: =-H12 -> 0 | M84: =-H13 -> 0 | N84: =-H14 -> 0 | O84: =-H15 -> 0 | P84: =-H16 -> 0 | Q84: =-H17 -> 0 | R84: =-H18 -> 0
D86: Annual Distributions
A87: New Commitments | B87: Commitment | D87: =D$100 -> 2025 | E87: =E$100 -> 2026 | F87: =F$100 -> 2027 | G87: =G$100 -> 2028 | H87: =H$100 -> 2029 | I87: =I$100 -> 2030 | J87: =J$100 -> 2031 | K87: =K$100 -> 2032 | ... R87: =R$100 -> 2039
B89: =SUM(H4:H18) -> 0 | D89: 0 | E89: 0 | F89: 0 | G89: 0 | H89: 0 | I89: 0 | J89: 0 | K89: 0 | L89: 0 | M89: 0 | N89: 0 | O89: 0 | P89: 0 | Q89: 0 | R89: 0
D91: Net Cash Flow
A92: New Commitments | B92: Commitment | D92: =D$100 -> 2025 | E92: =E$100 -> 2026 | F92: =F$100 -> 2027 | G92: =G$100 -> 2028 | H92: =H$100 -> 2029 | I92: =I$100 -> 2030 | J92: =J$100 -> 2031 | K92: =K$100 -> 2032 | ... R92: =R$100 -> 2039
B94: =SUM(H4:H18) -> 0 | D94: =D84+D89 -> 0 | E94: =E84+E89 -> 0 | F94: =F84+F89 -> 0 | G94: =G84+G89 -> 0 | H94: =H84+H89 -> 0 | I94: =I84+I89 -> 0 | J94: =J84+J89 -> 0 | K94: =K84+K89 -> 0 | ... R94: =R84+R89 -> 0
A97: Net Cash Flow Cumulative | D97: =SUM($D$94:D94) -> 0 | E97: =SUM($D$94:E94) -> 0 | F97: =SUM($D$94:F94) -> 0 | G97: =SUM($D$94:G94) -> 0 | H97: =SUM($D$94:H94) -> 0 | I97: =SUM($D$94:I94) -> 0 | J97: =SUM($D$94:J94) -> 0 | K97: =SUM($D$94:K94) -> 0 | ... R97: =SUM($D$94:R94) -> 0
A99: NEW DRAWDOWN PORTFOLIO | D99: Net Asset Value
A100: New Commitments | B100: Commitment | C100: % of Total Portfolio Value | D100: 2025 | E100: =D100+1 -> 2026 | F100: =E100+1 -> 2027 | G100: =F100+1 -> 2028 | H100: =G100+1 -> 2029 | I100: =H100+1 -> 2030 | J100: =I100+1 -> 2031 | K100: =J100+1 -> 2032 | L100: =K100+1 -> 2033 | ... R100: =Q100+1 -> 2039
A101: 2025 | B101: 3900000 | C101: =B101/$D4 -> 0.39 | D101: =VLOOKUP(D$100,'Aggregated Median CA data'!$D$126:$M$140,5,0)*$B101 -> 619798.85 | E101: =VLOOKUP(E$100,'Aggregated Median CA data'!$D$126:$M$140,5,0)*$B101 -> 1377730.5 | F101: =VLOOKUP(F$100,'Aggregated Median CA data'!$D$126:$M$140,5,0)*$B101 -> 2240893 | G101: =VLOOKUP(G$100,'Aggregated Median CA data'!$D$126:$M$140,5,0)*$B101 -> 2928916.1 | H101: =VLOOKUP(H$100,'Aggregated Median CA data'!$D$126:$M$140,5,0)*$B101 -> 3284097.9 | I101: =VLOOKUP(I$100,'Aggregated Median CA data'!$D$126:$M$140,5,0)*$B101 -> 3142486.4 | J101: =VLOOKUP(J$100,'Aggregated Median CA data'!$D$126:$M$140,5,0)*$B101 -> 2861892.1 | K101: =VLOOKUP(K$100,'Aggregated Median CA data'!$D$126:$M$140,5,0)*$B101 -> 2426009.3 | ... R101: =VLOOKUP(R$100,'Aggregated Median CA data'!$D$126:$M$140,5,0)*$B101 -> 549638.68
A102: =A101+1 -> 2026 | B102: 3900000 | C102: =B102/$D5 -> 0.36757776 | E102: =IF($B102=0,0,(D101/$B101)*$B102) -> 619798.85 | F102: =IF($B102=0,0,(E101/$B101)*$B102) -> 1377730.5 | G102: =IF($B102=0,0,(F101/$B101)*$B102) -> 2240893 | H102: =IF($B102=0,0,(G101/$B101)*$B102) -> 2928916.1 | I102: =IF($B102=0,0,(H101/$B101)*$B102) -> 3284097.9 | J102: =IF($B102=0,0,(I101/$B101)*$B102) -> 3142486.4 | K102: =IF($B102=0,0,(J101/$B101)*$B102) -> 2861892.1 | L102: =IF($B102=0,0,(K101/$B101)*$B102) -> 2426009.3 | ... R102: =IF($B102=0,0,(Q101/$B101)*$B102) -> 603071.2
A103: =A102+1 -> 2027 | B103: 3900000 | C103: =B103/$D6 -> 0.34644463 | F103: =IF($B103=0,0,(E102/$B102)*$B103) -> 619798.85 | G103: =IF($B103=0,0,(F102/$B102)*$B103) -> 1377730.5 | H103: =IF($B103=0,0,(G102/$B102)*$B103) -> 2240893 | I103: =IF($B103=0,0,(H102/$B102)*$B103) -> 2928916.1 | J103: =IF($B103=0,0,(I102/$B102)*$B103) -> 3284097.9 | K103: =IF($B103=0,0,(J102/$B102)*$B103) -> 3142486.4 | L103: =IF($B103=0,0,(K102/$B102)*$B103) -> 2861892.1 | M103: =IF($B103=0,0,(L102/$B102)*$B103) -> 2426009.3 | ... R103: =IF($B103=0,0,(Q102/$B102)*$B103) -> 698711.62
A104: =A103+1 -> 2028 | B104: 3900000 | C104: =B104/$D7 -> 0.32652652 | G104: =IF($B104=0,0,(F103/$B103)*$B104) -> 619798.85 | H104: =IF($B104=0,0,(G103/$B103)*$B104) -> 1377730.5 | I104: =IF($B104=0,0,(H103/$B103)*$B104) -> 2240893 | J104: =IF($B104=0,0,(I103/$B103)*$B104) -> 2928916.1 | K104: =IF($B104=0,0,(J103/$B103)*$B104) -> 3284097.9 | L104: =IF($B104=0,0,(K103/$B103)*$B104) -> 3142486.4 | M104: =IF($B104=0,0,(L103/$B103)*$B104) -> 2861892.1 | N104: =IF($B104=0,0,(M103/$B103)*$B104) -> 2426009.3 | ... R104: =IF($B104=0,0,(Q103/$B103)*$B104) -> 902056.17
A105: =A104+1 -> 2029 | B105: 3900000 | C105: =B105/$D8 -> 0.30775355 | H105: =IF($B105=0,0,(G104/$B104)*$B105) -> 619798.85 | I105: =IF($B105=0,0,(H104/$B104)*$B105) -> 1377730.5 | J105: =IF($B105=0,0,(I104/$B104)*$B105) -> 2240893 | K105: =IF($B105=0,0,(J104/$B104)*$B105) -> 2928916.1 | L105: =IF($B105=0,0,(K104/$B104)*$B105) -> 3284097.9 | M105: =IF($B105=0,0,(L104/$B104)*$B105) -> 3142486.4 | N105: =IF($B105=0,0,(M104/$B104)*$B105) -> 2861892.1 | O105: =IF($B105=0,0,(N104/$B104)*$B105) -> 2426009.3 | ... R105: =IF($B105=0,0,(Q104/$B104)*$B105) -> 1174462.8
A106: =A105+1 -> 2030 | B106: 3900000 | C106: =B106/$D9 -> 0.2900599 | I106: =IF($B106=0,0,(H105/$B105)*$B106) -> 619798.85 | J106: =IF($B106=0,0,(I105/$B105)*$B106) -> 1377730.5 | K106: =IF($B106=0,0,(J105/$B105)*$B106) -> 2240893 | L106: =IF($B106=0,0,(K105/$B105)*$B106) -> 2928916.1 | M106: =IF($B106=0,0,(L105/$B105)*$B106) -> 3284097.9 | N106: =IF($B106=0,0,(M105/$B105)*$B106) -> 3142486.4 | O106: =IF($B106=0,0,(N105/$B105)*$B106) -> 2861892.1 | P106: =IF($B106=0,0,(O105/$B105)*$B106) -> 2426009.3 | ... R106: =IF($B106=0,0,(Q105/$B105)*$B106) -> 1564270.3
A107: =A106+1 -> 2031 | B107: 3900000 | C107: =B107/$D10 -> 0.2733835 | J107: =IF($B107=0,0,(I106/$B106)*$B107) -> 619798.85 | K107: =IF($B107=0,0,(J106/$B106)*$B107) -> 1377730.5 | L107: =IF($B107=0,0,(K106/$B106)*$B107) -> 2240893 | M107: =IF($B107=0,0,(L106/$B106)*$B107) -> 2928916.1 | N107: =IF($B107=0,0,(M106/$B106)*$B107) -> 3284097.9 | O107: =IF($B107=0,0,(N106/$B106)*$B107) -> 3142486.4 | P107: =IF($B107=0,0,(O106/$B106)*$B107) -> 2861892.1 | Q107: =IF($B107=0,0,(P106/$B106)*$B107) -> 2426009.3 | R107: =IF($B107=0,0,(Q106/$B106)*$B107) -> 1922276.8
A108: =A107+1 -> 2032 | B108: 3900000 | C108: =B108/$D11 -> 0.25766588 | K108: =IF($B108=0,0,(J107/$B107)*$B108) -> 619798.85 | L108: =IF($B108=0,0,(K107/$B107)*$B108) -> 1377730.5 | M108: =IF($B108=0,0,(L107/$B107)*$B108) -> 2240893 | N108: =IF($B108=0,0,(M107/$B107)*$B108) -> 2928916.1 | O108: =IF($B108=0,0,(N107/$B107)*$B108) -> 3284097.9 | P108: =IF($B108=0,0,(O107/$B107)*$B108) -> 3142486.4 | Q108: =IF($B108=0,0,(P107/$B107)*$B108) -> 2861892.1 | R108: =IF($B108=0,0,(Q107/$B107)*$B108) -> 2426009.3
A109: =A108+1 -> 2033 | B109: 3900000 | C109: =B109/$D12 -> 0.24285192 | L109: =IF($B109=0,0,(K108/$B108)*$B109) -> 619798.85 | M109: =IF($B109=0,0,(L108/$B108)*$B109) -> 1377730.5 | N109: =IF($B109=0,0,(M108/$B108)*$B109) -> 2240893 | O109: =IF($B109=0,0,(N108/$B108)*$B109) -> 2928916.1 | P109: =IF($B109=0,0,(O108/$B108)*$B109) -> 3284097.9 | Q109: =IF($B109=0,0,(P108/$B108)*$B109) -> 3142486.4 | R109: =IF($B109=0,0,(Q108/$B108)*$B109) -> 2861892.1
A110: =A109+1 -> 2034 | B110: 3900000 | C110: =B110/$D13 -> 0.22888965 | M110: =IF($B110=0,0,(L109/$B109)*$B110) -> 619798.85 | N110: =IF($B110=0,0,(M109/$B109)*$B110) -> 1377730.5 | O110: =IF($B110=0,0,(N109/$B109)*$B110) -> 2240893 | P110: =IF($B110=0,0,(O109/$B109)*$B110) -> 2928916.1 | Q110: =IF($B110=0,0,(P109/$B109)*$B110) -> 3284097.9 | R110: =IF($B110=0,0,(Q109/$B109)*$B110) -> 3142486.4
A111: =A110+1 -> 2035 | B111: 3900000 | C111: =B111/$D14 -> 0.21573011 | N111: =IF($B111=0,0,(M110/$B110)*$B111) -> 619798.85 | O111: =IF($B111=0,0,(N110/$B110)*$B111) -> 1377730.5 | P111: =IF($B111=0,0,(O110/$B110)*$B111) -> 2240893 | Q111: =IF($B111=0,0,(P110/$B110)*$B111) -> 2928916.1 | R111: =IF($B111=0,0,(Q110/$B110)*$B111) -> 3284097.9
A112: =A111+1 -> 2036 | B112: 3900000 | C112: =B112/$D15 -> 0.20332716 | O112: =IF($B112=0,0,(N111/$B111)*$B112) -> 619798.85 | P112: =IF($B112=0,0,(O111/$B111)*$B112) -> 1377730.5 | Q112: =IF($B112=0,0,(P111/$B111)*$B112) -> 2240893 | R112: =IF($B112=0,0,(Q111/$B111)*$B112) -> 2928916.1
A113: =A112+1 -> 2037 | B113: 3900000 | C113: =B113/$D16 -> 0.19163728 | P113: =IF($B113=0,0,(O112/$B112)*$B113) -> 619798.85 | Q113: =IF($B113=0,0,(P112/$B112)*$B113) -> 1377730.5 | R113: =IF($B113=0,0,(Q112/$B112)*$B113) -> 2240893
A114: =A113+1 -> 2038 | B114: 3900000 | C114: =B114/$D17 -> 0.18061949 | Q114: =IF($B114=0,0,(P113/$B113)*$B114) -> 619798.85 | R114: =IF($B114=0,0,(Q113/$B113)*$B114) -> 1377730.5
A115: =A114+1 -> 2039 | B115: 3900000 | C115: =B115/$D18 -> 0.17023515 | R115: =IF($B115=0,0,(Q114/$B114)*$B115) -> 619798.85
A117: Total New | D117: =SUM(D101:D115) -> 619798.85 | E117: =SUM(E101:E115) -> 1997529.4 | F117: =SUM(F101:F115) -> 4238422.4 | G117: =SUM(G101:G115) -> 7167338.5 | H117: =SUM(H101:H115) -> 10451436 | I117: =SUM(I101:I115) -> 13593923 | J117: =SUM(J101:J115) -> 16455815 | K117: =SUM(K101:K115) -> 18881824 | ... R117: =SUM(R101:R115) -> 26296312
A119: Total New + Open-ended PE | D119: =SUM(D117,D78,D54,D30) -> 10600656 | E119: =SUM(E117,E78,E54,E30) -> 11132372 | F119: =SUM(F117,F78,F54,F30) -> 11668652 | G119: =SUM(G117,G78,G54,G30) -> 12356559 | H119: =SUM(H117,H78,H54,H30) -> 13459100 | I119: =SUM(I117,I78,I54,I30) -> 14787801 | J119: =SUM(J117,J78,J54,J30) -> 16636856 | K119: =SUM(K117,K78,K54,K30) -> 18924892 | ... R119: =SUM(R117,R78,R54,R30) -> 42613909
A121: Total Mandate MV | D121: =$D$4 -> 10000000 | E121: =$D$5 -> 10610000 | F121: =$D$6 -> 11257210 | G121: =$D$7 -> 11943900 | H121: =$D$8 -> 12672478 | I121: =$D$9 -> 13445499 | J121: =$D$10 -> 14265674 | K121: =$D$11 -> 15135880 | L121: =$D$12 -> 16059169 | M121: =$D$13 -> 17038778 | N121: =$D$14 -> 18078144 | O121: =$D$15 -> 19180911 | P121: =$D$16 -> 20350946 | Q121: =$D$17 -> 21592354 | R121: =$D$18 -> 22909488
A122: % | D122: =D119/D121 -> 1.0600656 | E122: =E119/E121 -> 1.0492339 | F122: =F119/F121 -> 1.0365492 | G122: =G119/G121 -> 1.0345498 | H122: =H119/H121 -> 1.0620733 | I122: =I119/I121 -> 1.0998328 | J122: =J119/J121 -> 1.1662159 | K122: =K119/K121 -> 1.2503331 | ... R122: =R119/R121 -> 1.8600988
C123: Portfolio Value | D123: =D121/1000000 -> 10 | E123: =E121/1000000 -> 10.61 | F123: =F121/1000000 -> 11.25721 | G123: =G121/1000000 -> 11.9439 | H123: =H121/1000000 -> 12.672478 | I123: =I121/1000000 -> 13.445499 | J123: =J121/1000000 -> 14.265674 | K123: =K121/1000000 -> 15.13588 | ... R123: =R121/1000000 -> 22.909488
C124: Commitments | D124: =$B$101/1000000 -> 3.9 | E124: =$B$102/1000000 -> 3.9 | F124: =$B$103/1000000 -> 3.9 | G124: =$B$104/1000000 -> 3.9 | H124: =$B$105/1000000 -> 3.9 | I124: =$B$106/1000000 -> 3.9 | J124: =$B$107/1000000 -> 3.9 | K124: =$B$108/1000000 -> 3.9 | L124: =$B$109/1000000 -> 3.9 | M124: =$B$110/1000000 -> 3.9 | N124: =$B$111/1000000 -> 3.9 | O124: =$B$112/1000000 -> 3.9 | P124: =$B$113/1000000 -> 3.9 | Q124: =$B$114/1000000 -> 3.9 | R124: =$B$115/1000000 -> 3.9
C125: PI Portfolio NAV | D125: =D119/1000000 -> 10.600656 | E125: =E119/1000000 -> 11.132372 | F125: =F119/1000000 -> 11.668652 | G125: =G119/1000000 -> 12.356559 | H125: =H119/1000000 -> 13.4591 | I125: =I119/1000000 -> 14.787801 | J125: =J119/1000000 -> 16.636856 | K125: =K119/1000000 -> 18.924892 | ... R125: =R119/1000000 -> 42.613909
D126: Annual Capital Called
A127: New Commitments | B127: Commitment | D127: =D$100 -> 2025 | E127: =E$100 -> 2026 | F127: =F$100 -> 2027 | G127: =G$100 -> 2028 | H127: =H$100 -> 2029 | I127: =I$100 -> 2030 | J127: =J$100 -> 2031 | K127: =K$100 -> 2032 | ... R127: =R$100 -> 2039
A128: =A101 -> 2025 | B128: =B101 -> 3900000 | D128: =VLOOKUP(D$100,'Aggregated Median CA data'!$D$126:$M$140,7,0)*$B128 -> -672096.06 | E128: =VLOOKUP(E$100,'Aggregated Median CA data'!$D$126:$M$140,7,0)*$B128 -> -774526.06 | F128: =VLOOKUP(F$100,'Aggregated Median CA data'!$D$126:$M$140,7,0)*$B128 -> -829338.6 | G128: =VLOOKUP(G$100,'Aggregated Median CA data'!$D$126:$M$140,7,0)*$B128 -> -723349.3 | H128: =VLOOKUP(H$100,'Aggregated Median CA data'!$D$126:$M$140,7,0)*$B128 -> -451017.53 | I128: =VLOOKUP(I$100,'Aggregated Median CA data'!$D$126:$M$140,7,0)*$B128 -> -228788.73 | J128: =VLOOKUP(J$100,'Aggregated Median CA data'!$D$126:$M$140,7,0)*$B128 -> -103339.4 | K128: =VLOOKUP(K$100,'Aggregated Median CA data'!$D$126:$M$140,7,0)*$B128 -> -60792.103 | ... R128: =VLOOKUP(R$100,'Aggregated Median CA data'!$D$126:$M$140,7,0)*$B128 -> -1530.3283
A129: =A102 -> 2026 | B129: =B102 -> 3900000 | E129: =IFERROR((D128/$B128)*$B129,0) -> -672096.06 | F129: =IFERROR((E128/$B128)*$B129,0) -> -774526.06 | G129: =IFERROR((F128/$B128)*$B129,0) -> -829338.6 | H129: =IFERROR((G128/$B128)*$B129,0) -> -723349.3 | I129: =IFERROR((H128/$B128)*$B129,0) -> -451017.53 | J129: =IFERROR((I128/$B128)*$B129,0) -> -228788.73 | K129: =IFERROR((J128/$B128)*$B129,0) -> -103339.4 | L129: =IFERROR((K128/$B128)*$B129,0) -> -60792.103 | ... R129: =IFERROR((Q128/$B128)*$B129,0) -> -355.66796
A130: =A103 -> 2027 | B130: =B103 -> 3900000 | F130: =IFERROR((E129/$B129)*$B130,0) -> -672096.06 | G130: =IFERROR((F129/$B129)*$B130,0) -> -774526.06 | H130: =IFERROR((G129/$B129)*$B130,0) -> -829338.6 | I130: =IFERROR((H129/$B129)*$B130,0) -> -723349.3 | J130: =IFERROR((I129/$B129)*$B130,0) -> -451017.53 | K130: =IFERROR((J129/$B129)*$B130,0) -> -228788.73 | L130: =IFERROR((K129/$B129)*$B130,0) -> -103339.4 | M130: =IFERROR((L129/$B129)*$B130,0) -> -60792.103 | ... R130: =IFERROR((Q129/$B129)*$B130,0) -> -4230.8477
A131: =A104 -> 2028 | B131: =B104 -> 3900000 | G131: =IFERROR((F130/$B130)*$B131,0) -> -672096.06 | H131: =IFERROR((G130/$B130)*$B131,0) -> -774526.06 | I131: =IFERROR((H130/$B130)*$B131,0) -> -829338.6 | J131: =IFERROR((I130/$B130)*$B131,0) -> -723349.3 | K131: =IFERROR((J130/$B130)*$B131,0) -> -451017.53 | L131: =IFERROR((K130/$B130)*$B131,0) -> -228788.73 | M131: =IFERROR((L130/$B130)*$B131,0) -> -103339.4 | N131: =IFERROR((M130/$B130)*$B131,0) -> -60792.103 | ... R131: =IFERROR((Q130/$B130)*$B131,0) -> -5834.1943
A132: =A105 -> 2029 | B132: =B105 -> 3900000 | H132: =IFERROR((G131/$B131)*$B132,0) -> -672096.06 | I132: =IFERROR((H131/$B131)*$B132,0) -> -774526.06 | J132: =IFERROR((I131/$B131)*$B132,0) -> -829338.6 | K132: =IFERROR((J131/$B131)*$B132,0) -> -723349.3 | L132: =IFERROR((K131/$B131)*$B132,0) -> -451017.53 | M132: =IFERROR((L131/$B131)*$B132,0) -> -228788.73 | N132: =IFERROR((M131/$B131)*$B132,0) -> -103339.4 | O132: =IFERROR((N131/$B131)*$B132,0) -> -60792.103 | ... R132: =IFERROR((Q131/$B131)*$B132,0) -> -10599.082
A133: =A106 -> 2030 | B133: =B106 -> 3900000 | I133: =IFERROR((H132/$B132)*$B133,0) -> -672096.06 | J133: =IFERROR((I132/$B132)*$B133,0) -> -774526.06 | K133: =IFERROR((J132/$B132)*$B133,0) -> -829338.6 | L133: =IFERROR((K132/$B132)*$B133,0) -> -723349.3 | M133: =IFERROR((L132/$B132)*$B133,0) -> -451017.53 | N133: =IFERROR((M132/$B132)*$B133,0) -> -228788.73 | O133: =IFERROR((N132/$B132)*$B133,0) -> -103339.4 | P133: =IFERROR((O132/$B132)*$B133,0) -> -60792.103 | ... R133: =IFERROR((Q132/$B132)*$B133,0) -> -15950.28
A134: =A107 -> 2031 | B134: =B107 -> 3900000 | J134: =IFERROR((I133/$B133)*$B134,0) -> -672096.06 | K134: =IFERROR((J133/$B133)*$B134,0) -> -774526.06 | L134: =IFERROR((K133/$B133)*$B134,0) -> -829338.6 | M134: =IFERROR((L133/$B133)*$B134,0) -> -723349.3 | N134: =IFERROR((M133/$B133)*$B134,0) -> -451017.53 | O134: =IFERROR((N133/$B133)*$B134,0) -> -228788.73 | P134: =IFERROR((O133/$B133)*$B134,0) -> -103339.4 | Q134: =IFERROR((P133/$B133)*$B134,0) -> -60792.103 | R134: =IFERROR((Q133/$B133)*$B134,0) -> -22944.112
A135: =A108 -> 2032 | B135: =B108 -> 3900000 | K135: =IFERROR((J134/$B134)*$B135,0) -> -672096.06 | L135: =IFERROR((K134/$B134)*$B135,0) -> -774526.06 | M135: =IFERROR((L134/$B134)*$B135,0) -> -829338.6 | N135: =IFERROR((M134/$B134)*$B135,0) -> -723349.3 | O135: =IFERROR((N134/$B134)*$B135,0) -> -451017.53 | P135: =IFERROR((O134/$B134)*$B135,0) -> -228788.73 | Q135: =IFERROR((P134/$B134)*$B135,0) -> -103339.4 | R135: =IFERROR((Q134/$B134)*$B135,0) -> -60792.103
A136: =A109 -> 2033 | B136: =B109 -> 3900000 | L136: =IFERROR((K135/$B135)*$B136,0) -> -672096.06 | M136: =IFERROR((L135/$B135)*$B136,0) -> -774526.06 | N136: =IFERROR((M135/$B135)*$B136,0) -> -829338.6 | O136: =IFERROR((N135/$B135)*$B136,0) -> -723349.3 | P136: =IFERROR((O135/$B135)*$B136,0) -> -451017.53 | Q136: =IFERROR((P135/$B135)*$B136,0) -> -228788.73 | R136: =IFERROR((Q135/$B135)*$B136,0) -> -103339.4
A137: =A110 -> 2034 | B137: =B110 -> 3900000 | M137: =IFERROR((L136/$B136)*$B137,0) -> -672096.06 | N137: =IFERROR((M136/$B136)*$B137,0) -> -774526.06 | O137: =IFERROR((N136/$B136)*$B137,0) -> -829338.6 | P137: =IFERROR((O136/$B136)*$B137,0) -> -723349.3 | Q137: =IFERROR((P136/$B136)*$B137,0) -> -451017.53 | R137: =IFERROR((Q136/$B136)*$B137,0) -> -228788.73
A138: =A111 -> 2035 | B138: =B111 -> 3900000 | N138: =IFERROR((M137/$B137)*$B138,0) -> -672096.06 | O138: =IFERROR((N137/$B137)*$B138,0) -> -774526.06 | P138: =IFERROR((O137/$B137)*$B138,0) -> -829338.6 | Q138: =IFERROR((P137/$B137)*$B138,0) -> -723349.3 | R138: =IFERROR((Q137/$B137)*$B138,0) -> -451017.53
A139: =A112 -> 2036 | B139: =B112 -> 3900000 | O139: =IFERROR((N138/$B138)*$B139,0) -> -672096.06 | P139: =IFERROR((O138/$B138)*$B139,0) -> -774526.06 | Q139: =IFERROR((P138/$B138)*$B139,0) -> -829338.6 | R139: =IFERROR((Q138/$B138)*$B139,0) -> -723349.3
A140: =A113 -> 2037 | B140: =B113 -> 3900000 | P140: =IFERROR((O139/$B139)*$B140,0) -> -672096.06 | Q140: =IFERROR((P139/$B139)*$B140,0) -> -774526.06 | R140: =IFERROR((Q139/$B139)*$B140,0) -> -829338.6
A141: =A114 -> 2038 | B141: =B114 -> 3900000 | Q141: =IFERROR((P140/$B140)*$B141,0) -> -672096.06 | R141: =IFERROR((Q140/$B140)*$B141,0) -> -774526.06
A142: =A115 -> 2039 | B142: =B115 -> 3900000 | R142: =IFERROR((Q141/$B141)*$B142,0) -> -672096.06
A144: Total New | D144: =SUM(D128:D142) -> -672096.06 | E144: =SUM(E128:E142) -> -1446622.1 | F144: =SUM(F128:F142) -> -2275960.7 | G144: =SUM(G128:G142) -> -2999310 | H144: =SUM(H128:H142) -> -3450327.5 | I144: =SUM(I128:I142) -> -3679116.3 | J144: =SUM(J128:J142) -> -3782455.7 | K144: =SUM(K128:K142) -> -3843247.8 | ... R144: =SUM(R128:R142) -> -3904692.3
A146: Total Existing + New + Open-ended PE | D146: =SUM(D144,D84,D60,D36) -> -672096.06 | E146: =SUM(E144,E84,E60,E36) -> -1446622.1 | F146: =SUM(F144,F84,F60,F36) -> -2275960.7 | G146: =SUM(G144,G84,G60,G36) -> -2999310 | H146: =SUM(H144,H84,H60,H36) -> -3450327.5 | I146: =SUM(I144,I84,I60,I36) -> -3679116.3 | J146: =SUM(J144,J84,J60,J36) -> -3782455.7 | K146: =SUM(K144,K84,K60,K36) -> -3843247.8 | ... R146: =SUM(R144,R84,R60,R36) -> -3904692.3
A148: Cumulative called | D148: =D146 -> -672096.06 | E148: =SUM($D$146:E147) -> -2118718.2 | F148: =SUM($D$146:F147) -> -4394678.9 | G148: =SUM($D$146:G147) -> -7393988.9 | H148: =SUM($D$146:H147) -> -10844316 | I148: =SUM($D$146:I147) -> -14523433 | J148: =SUM($D$146:J147) -> -18305888 | K148: =SUM($D$146:K147) -> -22149136 | L148: =SUM($D$146:L147) -> -26015328 | ... R148: =SUM($D$146:R147) -> -49399447
...

Sheet Drawdown+Evergreen from start
A1: After-tax annualized investment return: | B1: 0.061
A3: Year | B3: Current Market Value | C3: New Money Ins/Outs | D3: Total Assets | E3: PE Target (%) | F3: PE Target ($) | H3: Compounding Open-ended PE Commitments | I3: Compounding Rate | K3: Yielding Open-ended PE Commitments | L3: Yield Rate | N3: New Drawdown Target Portfolio | O3: **Make sure this sums to 100%
A4: 2025 | B4: 10000000 | C4: 0 | D4: =SUM(B4:C4) -> 10000000 | E4: 1 | F4: =D4*E4 -> 10000000 | H4: 5000000 | I4: =LTCMAs!K11 -> 0.0939 | K4: 0 | L4: 0.06 | N4: Buyout | O4: 1
A5: =A4+1 -> 2026 | D5: =(D4*(1+$B$1))+C5 -> 10610000 | E5: =E4 -> 1 | F5: =D5*E5 -> 10610000 | H5: 0 | K5: 0 | N5: Growth Equity | O5: 0
A6: =A5+1 -> 2027 | D6: =(D5*(1+$B$1))+C6 -> 11257210 | E6: =E5 -> 1 | F6: =D6*E6 -> 11257210 | H6: 0 | K6: 0 | N6: Venture Capital | O6: 0
A7: =A6+1 -> 2028 | D7: =(D6*(1+$B$1))+C7 -> 11943900 | E7: =E6 -> 1 | F7: =D7*E7 -> 11943900 | H7: 0 | K7: 0 | N7: Fund of Funds | O7: 0
A8: =A7+1 -> 2029 | D8: =(D7*(1+$B$1))+C8 -> 12672478 | E8: =E7 -> 1 | F8: =D8*E8 -> 12672478 | H8: 0 | K8: 0 | N8: Secondary Funds | O8: 0
A9: =A8+1 -> 2030 | D9: =(D8*(1+$B$1))+C9 -> 13445499 | E9: =E8 -> 1 | F9: =D9*E9 -> 13445499 | H9: 0 | K9: 0 | N9: Private Credit | O9: 0
A10: =A9+1 -> 2031 | D10: =(D9*(1+$B$1))+C10 -> 14265674 | E10: =E9 -> 1 | F10: =D10*E10 -> 14265674 | H10: 0 | K10: 0 | N10: Real Estate | O10: 0
A11: =A10+1 -> 2032 | D11: =(D10*(1+$B$1))+C11 -> 15135880 | E11: =E10 -> 1 | F11: =D11*E11 -> 15135880 | H11: 0 | K11: 0
A12: =A11+1 -> 2033 | D12: =(D11*(1+$B$1))+C12 -> 16059169 | E12: =E11 -> 1 | F12: =D12*E12 -> 16059169 | H12: 0 | K12: 0 | N12: Total | O12: =SUM(O4:O10) -> 1
A13: =A12+1 -> 2034 | D13: =(D12*(1+$B$1))+C13 -> 17038778 | E13: =E12 -> 1 | F13: =D13*E13 -> 17038778 | H13: 0 | K13: 0
A14: =A13+1 -> 2035 | D14: =(D13*(1+$B$1))+C14 -> 18078144 | E14: =E13 -> 1 | F14: =D14*E14 -> 18078144 | H14: 0 | K14: 0
A15: =A14+1 -> 2036 | D15: =(D14*(1+$B$1))+C15 -> 19180911 | E15: =E14 -> 1 | F15: =D15*E15 -> 19180911 | H15: 0 | K15: 0
A16: =A15+1 -> 2037 | D16: =(D15*(1+$B$1))+C16 -> 20350946 | E16: =E15 -> 1 | F16: =D16*E16 -> 20350946 | H16: 0 | K16: 0
A17: =A16+1 -> 2038 | D17: =(D16*(1+$B$1))+C17 -> 21592354 | E17: =E16 -> 1 | F17: =D17*E17 -> 21592354 | H17: 0 | K17: 0
A18: =A17+1 -> 2039 | D18: =(D17*(1+$B$1))+C18 -> 22909488 | E18: =E17 -> 1 | F18: =D18*E18 -> 22909488 | H18: 0 | K18: 0
A27: EXISTING PORTFOLIO | B27: TO FILL IN WITH CONNECT OUTPUT | D27: Net Asset Value
A28: New Commitments | B28: Commitment | C28: % of Total Portfolio Value | D28: 2025 | E28: =D28+1 -> 2026 | F28: =E28+1 -> 2027 | G28: =F28+1 -> 2028 | H28: =G28+1 -> 2029 | I28: =H28+1 -> 2030 | J28: =I28+1 -> 2031 | K28: =J28+1 -> 2032 | L28: =K28+1 -> 2033 | ... R28: =Q28+1 -> 2039
B30: 0 | D30: 0 | E30: 0 | F30: 0 | G30: 0 | H30: 0 | I30: 0 | J30: 0 | K30: 0 | L30: 0 | M30: 0 | N30: 0 | O30: 0 | P30: 0 | Q30: 0 | R30: 0
D33: Annual Capital Called
A34: New Commitments | B34: Commitment | D34: =D$100 -> 2025 | E34: =E$100 -> 2026 | F34: =F$100 -> 2027 | G34: =G$100 -> 2028 | H34: =H$100 -> 2029 | I34: =I$100 -> 2030 | J34: =J$100 -> 2031 | K34: =K$100 -> 2032 | ... R34: =R$100 -> 2039
B36: 0 | D36: 0 | E36: 0 | F36: 0 | G36: 0 | H36: 0 | I36: 0 | J36: 0 | K36: 0 | L36: 0 | M36: 0 | N36: 0 | O36: 0 | P36: 0 | Q36: 0 | R36: 0
D38: Annual Distributions
A39: New Commitments | B39: Commitment | D39: =D$100 -> 2025 | E39: =E$100 -> 2026 | F39: =F$100 -> 2027 | G39: =G$100 -> 2028 | H39: =H$100 -> 2029 | I39: =I$100 -> 2030 | J39: =J$100 -> 2031 | K39: =K$100 -> 2032 | ... R39: =R$100 -> 2039
B41: 0 | D41: 0 | E41: 0 | F41: 0 | G41: 0 | H41: 0 | I41: 0 | J41: 0 | K41: 0 | L41: 0 | M41: 0 | N41: 0 | O41: 0 | P41: 0 | Q41: 0 | R41: 0
D43: Net Cash Flow
A44: New Commitments | B44: Commitment | D44: =D$100 -> 2025 | E44: =E$100 -> 2026 | F44: =F$100 -> 2027 | G44: =G$100 -> 2028 | H44: =H$100 -> 2029 | I44: =I$100 -> 2030 | J44: =J$100 -> 2031 | K44: =K$100 -> 2032 | ... R44: =R$100 -> 2039
B46: 0 | D46: =D36+D41 -> 0 | E46: =E36+E41 -> 0 | F46: =F36+F41 -> 0 | G46: =G36+G41 -> 0 | H46: =H36+H41 -> 0 | I46: =I36+I41 -> 0 | J46: =J36+J41 -> 0 | K46: =K36+K41 -> 0 | ... R46: =R36+R41 -> 0
A49: Net Cash Flow Cumulative | D49: =D46 -> 0 | E49: =D49+E46 -> 0 | F49: =E49+F46 -> 0 | G49: =F49+G46 -> 0 | H49: =G49+H46 -> 0 | I49: =H49+I46 -> 0 | J49: =I49+J46 -> 0 | K49: =J49+K46 -> 0 | L49: =K49+L46 -> 0 | ... R49: =Q49+R46 -> 0
A51: Cash invested | D51: Net Asset Value
A52: New Commitments | B52: Commitment | C52: % of Total Portfolio Value | D52: 2025 | E52: =D52+1 -> 2026 | F52: =E52+1 -> 2027 | G52: =F52+1 -> 2028 | H52: =G52+1 -> 2029 | I52: =H52+1 -> 2030 | J52: =I52+1 -> 2031 | K52: =J52+1 -> 2032 | L52: =K52+1 -> 2033 | ... R52: =Q52+1 -> 2039
B54: =SUM(K4:K18) -> 0 | C54: 10000000 | D54: =(C54+D146+D170)*(1+LTCMAs!$K$10) -> 4990428.6 | E54: =(D54+E146+E170)*(1+LTCMAs!$K$10) -> 4567421.1 | F54: =(E54+F146+F170)*(1+LTCMAs!$K$10) -> 3715115 | G54: =(F54+G146+G170)*(1+LTCMAs!$K$10) -> 2594610.2 | H54: =(G54+H146+H170)*(1+LTCMAs!$K$10) -> 1503831.8 | I54: =(H54+I146+I170)*(1+LTCMAs!$K$10) -> 596939.16 | J54: =(I54+J146+J170)*(1+LTCMAs!$K$10) -> 90520.41 | K54: =(J54+K146+K170)*(1+LTCMAs!$K$10) -> 21533.67 | ... R54: =(Q54+R146+R170)*(1+LTCMAs!$K$10) -> 8158798.7
D57: Annual Capital Called
A58: New Commitments | B58: Commitment | D58: =D$100 -> 2025 | E58: =E$100 -> 2026 | F58: =F$100 -> 2027 | G58: =G$100 -> 2028 | H58: =H$100 -> 2029 | I58: =I$100 -> 2030 | J58: =J$100 -> 2031 | K58: =K$100 -> 2032 | ... R58: =R$100 -> 2039
B60: =SUM(K4:K18) -> 0 | D60: =-K4 -> 0 | E60: =-$K5 -> 0 | F60: =-$K6 -> 0 | G60: =-$K7 -> 0 | H60: =-$K8 -> 0 | I60: =-$K9 -> 0 | J60: =-$K10 -> 0 | K60: =-$K11 -> 0 | L60: =-$K12 -> 0 | M60: =-$K13 -> 0 | N60: =-$K14 -> 0 | O60: =-$K15 -> 0 | P60: =-$K16 -> 0 | Q60: =-$K17 -> 0 | R60: =-$K18 -> 0
D62: Annual Distributions
A63: New Commitments | B63: Commitment | D63: =D$100 -> 2025 | E63: =E$100 -> 2026 | F63: =F$100 -> 2027 | G63: =G$100 -> 2028 | H63: =H$100 -> 2029 | I63: =I$100 -> 2030 | J63: =J$100 -> 2031 | K63: =K$100 -> 2032 | ... R63: =R$100 -> 2039
B65: =SUM(K4:K18) -> 0 | D65: =K4*$L$4 -> 0 | E65: =SUM($K4:$K5)*$L$4 -> 0 | F65: =SUM($K4:$K6)*$L$4 -> 0 | G65: =SUM($K4:$K7)*$L$4 -> 0 | H65: =SUM($K4:$K8)*$L$4 -> 0 | I65: =SUM($K4:$K9)*$L$4 -> 0 | J65: =SUM($K4:$K10)*$L$4 -> 0 | K65: =SUM($K4:$K11)*$L$4 -> 0 | L65: =SUM($K4:$K12)*$L$4 -> 0 | M65: =SUM($K4:$K13)*$L$4 -> 0 | N65: =SUM($K4:$K14)*$L$4 -> 0 | O65: =SUM($K4:$K15)*$L$4 -> 0 | P65: =SUM($K4:$K16)*$L$4 -> 0 | Q65: =SUM($K4:$K17)*$L$4 -> 0 | R65: =SUM($K4:$K18)*$L$4 -> 0
D67: Net Cash Flow
A68: New Commitments | B68: Commitment | D68: =D$100 -> 2025 | E68: =E$100 -> 2026 | F68: =F$100 -> 2027 | G68: =G$100 -> 2028 | H68: =H$100 -> 2029 | I68: =I$100 -> 2030 | J68: =J$100 -> 2031 | K68: =K$100 -> 2032 | ... R68: =R$100 -> 2039
B70: =SUM(K4:K18) -> 0 | D70: =D60+D65 -> 0 | E70: =E60+E65 -> 0 | F70: =F60+F65 -> 0 | G70: =G60+G65 -> 0 | H70: =H60+H65 -> 0 | I70: =I60+I65 -> 0 | J70: =J60+J65 -> 0 | K70: =K60+K65 -> 0 | ... R70: =R60+R65 -> 0
A73: Net Cash Flow Cumulative | D73: =D70 -> 0 | E73: =D73+E70 -> 0 | F73: =E73+F70 -> 0 | G73: =F73+G70 -> 0 | H73: =G73+H70 -> 0 | I73: =H73+I70 -> 0 | J73: =I73+J70 -> 0 | K73: =J73+K70 -> 0 | L73: =K73+L70 -> 0 | ... R73: =Q73+R70 -> 0
A75: NEW COMPOUNDING OPEN-ENDED PORTFOLIO | D75: Net Asset Value
A76: New Commitments | B76: Commitment | C76: % of Total Portfolio Value | D76: 2025 | E76: =D76+1 -> 2026 | F76: =E76+1 -> 2027 | G76: =F76+1 -> 2028 | H76: =G76+1 -> 2029 | I76: =H76+1 -> 2030 | J76: =I76+1 -> 2031 | K76: =J76+1 -> 2032 | L76: =K76+1 -> 2033 | ... R76: =Q76+1 -> 2039
B78: =SUM(H4:H18) -> 5000000 | D78: =H4*(1+$I$4) -> 5469500 | E78: =D78*(1+$I$4)+E$84*(1+$I$4) -> 5983086.1 | F78: =E78*(1+$I$4)+F$84*(1+$I$4) -> 6544897.8 | G78: =F78*(1+$I$4)+G$84*(1+$I$4) -> 7159463.7 | H78: =G78*(1+$I$4)+H$84*(1+$I$4) -> 7831737.4 | I78: =H78*(1+$I$4)+I$84*(1+$I$4) -> 8567137.5 | J78: =I78*(1+$I$4)+J$84*(1+$I$4) -> 9371591.7 | K78: =J78*(1+$I$4)+K$84*(1+$I$4) -> 10251584 | L78: =K78*(1+$I$4)+L$84*(1+$I$4) -> 11214208 | ... R78: =Q78*(1+$I$4)+R$84*(1+$I$4) -> 19214732
D81: Annual Capital Called
A82: New Commitments | B82: Commitment | D82: =D$100 -> 2025 | E82: =E$100 -> 2026 | F82: =F$100 -> 2027 | G82: =G$100 -> 2028 | H82: =H$100 -> 2029 | I82: =I$100 -> 2030 | J82: =J$100 -> 2031 | K82: =K$100 -> 2032 | ... R82: =R$100 -> 2039
B84: =SUM(H4:H18) -> 5000000 | D84: =-$H4 -> -5000000 | E84: =-$H5 -> 0 | F84: =-$H6 -> 0 | G84: =-$H7 -> 0 | H84: =-$H8 -> 0 | I84: =-$H9 -> 0 | J84: =-$H10 -> 0 | K84: =-$H11 -> 0 | L84: =-H12 -> 0 | M84: =-H13 -> 0 | N84: =-H14 -> 0 | O84: =-H15 -> 0 | P84: =-H16 -> 0 | Q84: =-H17 -> 0 | R84: =-H18 -> 0
D86: Annual Distributions
A87: New Commitments | B87: Commitment | D87: =D$100 -> 2025 | E87: =E$100 -> 2026 | F87: =F$100 -> 2027 | G87: =G$100 -> 2028 | H87: =H$100 -> 2029 | I87: =I$100 -> 2030 | J87: =J$100 -> 2031 | K87: =K$100 -> 2032 | ... R87: =R$100 -> 2039
B89: =SUM(H4:H18) -> 5000000 | D89: 0 | E89: 0 | F89: 0 | G89: 0 | H89: 0 | I89: 0 | J89: 0 | K89: 0 | L89: 0 | M89: 0 | N89: 0 | O89: 0 | P89: 0 | Q89: 0 | R89: 0
D91: Net Cash Flow
A92: New Commitments | B92: Commitment | D92: =D$100 -> 2025 | E92: =E$100 -> 2026 | F92: =F$100 -> 2027 | G92: =G$100 -> 2028 | H92: =H$100 -> 2029 | I92: =I$100 -> 2030 | J92: =J$100 -> 2031 | K92: =K$100 -> 2032 | ... R92: =R$100 -> 2039
B94: =SUM(H4:H18) -> 5000000 | D94: =D84+D89 -> -5000000 | E94: =E84+E89 -> 0 | F94: =F84+F89 -> 0 | G94: =G84+G89 -> 0 | H94: =H84+H89 -> 0 | I94: =I84+I89 -> 0 | J94: =J84+J89 -> 0 | K94: =K84+K89 -> 0 | ... R94: =R84+R89 -> 0
A97: Net Cash Flow Cumulative | D97: =SUM($D$94:D94) -> -5000000 | E97: =SUM($D$94:E94) -> -5000000 | F97: =SUM($D$94:F94) -> -5000000 | G97: =SUM($D$94:G94) -> -5000000 | H97: =SUM($D$94:H94) -> -5000000 | I97: =SUM($D$94:I94) -> -5000000 | J97: =SUM($D$94:J94) -> -5000000 | K97: =SUM($D$94:K94) -> -5000000 | ... R97: =SUM($D$94:R94) -> -5000000
A99: NEW DRAWDOWN PORTFOLIO | D99: Net Asset Value
A100: New Commitments | B100: Commitment | C100: % of Total Portfolio Value | D100: 2025 | E100: =D100+1 -> 2026 | F100: =E100+1 -> 2027 | G100: =F100+1 -> 2028 | H100: =G100+1 -> 2029 | I100: =H100+1 -> 2030 | J100: =I100+1 -> 2031 | K100: =J100+1 -> 2032 | L100: =K100+1 -> 2033 | ... R100: =Q100+1 -> 2039
A101: 2025 | B101: 1950000 | C101: =B101/$D4 -> 0.195 | D101: =VLOOKUP(D$100,'Aggregated Median CA data'!$D$126:$M$140,5,0)*$B101 -> 309899.42 | E101: =VLOOKUP(E$100,'Aggregated Median CA data'!$D$126:$M$140,5,0)*$B101 -> 688865.27 | F101: =VLOOKUP(F$100,'Aggregated Median CA data'!$D$126:$M$140,5,0)*$B101 -> 1120446.5 | G101: =VLOOKUP(G$100,'Aggregated Median CA data'!$D$126:$M$140,5,0)*$B101 -> 1464458 | H101: =VLOOKUP(H$100,'Aggregated Median CA data'!$D$126:$M$140,5,0)*$B101 -> 1642049 | I101: =VLOOKUP(I$100,'Aggregated Median CA data'!$D$126:$M$140,5,0)*$B101 -> 1571243.2 | J101: =VLOOKUP(J$100,'Aggregated Median CA data'!$D$126:$M$140,5,0)*$B101 -> 1430946.1 | K101: =VLOOKUP(K$100,'Aggregated Median CA data'!$D$126:$M$140,5,0)*$B101 -> 1213004.6 | ... R101: =VLOOKUP(R$100,'Aggregated Median CA data'!$D$126:$M$140,5,0)*$B101 -> 274819.34
A102: =A101+1 -> 2026 | B102: 1950000 | C102: =B102/$D5 -> 0.18378888 | E102: =IF($B102=0,0,(D101/$B101)*$B102) -> 309899.42 | F102: =IF($B102=0,0,(E101/$B101)*$B102) -> 688865.27 | G102: =IF($B102=0,0,(F101/$B101)*$B102) -> 1120446.5 | H102: =IF($B102=0,0,(G101/$B101)*$B102) -> 1464458 | I102: =IF($B102=0,0,(H101/$B101)*$B102) -> 1642049 | J102: =IF($B102=0,0,(I101/$B101)*$B102) -> 1571243.2 | K102: =IF($B102=0,0,(J101/$B101)*$B102) -> 1430946.1 | L102: =IF($B102=0,0,(K101/$B101)*$B102) -> 1213004.6 | ... R102: =IF($B102=0,0,(Q101/$B101)*$B102) -> 301535.6
A103: =A102+1 -> 2027 | B103: 1950000 | C103: =B103/$D6 -> 0.17322232 | F103: =IF($B103=0,0,(E102/$B102)*$B103) -> 309899.42 | G103: =IF($B103=0,0,(F102/$B102)*$B103) -> 688865.27 | H103: =IF($B103=0,0,(G102/$B102)*$B103) -> 1120446.5 | I103: =IF($B103=0,0,(H102/$B102)*$B103) -> 1464458 | J103: =IF($B103=0,0,(I102/$B102)*$B103) -> 1642049 | K103: =IF($B103=0,0,(J102/$B102)*$B103) -> 1571243.2 | L103: =IF($B103=0,0,(K102/$B102)*$B103) -> 1430946.1 | M103: =IF($B103=0,0,(L102/$B102)*$B103) -> 1213004.6 | ... R103: =IF($B103=0,0,(Q102/$B102)*$B103) -> 349355.81
A104: =A103+1 -> 2028 | B104: 1950000 | C104: =B104/$D7 -> 0.16326326 | G104: =IF($B104=0,0,(F103/$B103)*$B104) -> 309899.42 | H104: =IF($B104=0,0,(G103/$B103)*$B104) -> 688865.27 | I104: =IF($B104=0,0,(H103/$B103)*$B104) -> 1120446.5 | J104: =IF($B104=0,0,(I103/$B103)*$B104) -> 1464458 | K104: =IF($B104=0,0,(J103/$B103)*$B104) -> 1642049 | L104: =IF($B104=0,0,(K103/$B103)*$B104) -> 1571243.2 | M104: =IF($B104=0,0,(L103/$B103)*$B104) -> 1430946.1 | N104: =IF($B104=0,0,(M103/$B103)*$B104) -> 1213004.6 | ... R104: =IF($B104=0,0,(Q103/$B103)*$B104) -> 451028.09
A105: =A104+1 -> 2029 | B105: 1950000 | C105: =B105/$D8 -> 0.15387678 | H105: =IF($B105=0,0,(G104/$B104)*$B105) -> 309899.42 | I105: =IF($B105=0,0,(H104/$B104)*$B105) -> 688865.27 | J105: =IF($B105=0,0,(I104/$B104)*$B105) -> 1120446.5 | K105: =IF($B105=0,0,(J104/$B104)*$B105) -> 1464458 | L105: =IF($B105=0,0,(K104/$B104)*$B105) -> 1642049 | M105: =IF($B105=0,0,(L104/$B104)*$B105) -> 1571243.2 | N105: =IF($B105=0,0,(M104/$B104)*$B105) -> 1430946.1 | O105: =IF($B105=0,0,(N104/$B104)*$B105) -> 1213004.6 | ... R105: =IF($B105=0,0,(Q104/$B104)*$B105) -> 587231.4
A106: =A105+1 -> 2030 | B106: 1950000 | C106: =B106/$D9 -> 0.14502995 | I106: =IF($B106=0,0,(H105/$B105)*$B106) -> 309899.42 | J106: =IF($B106=0,0,(I105/$B105)*$B106) -> 688865.27 | K106: =IF($B106=0,0,(J105/$B105)*$B106) -> 1120446.5 | L106: =IF($B106=0,0,(K105/$B105)*$B106) -> 1464458 | M106: =IF($B106=0,0,(L105/$B105)*$B106) -> 1642049 | N106: =IF($B106=0,0,(M105/$B105)*$B106) -> 1571243.2 | O106: =IF($B106=0,0,(N105/$B105)*$B106) -> 1430946.1 | P106: =IF($B106=0,0,(O105/$B105)*$B106) -> 1213004.6 | ... R106: =IF($B106=0,0,(Q105/$B105)*$B106) -> 782135.17
A107: =A106+1 -> 2031 | B107: 1950000 | C107: =B107/$D10 -> 0.13669175 | J107: =IF($B107=0,0,(I106/$B106)*$B107) -> 309899.42 | K107: =IF($B107=0,0,(J106/$B106)*$B107) -> 688865.27 | L107: =IF($B107=0,0,(K106/$B106)*$B107) -> 1120446.5 | M107: =IF($B107=0,0,(L106/$B106)*$B107) -> 1464458 | N107: =IF($B107=0,0,(M106/$B106)*$B107) -> 1642049 | O107: =IF($B107=0,0,(N106/$B106)*$B107) -> 1571243.2 | P107: =IF($B107=0,0,(O106/$B106)*$B107) -> 1430946.1 | Q107: =IF($B107=0,0,(P106/$B106)*$B107) -> 1213004.6 | R107: =IF($B107=0,0,(Q106/$B106)*$B107) -> 961138.4
A108: =A107+1 -> 2032 | B108: 1950000 | C108: =B108/$D11 -> 0.12883294 | K108: =IF($B108=0,0,(J107/$B107)*$B108) -> 309899.42 | L108: =IF($B108=0,0,(K107/$B107)*$B108) -> 688865.27 | M108: =IF($B108=0,0,(L107/$B107)*$B108) -> 1120446.5 | N108: =IF($B108=0,0,(M107/$B107)*$B108) -> 1464458 | O108: =IF($B108=0,0,(N107/$B107)*$B108) -> 1642049 | P108: =IF($B108=0,0,(O107/$B107)*$B108) -> 1571243.2 | Q108: =IF($B108=0,0,(P107/$B107)*$B108) -> 1430946.1 | R108: =IF($B108=0,0,(Q107/$B107)*$B108) -> 1213004.6
A109: =A108+1 -> 2033 | B109: 1950000 | C109: =B109/$D12 -> 0.12142596 | L109: =IF($B109=0,0,(K108/$B108)*$B109) -> 309899.42 | M109: =IF($B109=0,0,(L108/$B108)*$B109) -> 688865.27 | N109: =IF($B109=0,0,(M108/$B108)*$B109) -> 1120446.5 | O109: =IF($B109=0,0,(N108/$B108)*$B109) -> 1464458 | P109: =IF($B109=0,0,(O108/$B108)*$B109) -> 1642049 | Q109: =IF($B109=0,0,(P108/$B108)*$B109) -> 1571243.2 | R109: =IF($B109=0,0,(Q108/$B108)*$B109) -> 1430946.1
A110: =A109+1 -> 2034 | B110: 1950000 | C110: =B110/$D13 -> 0.11444482 | M110: =IF($B110=0,0,(L109/$B109)*$B110) -> 309899.42 | N110: =IF($B110=0,0,(M109/$B109)*$B110) -> 688865.27 | O110: =IF($B110=0,0,(N109/$B109)*$B110) -> 1120446.5 | P110: =IF($B110=0,0,(O109/$B109)*$B110) -> 1464458 | Q110: =IF($B110=0,0,(P109/$B109)*$B110) -> 1642049 | R110: =IF($B110=0,0,(Q109/$B109)*$B110) -> 1571243.2
A111: =A110+1 -> 2035 | B111: 1950000 | C111: =B111/$D14 -> 0.10786506 | N111: =IF($B111=0,0,(M110/$B110)*$B111) -> 309899.42 | O111: =IF($B111=0,0,(N110/$B110)*$B111) -> 688865.27 | P111: =IF($B111=0,0,(O110/$B110)*$B111) -> 1120446.5 | Q111: =IF($B111=0,0,(P110/$B110)*$B111) -> 1464458 | R111: =IF($B111=0,0,(Q110/$B110)*$B111) -> 1642049
A112: =A111+1 -> 2036 | B112: 1950000 | C112: =B112/$D15 -> 0.10166358 | O112: =IF($B112=0,0,(N111/$B111)*$B112) -> 309899.42 | P112: =IF($B112=0,0,(O111/$B111)*$B112) -> 688865.27 | Q112: =IF($B112=0,0,(P111/$B111)*$B112) -> 1120446.5 | R112: =IF($B112=0,0,(Q111/$B111)*$B112) -> 1464458
A113: =A112+1 -> 2037 | B113: 1950000 | C113: =B113/$D16 -> 0.09581864 | P113: =IF($B113=0,0,(O112/$B112)*$B113) -> 309899.42 | Q113: =IF($B113=0,0,(P112/$B112)*$B113) -> 688865.27 | R113: =IF($B113=0,0,(Q112/$B112)*$B113) -> 1120446.5
A114: =A113+1 -> 2038 | B114: 1950000 | C114: =B114/$D17 -> 0.090309746 | Q114: =IF($B114=0,0,(P113/$B113)*$B114) -> 309899.42 | R114: =IF($B114=0,0,(Q113/$B113)*$B114) -> 688865.27
A115: =A114+1 -> 2039 | B115: 1950000 | C115: =B115/$D18 -> 0.085117574 | R115: =IF($B115=0,0,(Q114/$B114)*$B115) -> 309899.42
A117: Total New | D117: =SUM(D101:D115) -> 309899.42 | E117: =SUM(E101:E115) -> 998764.69 | F117: =SUM(F101:F115) -> 2119211.2 | G117: =SUM(G101:G115) -> 3583669.3 | H117: =SUM(H101:H115) -> 5225718.2 | I117: =SUM(I101:I115) -> 6796961.4 | J117: =SUM(J101:J115) -> 8227907.5 | K117: =SUM(K101:K115) -> 9440912.1 | ... R117: =SUM(R101:R115) -> 13148156
A119: Total New + Open-ended PE | D119: =SUM(D117,D78,D54,D30) -> 10769828 | E119: =SUM(E117,E78,E54,E30) -> 11549272 | F119: =SUM(F117,F78,F54,F30) -> 12379224 | G119: =SUM(G117,G78,G54,G30) -> 13337743 | H119: =SUM(H117,H78,H54,H30) -> 14561287 | I119: =SUM(I117,I78,I54,I30) -> 15961038 | J119: =SUM(J117,J78,J54,J30) -> 17690020 | K119: =SUM(K117,K78,K54,K30) -> 19714030 | ... R119: =SUM(R117,R78,R54,R30) -> 40521687
A121: Total Mandate MV | D121: =$D$4 -> 10000000 | E121: =$D$5 -> 10610000 | F121: =$D$6 -> 11257210 | G121: =$D$7 -> 11943900 | H121: =$D$8 -> 12672478 | I121: =$D$9 -> 13445499 | J121: =$D$10 -> 14265674 | K121: =$D$11 -> 15135880 | L121: =$D$12 -> 16059169 | M121: =$D$13 -> 17038778 | N121: =$D$14 -> 18078144 | O121: =$D$15 -> 19180911 | P121: =$D$16 -> 20350946 | Q121: =$D$17 -> 21592354 | R121: =$D$18 -> 22909488
A122: % | D122: =D119/D121 -> 1.0769828 | E122: =E119/E121 -> 1.088527 | F122: =F119/F121 -> 1.0996707 | G122: =G119/G121 -> 1.1166992 | H122: =H119/H121 -> 1.1490482 | I122: =I119/I121 -> 1.1870916 | J122: =J119/J121 -> 1.2400409 | K122: =K119/K121 -> 1.30247 | ... R122: =R119/R121 -> 1.7687732
C123: Portfolio Value | D123: =D121/1000000 -> 10 | E123: =E121/1000000 -> 10.61 | F123: =F121/1000000 -> 11.25721 | G123: =G121/1000000 -> 11.9439 | H123: =H121/1000000 -> 12.672478 | I123: =I121/1000000 -> 13.445499 | J123: =J121/1000000 -> 14.265674 | K123: =K121/1000000 -> 15.13588 | ... R123: =R121/1000000 -> 22.909488
C124: Commitments | D124: =$B$101/1000000 -> 1.95 | E124: =$B$102/1000000 -> 1.95 | F124: =$B$103/1000000 -> 1.95 | G124: =$B$104/1000000 -> 1.95 | H124: =$B$105/1000000 -> 1.95 | I124: =$B$106/1000000 -> 1.95 | J124: =$B$107/1000000 -> 1.95 | K124: =$B$108/1000000 -> 1.95 | L124: =$B$109/1000000 -> 1.95 | M124: =$B$110/1000000 -> 1.95 | N124: =$B$111/1000000 -> 1.95 | O124: =$B$112/1000000 -> 1.95 | P124: =$B$113/1000000 -> 1.95 | Q124: =$B$114/1000000 -> 1.95 | R124: =$B$115/1000000 -> 1.95
C125: PI Portfolio NAV | D125: =D119/1000000 -> 10.769828 | E125: =E119/1000000 -> 11.549272 | F125: =F119/1000000 -> 12.379224 | G125: =G119/1000000 -> 13.337743 | H125: =H119/1000000 -> 14.561287 | I125: =I119/1000000 -> 15.961038 | J125: =J119/1000000 -> 17.69002 | K125: =K119/1000000 -> 19.71403 | ... R125: =R119/1000000 -> 40.521687
D126: Annual Capital Called
A127: New Commitments | B127: Commitment | D127: =D$100 -> 2025 | E127: =E$100 -> 2026 | F127: =F$100 -> 2027 | G127: =G$100 -> 2028 | H127: =H$100 -> 2029 | I127: =I$100 -> 2030 | J127: =J$100 -> 2031 | K127: =K$100 -> 2032 | ... R127: =R$100 -> 2039
A128: =A101 -> 2025 | B128: =B101 -> 1950000 | D128: =VLOOKUP(D$100,'Aggregated Median CA data'!$D$126:$M$140,7,0)*$B128 -> -336048.03 | E128: =VLOOKUP(E$100,'Aggregated Median CA data'!$D$126:$M$140,7,0)*$B128 -> -387263.03 | F128: =VLOOKUP(F$100,'Aggregated Median CA data'!$D$126:$M$140,7,0)*$B128 -> -414669.3 | G128: =VLOOKUP(G$100,'Aggregated Median CA data'!$D$126:$M$140,7,0)*$B128 -> -361674.65 | H128: =VLOOKUP(H$100,'Aggregated Median CA data'!$D$126:$M$140,7,0)*$B128 -> -225508.77 | I128: =VLOOKUP(I$100,'Aggregated Median CA data'!$D$126:$M$140,7,0)*$B128 -> -114394.37 | J128: =VLOOKUP(J$100,'Aggregated Median CA data'!$D$126:$M$140,7,0)*$B128 -> -51669.698 | K128: =VLOOKUP(K$100,'Aggregated Median CA data'!$D$126:$M$140,7,0)*$B128 -> -30396.051 | ... R128: =VLOOKUP(R$100,'Aggregated Median CA data'!$D$126:$M$140,7,0)*$B128 -> -765.16417
A129: =A102 -> 2026 | B129: =B102 -> 1950000 | E129: =IFERROR((D128/$B128)*$B129,0) -> -336048.03 | F129: =IFERROR((E128/$B128)*$B129,0) -> -387263.03 | G129: =IFERROR((F128/$B128)*$B129,0) -> -414669.3 | H129: =IFERROR((G128/$B128)*$B129,0) -> -361674.65 | I129: =IFERROR((H128/$B128)*$B129,0) -> -225508.77 | J129: =IFERROR((I128/$B128)*$B129,0) -> -114394.37 | K129: =IFERROR((J128/$B128)*$B129,0) -> -51669.698 | L129: =IFERROR((K128/$B128)*$B129,0) -> -30396.051 | ... R129: =IFERROR((Q128/$B128)*$B129,0) -> -177.83398
A130: =A103 -> 2027 | B130: =B103 -> 1950000 | F130: =IFERROR((E129/$B129)*$B130,0) -> -336048.03 | G130: =IFERROR((F129/$B129)*$B130,0) -> -387263.03 | H130: =IFERROR((G129/$B129)*$B130,0) -> -414669.3 | I130: =IFERROR((H129/$B129)*$B130,0) -> -361674.65 | J130: =IFERROR((I129/$B129)*$B130,0) -> -225508.77 | K130: =IFERROR((J129/$B129)*$B130,0) -> -114394.37 | L130: =IFERROR((K129/$B129)*$B130,0) -> -51669.698 | M130: =IFERROR((L129/$B129)*$B130,0) -> -30396.051 | ... R130: =IFERROR((Q129/$B129)*$B130,0) -> -2115.4239
A131: =A104 -> 2028 | B131: =B104 -> 1950000 | G131: =IFERROR((F130/$B130)*$B131,0) -> -336048.03 | H131: =IFERROR((G130/$B130)*$B131,0) -> -387263.03 | I131: =IFERROR((H130/$B130)*$B131,0) -> -414669.3 | J131: =IFERROR((I130/$B130)*$B131,0) -> -361674.65 | K131: =IFERROR((J130/$B130)*$B131,0) -> -225508.77 | L131: =IFERROR((K130/$B130)*$B131,0) -> -114394.37 | M131: =IFERROR((L130/$B130)*$B131,0) -> -51669.698 | N131: =IFERROR((M130/$B130)*$B131,0) -> -30396.051 | ... R131: =IFERROR((Q130/$B130)*$B131,0) -> -2917.0972
A132: =A105 -> 2029 | B132: =B105 -> 1950000 | H132: =IFERROR((G131/$B131)*$B132,0) -> -336048.03 | I132: =IFERROR((H131/$B131)*$B132,0) -> -387263.03 | J132: =IFERROR((I131/$B131)*$B132,0) -> -414669.3 | K132: =IFERROR((J131/$B131)*$B132,0) -> -361674.65 | L132: =IFERROR((K131/$B131)*$B132,0) -> -225508.77 | M132: =IFERROR((L131/$B131)*$B132,0) -> -114394.37 | N132: =IFERROR((M131/$B131)*$B132,0) -> -51669.698 | O132: =IFERROR((N131/$B131)*$B132,0) -> -30396.051 | ... R132: =IFERROR((Q131/$B131)*$B132,0) -> -5299.5409
A133: =A106 -> 2030 | B133: =B106 -> 1950000 | I133: =IFERROR((H132/$B132)*$B133,0) -> -336048.03 | J133: =IFERROR((I132/$B132)*$B133,0) -> -387263.03 | K133: =IFERROR((J132/$B132)*$B133,0) -> -414669.3 | L133: =IFERROR((K132/$B132)*$B133,0) -> -361674.65 | M133: =IFERROR((L132/$B132)*$B133,0) -> -225508.77 | N133: =IFERROR((M132/$B132)*$B133,0) -> -114394.37 | O133: =IFERROR((N132/$B132)*$B133,0) -> -51669.698 | P133: =IFERROR((O132/$B132)*$B133,0) -> -30396.051 | ... R133: =IFERROR((Q132/$B132)*$B133,0) -> -7975.1401
A134: =A107 -> 2031 | B134: =B107 -> 1950000 | J134: =IFERROR((I133/$B133)*$B134,0) -> -336048.03 | K134: =IFERROR((J133/$B133)*$B134,0) -> -387263.03 | L134: =IFERROR((K133/$B133)*$B134,0) -> -414669.3 | M134: =IFERROR((L133/$B133)*$B134,0) -> -361674.65 | N134: =IFERROR((M133/$B133)*$B134,0) -> -225508.77 | O134: =IFERROR((N133/$B133)*$B134,0) -> -114394.37 | P134: =IFERROR((O133/$B133)*$B134,0) -> -51669.698 | Q134: =IFERROR((P133/$B133)*$B134,0) -> -30396.051 | R134: =IFERROR((Q133/$B133)*$B134,0) -> -11472.056
A135: =A108 -> 2032 | B135: =B108 -> 1950000 | K135: =IFERROR((J134/$B134)*$B135,0) -> -336048.03 | L135: =IFERROR((K134/$B134)*$B135,0) -> -387263.03 | M135: =IFERROR((L134/$B134)*$B135,0) -> -414669.3 | N135: =IFERROR((M134/$B134)*$B135,0) -> -361674.65 | O135: =IFERROR((N134/$B134)*$B135,0) -> -225508.77 | P135: =IFERROR((O134/$B134)*$B135,0) -> -114394.37 | Q135: =IFERROR((P134/$B134)*$B135,0) -> -51669.698 | R135: =IFERROR((Q134/$B134)*$B135,0) -> -30396.051
A136: =A109 -> 2033 | B136: =B109 -> 1950000 | L136: =IFERROR((K135/$B135)*$B136,0) -> -336048.03 | M136: =IFERROR((L135/$B135)*$B136,0) -> -387263.03 | N136: =IFERROR((M135/$B135)*$B136,0) -> -414669.3 | O136: =IFERROR((N135/$B135)*$B136,0) -> -361674.65 | P136: =IFERROR((O135/$B135)*$B136,0) -> -225508.77 | Q136: =IFERROR((P135/$B135)*$B136,0) -> -114394.37 | R136: =IFERROR((Q135/$B135)*$B136,0) -> -51669.698
A137: =A110 -> 2034 | B137: =B110 -> 1950000 | M137: =IFERROR((L136/$B136)*$B137,0) -> -336048.03 | N137: =IFERROR((M136/$B136)*$B137,0) -> -387263.03 | O137: =IFERROR((N136/$B136)*$B137,0) -> -414669.3 | P137: =IFERROR((O136/$B136)*$B137,0) -> -361674.65 | Q137: =IFERROR((P136/$B136)*$B137,0) -> -225508.77 | R137: =IFERROR((Q136/$B136)*$B137,0) -> -114394.37
A138: =A111 -> 2035 | B138: =B111 -> 1950000 | N138: =IFERROR((M137/$B137)*$B138,0) -> -336048.03 | O138: =IFERROR((N137/$B137)*$B138,0) -> -387263.03 | P138: =IFERROR((O137/$B137)*$B138,0) -> -414669.3 | Q138: =IFERROR((P137/$B137)*$B138,0) -> -361674.65 | R138: =IFERROR((Q137/$B137)*$B138,0) -> -225508.77
A139: =A112 -> 2036 | B139: =B112 -> 1950000 | O139: =IFERROR((N138/$B138)*$B139,0) -> -336048.03 | P139: =IFERROR((O138/$B138)*$B139,0) -> -387263.03 | Q139: =IFERROR((P138/$B138)*$B139,0) -> -414669.3 | R139: =IFERROR((Q138/$B138)*$B139,0) -> -361674.65
A140: =A113 -> 2037 | B140: =B113 -> 1950000 | P140: =IFERROR((O139/$B139)*$B140,0) -> -336048.03 | Q140: =IFERROR((P139/$B139)*$B140,0) -> -387263.03 | R140: =IFERROR((Q139/$B139)*$B140,0) -> -414669.3
A141: =A114 -> 2038 | B141: =B114 -> 1950000 | Q141: =IFERROR((P140/$B140)*$B141,0) -> -336048.03 | R141: =IFERROR((Q140/$B140)*$B141,0) -> -387263.03
A142: =A115 -> 2039 | B142: =B115 -> 1950000 | R142: =IFERROR((Q141/$B141)*$B142,0) -> -336048.03
A144: Total New | D144: =SUM(D128:D142) -> -336048.03 | E144: =SUM(E128:E142) -> -723311.06 | F144: =SUM(F128:F142) -> -1137980.4 | G144: =SUM(G128:G142) -> -1499655 | H144: =SUM(H128:H142) -> -1725163.8 | I144: =SUM(I128:I142) -> -1839558.1 | J144: =SUM(J128:J142) -> -1891227.8 | K144: =SUM(K128:K142) -> -1921623.9 | ... R144: =SUM(R128:R142) -> -1952346.1
A146: Total Existing + New + Open-ended PE | D146: =SUM(D144,D84,D60,D36) -> -5336048 | E146: =SUM(E144,E84,E60,E36) -> -723311.06 | F146: =SUM(F144,F84,F60,F36) -> -1137980.4 | G146: =SUM(G144,G84,G60,G36) -> -1499655 | H146: =SUM(H144,H84,H60,H36) -> -1725163.8 | I146: =SUM(I144,I84,I60,I36) -> -1839558.1 | J146: =SUM(J144,J84,J60,J36) -> -1891227.8 | K146: =SUM(K144,K84,K60,K36) -> -1921623.9 | ... R146: =SUM(R144,R84,R60,R36) -> -1952346.1
A148: Cumulative called | D148: =D146 -> -5336048 | E148: =SUM($D$146:E147) -> -6059359.1 | F148: =SUM($D$146:F147) -> -7197339.4 | G148: =SUM($D$146:G147) -> -8696994.5 | H148: =SUM($D$146:H147) -> -10422158 | I148: =SUM($D$146:I147) -> -12261716 | J148: =SUM($D$146:J147) -> -14152944 | K148: =SUM($D$146:K147) -> -16074568 | L148: =SUM($D$146:L147) -> -18007664 | ... R148: =SUM($D$146:R147) -> -29699724
...

Sheet LTCMAs
K5: Compound Return
J6: US Cash | K6: 0.031
J7: US Agg Bonds | K7: 0.048
J8: AC World Equity | K8: 0.07
J9: Private Equity | K9: 0.102
J10: AC World Equity | K10: 0.07
J11: Evergreen | K11: =(K9*0.85)+(K7*0.15) -> 0.0939
J12: AC World Equity
R21: Not sure how they are getting to 6.4%

Sheet Aggregated Median CA data
E1: 12 | F1: 14 | G1: 16 | H1: 18 | J1: 3 | K1: 5 | L1: 7 | M1: 9 | O1: 13 | P1: 15 | Q1: 17 | R1: 19 | T1: 4 | U1: 6 | V1: 8 | W1: 10
E2: Cumulative | J2: Annual | O2: Cumulative Standard Deviation | T2: Annual Standard Deviation
C3: Year | D3: Year | E3: PICC | F3: DCC | G3: Net | H3: RVCC | J3: PICC | K3: DCC | L3: Net | M3: RVCC | O3: PICC | P3: DCC | Q3: Net | R3: RVCC | T3: PICC | U3: DCC | V3: Net | W3: RVCC
A4: Buyout | B4: 1 | C4: Year 1 | D4: 2025 | E4: =VLOOKUP($B4,'Global Buyout'!$A$4:$S$19,E$1,0) -> -0.17233232 | F4: =VLOOKUP($B4,'Global Buyout'!$A$4:$S$19,F$1,0) -> 0 | G4: =VLOOKUP($B4,'Global Buyout'!$A$4:$S$19,G$1,0) -> -0.17233232 | H4: =VLOOKUP($B4,'Global Buyout'!$A$4:$S$19,H$1,0) -> 0.15892278 | J4: =VLOOKUP($B4,'Global Buyout'!$A$4:$S$19,J$1,0) -> -0.17233232 | K4: =VLOOKUP($B4,'Global Buyout'!$A$4:$S$19,K$1,0) -> 0 | L4: =VLOOKUP($B4,'Global Buyout'!$A$4:$S$19,L$1,0) -> -0.17233232 | M4: =VLOOKUP($B4,'Global Buyout'!$A$4:$S$19,M$1,0) -> 0.15892278 | O4: =VLOOKUP($B4,'Global Buyout'!$A$4:$S$19,O$1,0) -> 0.071281608 | P4: =VLOOKUP($B4,'Global Buyout'!$A$4:$S$19,P$1,0) -> 0 | Q4: =VLOOKUP($B4,'Global Buyout'!$A$4:$S$19,Q$1,0) -> 0.071281608 | R4: =VLOOKUP($B4,'Global Buyout'!$A$4:$S$19,R$1,0) -> 0.06951452 | T4: =VLOOKUP($B4,'Global Buyout'!$A$4:$S$19,T$1,0) -> 0.066877745 | U4: =VLOOKUP($B4,'Global Buyout'!$A$4:$S$19,U$1,0) -> 0 | V4: =VLOOKUP($B4,'Global Buyout'!$A$4:$S$19,V$1,0) -> 0.066877745 | W4: =VLOOKUP($B4,'Global Buyout'!$A$4:$S$19,W$1,0) -> 0.06951452
A5: Buyout | B5: =B4+1 -> 2 | C5: Year 2 | D5: =D4+1 -> 2026 | E5: =VLOOKUP($B5,'Global Buyout'!$A$4:$S$19,E$1,0) -> -0.37092875 | F5: =VLOOKUP($B5,'Global Buyout'!$A$4:$S$19,F$1,0) -> 0.00076937362 | G5: =VLOOKUP($B5,'Global Buyout'!$A$4:$S$19,G$1,0) -> -0.37015937 | H5: =VLOOKUP($B5,'Global Buyout'!$A$4:$S$19,H$1,0) -> 0.35326424 | J5: =VLOOKUP($B5,'Global Buyout'!$A$4:$S$19,J$1,0) -> -0.19859642 | K5: =VLOOKUP($B5,'Global Buyout'!$A$4:$S$19,K$1,0) -> 0.00076937362 | L5: =VLOOKUP($B5,'Global Buyout'!$A$4:$S$19,L$1,0) -> -0.19782705 | M5: =VLOOKUP($B5,'Global Buyout'!$A$4:$S$19,M$1,0) -> 0.35326424 | O5: =VLOOKUP($B5,'Global Buyout'!$A$4:$S$19,O$1,0) -> 0.088515872 | P5: =VLOOKUP($B5,'Global Buyout'!$A$4:$S$19,P$1,0) -> 0.0021904756 | Q5: =VLOOKUP($B5,'Global Buyout'!$A$4:$S$19,Q$1,0) -> 0.088542971 | R5: =VLOOKUP($B5,'Global Buyout'!$A$4:$S$19,R$1,0) -> 0.087742984 | T5: =VLOOKUP($B5,'Global Buyout'!$A$4:$S$19,T$1,0) -> 0.052478489 | U5: =VLOOKUP($B5,'Global Buyout'!$A$4:$S$19,U$1,0) -> 0.0021904756 | V5: =VLOOKUP($B5,'Global Buyout'!$A$4:$S$19,V$1,0) -> 0.052524185 | W5: =VLOOKUP($B5,'Global Buyout'!$A$4:$S$19,W$1,0) -> 0.087742984
A6: Buyout | B6: =B5+1 -> 3 | C6: Year 3 | D6: =D5+1 -> 2027 | E6: =VLOOKUP($B6,'Global Buyout'!$A$4:$S$19,E$1,0) -> -0.58357967 | F6: =VLOOKUP($B6,'Global Buyout'!$A$4:$S$19,F$1,0) -> 0.021861211 | G6: =VLOOKUP($B6,'Global Buyout'!$A$4:$S$19,G$1,0) -> -0.56171846 | H6: =VLOOKUP($B6,'Global Buyout'!$A$4:$S$19,H$1,0) -> 0.57458796 | J6: =VLOOKUP($B6,'Global Buyout'!$A$4:$S$19,J$1,0) -> -0.21265092 | K6: =VLOOKUP($B6,'Global Buyout'!$A$4:$S$19,K$1,0) -> 0.021091838 | L6: =VLOOKUP($B6,'Global Buyout'!$A$4:$S$19,L$1,0) -> -0.19155909 | M6: =VLOOKUP($B6,'Global Buyout'!$A$4:$S$19,M$1,0) -> 0.57458796 | O6: =VLOOKUP($B6,'Global Buyout'!$A$4:$S$19,O$1,0) -> 0.10776371 | P6: =VLOOKUP($B6,'Global Buyout'!$A$4:$S$19,P$1,0) -> 0.019305403 | Q6: =VLOOKUP($B6,'Global Buyout'!$A$4:$S$19,Q$1,0) -> 0.10947929 | R6: =VLOOKUP($B6,'Global Buyout'!$A$4:$S$19,R$1,0) -> 0.11673267 | T6: =VLOOKUP($B6,'Global Buyout'!$A$4:$S$19,T$1,0) -> 0.061465086 | U6: =VLOOKUP($B6,'Global Buyout'!$A$4:$S$19,U$1,0) -> 0.01918073 | V6: =VLOOKUP($B6,'Global Buyout'!$A$4:$S$19,V$1,0) -> 0.064388331 | W6: =VLOOKUP($B6,'Global Buyout'!$A$4:$S$19,W$1,0) -> 0.11673267
A7: Buyout | B7: =B6+1 -> 4 | C7: Year 4 | D7: =D6+1 -> 2028 | E7: =VLOOKUP($B7,'Global Buyout'!$A$4:$S$19,E$1,0) -> -0.76905385 | F7: =VLOOKUP($B7,'Global Buyout'!$A$4:$S$19,F$1,0) -> 0.10738943 | G7: =VLOOKUP($B7,'Global Buyout'!$A$4:$S$19,G$1,0) -> -0.66166442 | H7: =VLOOKUP($B7,'Global Buyout'!$A$4:$S$19,H$1,0) -> 0.75100413 | J7: =VLOOKUP($B7,'Global Buyout'!$A$4:$S$19,J$1,0) -> -0.18547418 | K7: =VLOOKUP($B7,'Global Buyout'!$A$4:$S$19,K$1,0) -> 0.085528218 | L7: =VLOOKUP($B7,'Global Buyout'!$A$4:$S$19,L$1,0) -> -0.09994596 | M7: =VLOOKUP($B7,'Global Buyout'!$A$4:$S$19,M$1,0) -> 0.75100413 | O7: =VLOOKUP($B7,'Global Buyout'!$A$4:$S$19,O$1,0) -> 0.11925917 | P7: =VLOOKUP($B7,'Global Buyout'!$A$4:$S$19,P$1,0) -> 0.053021567 | Q7: =VLOOKUP($B7,'Global Buyout'!$A$4:$S$19,Q$1,0) -> 0.1305145 | R7: =VLOOKUP($B7,'Global Buyout'!$A$4:$S$19,R$1,0) -> 0.14393299 | T7: =VLOOKUP($B7,'Global Buyout'!$A$4:$S$19,T$1,0) -> 0.051085547 | U7: =VLOOKUP($B7,'Global Buyout'!$A$4:$S$19,U$1,0) -> 0.049382061 | V7: =VLOOKUP($B7,'Global Buyout'!$A$4:$S$19,V$1,0) -> 0.071051538 | W7: =VLOOKUP($B7,'Global Buyout'!$A$4:$S$19,W$1,0) -> 0.14393299
A8: Buyout | B8: =B7+1 -> 5 | C8: Year 5 | D8: =D7+1 -> 2029 | E8: =VLOOKUP($B8,'Global Buyout'!$A$4:$S$19,E$1,0) -> -0.88469937 | F8: =VLOOKUP($B8,'Global Buyout'!$A$4:$S$19,F$1,0) -> 0.27487377 | G8: =VLOOKUP($B8,'Global Buyout'!$A$4:$S$19,G$1,0) -> -0.6098256 | H8: =VLOOKUP($B8,'Global Buyout'!$A$4:$S$19,H$1,0) -> 0.84207639 | J8: =VLOOKUP($B8,'Global Buyout'!$A$4:$S$19,J$1,0) -> -0.11564552 | K8: =VLOOKUP($B8,'Global Buyout'!$A$4:$S$19,K$1,0) -> 0.16748434 | L8: =VLOOKUP($B8,'Global Buyout'!$A$4:$S$19,L$1,0) -> 0.051838821 | M8: =VLOOKUP($B8,'Global Buyout'!$A$4:$S$19,M$1,0) -> 0.84207639 | O8: =VLOOKUP($B8,'Global Buyout'!$A$4:$S$19,O$1,0) -> 0.13066982 | P8: =VLOOKUP($B8,'Global Buyout'!$A$4:$S$19,P$1,0) -> 0.10392418 | Q8: =VLOOKUP($B8,'Global Buyout'!$A$4:$S$19,Q$1,0) -> 0.16695759 | R8: =VLOOKUP($B8,'Global Buyout'!$A$4:$S$19,R$1,0) -> 0.18199231 | T8: =VLOOKUP($B8,'Global Buyout'!$A$4:$S$19,T$1,0) -> 0.05340274 | U8: =VLOOKUP($B8,'Global Buyout'!$A$4:$S$19,U$1,0) -> 0.089380914 | V8: =VLOOKUP($B8,'Global Buyout'!$A$4:$S$19,V$1,0) -> 0.10411916 | W8: =VLOOKUP($B8,'Global Buyout'!$A$4:$S$19,W$1,0) -> 0.18199231
A9: Buyout | B9: =B8+1 -> 6 | C9: Year 6 | D9: =D8+1 -> 2030 | E9: =VLOOKUP($B9,'Global Buyout'!$A$4:$S$19,E$1,0) -> -0.94336315 | F9: =VLOOKUP($B9,'Global Buyout'!$A$4:$S$19,F$1,0) -> 0.45826327 | G9: =VLOOKUP($B9,'Global Buyout'!$A$4:$S$19,G$1,0) -> -0.48509988 | H9: =VLOOKUP($B9,'Global Buyout'!$A$4:$S$19,H$1,0) -> 0.80576574 | J9: =VLOOKUP($B9,'Global Buyout'!$A$4:$S$19,J$1,0) -> -0.058663778 | K9: =VLOOKUP($B9,'Global Buyout'!$A$4:$S$19,K$1,0) -> 0.1833895 | L9: =VLOOKUP($B9,'Global Buyout'!$A$4:$S$19,L$1,0) -> 0.12472572 | M9: =VLOOKUP($B9,'Global Buyout'!$A$4:$S$19,M$1,0) -> 0.80576574 | O9: =VLOOKUP($B9,'Global Buyout'!$A$4:$S$19,O$1,0) -> 0.1353251 | P9: =VLOOKUP($B9,'Global Buyout'!$A$4:$S$19,P$1,0) -> 0.1381456 | Q9: =VLOOKUP($B9,'Global Buyout'!$A$4:$S$19,Q$1,0) -> 0.19338327 | R9: =VLOOKUP($B9,'Global Buyout'!$A$4:$S$19,R$1,0) -> 0.20880906 | T9: =VLOOKUP($B9,'Global Buyout'!$A$4:$S$19,T$1,0) -> 0.035189222 | U9: =VLOOKUP($B9,'Global Buyout'!$A$4:$S$19,U$1,0) -> 0.091016331 | V9: =VLOOKUP($B9,'Global Buyout'!$A$4:$S$19,V$1,0) -> 0.097582037 | W9: =VLOOKUP($B9,'Global Buyout'!$A$4:$S$19,W$1,0) -> 0.20880906
A10: Buyout | B10: =B9+1 -> 7 | C10: Year 7 | D10: =D9+1 -> 2031 | E10: =VLOOKUP($B10,'Global Buyout'!$A$4:$S$19,E$1,0) -> -0.96986043 | F10: =VLOOKUP($B10,'Global Buyout'!$A$4:$S$19,F$1,0) -> 0.70712164 | G10: =VLOOKUP($B10,'Global Buyout'!$A$4:$S$19,G$1,0) -> -0.26273879 | H10: =VLOOKUP($B10,'Global Buyout'!$A$4:$S$19,H$1,0) -> 0.73381849 | J10: =VLOOKUP($B10,'Global Buyout'!$A$4:$S$19,J$1,0) -> -0.026497281 | K10: =VLOOKUP($B10,'Global Buyout'!$A$4:$S$19,K$1,0) -> 0.24885836 | L10: =VLOOKUP($B10,'Global Buyout'!$A$4:$S$19,L$1,0) -> 0.22236108 | M10: =VLOOKUP($B10,'Global Buyout'!$A$4:$S$19,M$1,0) -> 0.73381849 | O10: =VLOOKUP($B10,'Global Buyout'!$A$4:$S$19,O$1,0) -> 0.13669497 | P10: =VLOOKUP($B10,'Global Buyout'!$A$4:$S$19,P$1,0) -> 0.1971422 | Q10: =VLOOKUP($B10,'Global Buyout'!$A$4:$S$19,Q$1,0) -> 0.23989698 | R10: =VLOOKUP($B10,'Global Buyout'!$A$4:$S$19,R$1,0) -> 0.23325753 | T10: =VLOOKUP($B10,'Global Buyout'!$A$4:$S$19,T$1,0) -> 0.019303637 | U10: =VLOOKUP($B10,'Global Buyout'!$A$4:$S$19,U$1,0) -> 0.14064438 | V10: =VLOOKUP($B10,'Global Buyout'!$A$4:$S$19,V$1,0) -> 0.14196293 | W10: =VLOOKUP($B10,'Global Buyout'!$A$4:$S$19,W$1,0) -> 0.23325753
A11: Buyout | B11: =B10+1 -> 8 | C11: Year 8 | D11: =D10+1 -> 2032 | E11: =VLOOKUP($B11,'Global Buyout'!$A$4:$S$19,E$1,0) -> -0.98544815 | F11: =VLOOKUP($B11,'Global Buyout'!$A$4:$S$19,F$1,0) -> 0.9493479 | G11: =VLOOKUP($B11,'Global Buyout'!$A$4:$S$19,G$1,0) -> -0.036100249 | H11: =VLOOKUP($B11,'Global Buyout'!$A$4:$S$19,H$1,0) -> 0.62205367 | J11: =VLOOKUP($B11,'Global Buyout'!$A$4:$S$19,J$1,0) -> -0.015587719 | K11: =VLOOKUP($B11,'Global Buyout'!$A$4:$S$19,K$1,0) -> 0.24222626 | L11: =VLOOKUP($B11,'Global Buyout'!$A$4:$S$19,L$1,0) -> 0.22663854 | M11: =VLOOKUP($B11,'Global Buyout'!$A$4:$S$19,M$1,0) -> 0.62205367 | O11: =VLOOKUP($B11,'Global Buyout'!$A$4:$S$19,O$1,0) -> 0.13737405 | P11: =VLOOKUP($B11,'Global Buyout'!$A$4:$S$19,P$1,0) -> 0.23161404 | Q11: =VLOOKUP($B11,'Global Buyout'!$A$4:$S$19,Q$1,0) -> 0.26928924 | R11: =VLOOKUP($B11,'Global Buyout'!$A$4:$S$19,R$1,0) -> 0.25240624 | T11: =VLOOKUP($B11,'Global Buyout'!$A$4:$S$19,T$1,0) -> 0.013642414 | U11: =VLOOKUP($B11,'Global Buyout'!$A$4:$S$19,U$1,0) -> 0.12157309 | V11: =VLOOKUP($B11,'Global Buyout'!$A$4:$S$19,V$1,0) -> 0.12233614 | W11: =VLOOKUP($B11,'Global Buyout'!$A$4:$S$19,W$1,0) -> 0.25240624
A12: Buyout | B12: =B11+1 -> 9 | C12: Year 9 | D12: =D11+1 -> 2033 | E12: =VLOOKUP($B12,'Global Buyout'!$A$4:$S$19,E$1,0) -> -0.99133125 | F12: =VLOOKUP($B12,'Global Buyout'!$A$4:$S$19,F$1,0) -> 1.147734 | G12: =VLOOKUP($B12,'Global Buyout'!$A$4:$S$19,G$1,0) -> 0.15640279 | H12: =VLOOKUP($B12,'Global Buyout'!$A$4:$S$19,H$1,0) -> 0.49289149 | J12: =VLOOKUP($B12,'Global Buyout'!$A$4:$S$19,J$1,0) -> -0.0058831056 | K12: =VLOOKUP($B12,'Global Buyout'!$A$4:$S$19,K$1,0) -> 0.19838614 | L12: =VLOOKUP($B12,'Global Buyout'!$A$4:$S$19,L$1,0) -> 0.19250304 | M12: =VLOOKUP($B12,'Global Buyout'!$A$4:$S$19,M$1,0) -> 0.49289149 | O12: =VLOOKUP($B12,'Global Buyout'!$A$4:$S$19,O$1,0) -> 0.13749786 | P12: =VLOOKUP($B12,'Global Buyout'!$A$4:$S$19,P$1,0) -> 0.25003305 | Q12: =VLOOKUP($B12,'Global Buyout'!$A$4:$S$19,Q$1,0) -> 0.28534574 | R12: =VLOOKUP($B12,'Global Buyout'!$A$4:$S$19,R$1,0) -> 0.26996866 | T12: =VLOOKUP($B12,'Global Buyout'!$A$4:$S$19,T$1,0) -> 0.0058337022 | U12: =VLOOKUP($B12,'Global Buyout'!$A$4:$S$19,U$1,0) -> 0.094188445 | V12: =VLOOKUP($B12,'Global Buyout'!$A$4:$S$19,V$1,0) -> 0.094368932 | W12: =VLOOKUP($B12,'Global Buyout'!$A$4:$S$19,W$1,0) -> 0.26996866
A13: Buyout | B13: =B12+1 -> 10 | C13: Year 10 | D13: =D12+1 -> 2034 | E13: =VLOOKUP($B13,'Global Buyout'!$A$4:$S$19,E$1,0) -> -0.99542107 | F13: =VLOOKUP($B13,'Global Buyout'!$A$4:$S$19,F$1,0) -> 1.2947567 | G13: =VLOOKUP($B13,'Global Buyout'!$A$4:$S$19,G$1,0) -> 0.29933565 | H13: =VLOOKUP($B13,'Global Buyout'!$A$4:$S$19,H$1,0) -> 0.40109496 | J13: =VLOOKUP($B13,'Global Buyout'!$A$4:$S$19,J$1,0) -> -0.0040898154 | K13: =VLOOKUP($B13,'Global Buyout'!$A$4:$S$19,K$1,0) -> 0.14702267 | L13: =VLOOKUP($B13,'Global Buyout'!$A$4:$S$19,L$1,0) -> 0.14293286 | M13: =VLOOKUP($B13,'Global Buyout'!$A$4:$S$19,M$1,0) -> 0.40109496 | O13: =VLOOKUP($B13,'Global Buyout'!$A$4:$S$19,O$1,0) -> 0.1375857 | P13: =VLOOKUP($B13,'Global Buyout'!$A$4:$S$19,P$1,0) -> 0.26634634 | Q13: =VLOOKUP($B13,'Global Buyout'!$A$4:$S$19,Q$1,0) -> 0.29978358 | R13: =VLOOKUP($B13,'Global Buyout'!$A$4:$S$19,R$1,0) -> 0.2785575 | T13: =VLOOKUP($B13,'Global Buyout'!$A$4:$S$19,T$1,0) -> 0.0049156313 | U13: =VLOOKUP($B13,'Global Buyout'!$A$4:$S$19,U$1,0) -> 0.091781506 | V13: =VLOOKUP($B13,'Global Buyout'!$A$4:$S$19,V$1,0) -> 0.091913047 | W13: =VLOOKUP($B13,'Global Buyout'!$A$4:$S$19,W$1,0) -> 0.2785575
A14: Buyout | B14: =B13+1 -> 11 | C14: Year 11 | D14: =D13+1 -> 2035 | E14: =VLOOKUP($B14,'Global Buyout'!$A$4:$S$19,E$1,0) -> -0.99813878 | F14: =VLOOKUP($B14,'Global Buyout'!$A$4:$S$19,F$1,0) -> 1.44689 | G14: =VLOOKUP($B14,'Global Buyout'!$A$4:$S$19,G$1,0) -> 0.44875124 | H14: =VLOOKUP($B14,'Global Buyout'!$A$4:$S$19,H$1,0) -> 0.30114431 | J14: =VLOOKUP($B14,'Global Buyout'!$A$4:$S$19,J$1,0) -> -0.0027177133 | K14: =VLOOKUP($B14,'Global Buyout'!$A$4:$S$19,K$1,0) -> 0.15213331 | L14: =VLOOKUP($B14,'Global Buyout'!$A$4:$S$19,L$1,0) -> 0.14941559 | M14: =VLOOKUP($B14,'Global Buyout'!$A$4:$S$19,M$1,0) -> 0.30114431 | O14: =VLOOKUP($B14,'Global Buyout'!$A$4:$S$19,O$1,0) -> 0.13762888 | P14: =VLOOKUP($B14,'Global Buyout'!$A$4:$S$19,P$1,0) -> 0.28483522 | Q14: =VLOOKUP($B14,'Global Buyout'!$A$4:$S$19,Q$1,0) -> 0.31634287 | R14: =VLOOKUP($B14,'Global Buyout'!$A$4:$S$19,R$1,0) -> 0.28667331 | T14: =VLOOKUP($B14,'Global Buyout'!$A$4:$S$19,T$1,0) -> 0.0034473203 | U14: =VLOOKUP($B14,'Global Buyout'!$A$4:$S$19,U$1,0) -> 0.10094914 | V14: =VLOOKUP($B14,'Global Buyout'!$A$4:$S$19,V$1,0) -> 0.10100798 | W14: =VLOOKUP($B14,'Global Buyout'!$A$4:$S$19,W$1,0) -> 0.28667331
A15: Buyout | B15: =B14+1 -> 12 | C15: Year 12 | D15: =D14+1 -> 2036 | E15: =VLOOKUP($B15,'Global Buyout'!$A$4:$S$19,E$1,0) -> -0.99963473 | F15: =VLOOKUP($B15,'Global Buyout'!$A$4:$S$19,F$1,0) -> 1.529232 | G15: =VLOOKUP($B15,'Global Buyout'!$A$4:$S$19,G$1,0) -> 0.52959724 | H15: =VLOOKUP($B15,'Global Buyout'!$A$4:$S$19,H$1,0) -> 0.23129646 | J15: =VLOOKUP($B15,'Global Buyout'!$A$4:$S$19,J$1,0) -> -0.0014959473 | K15: =VLOOKUP($B15,'Global Buyout'!$A$4:$S$19,K$1,0) -> 0.08234195 | L15: =VLOOKUP($B15,'Global Buyout'!$A$4:$S$19,L$1,0) -> 0.080846002 | M15: =VLOOKUP($B15,'Global Buyout'!$A$4:$S$19,M$1,0) -> 0.23129646 | O15: =VLOOKUP($B15,'Global Buyout'!$A$4:$S$19,O$1,0) -> 0.13765502 | P15: =VLOOKUP($B15,'Global Buyout'!$A$4:$S$19,P$1,0) -> 0.28989953 | Q15: =VLOOKUP($B15,'Global Buyout'!$A$4:$S$19,Q$1,0) -> 0.32092155 | R15: =VLOOKUP($B15,'Global Buyout'!$A$4:$S$19,R$1,0) -> 0.28970275 | T15: =VLOOKUP($B15,'Global Buyout'!$A$4:$S$19,T$1,0) -> 0.0026823972 | U15: =VLOOKUP($B15,'Global Buyout'!$A$4:$S$19,U$1,0) -> 0.053950316 | V15: =VLOOKUP($B15,'Global Buyout'!$A$4:$S$19,V$1,0) -> 0.054016959 | W15: =VLOOKUP($B15,'Global Buyout'!$A$4:$S$19,W$1,0) -> 0.28970275
A16: Buyout | B16: =B15+1 -> 13 | C16: Year 13 | D16: =D15+1 -> 2037 | E16: =VLOOKUP($B16,'Global Buyout'!$A$4:$S$19,E$1,0) -> -1.0007196 | F16: =VLOOKUP($B16,'Global Buyout'!$A$4:$S$19,F$1,0) -> 1.5929652 | G16: =VLOOKUP($B16,'Global Buyout'!$A$4:$S$19,G$1,0) -> 0.59224565 | H16: =VLOOKUP($B16,'Global Buyout'!$A$4:$S$19,H$1,0) -> 0.17915683 | J16: =VLOOKUP($B16,'Global Buyout'!$A$4:$S$19,J$1,0) -> -0.0010848328 | K16: =VLOOKUP($B16,'Global Buyout'!$A$4:$S$19,K$1,0) -> 0.063733239 | L16: =VLOOKUP($B16,'Global Buyout'!$A$4:$S$19,L$1,0) -> 0.062648406 | M16: =VLOOKUP($B16,'Global Buyout'!$A$4:$S$19,M$1,0) -> 0.17915683 | O16: =VLOOKUP($B16,'Global Buyout'!$A$4:$S$19,O$1,0) -> 0.13767406 | P16: =VLOOKUP($B16,'Global Buyout'!$A$4:$S$19,P$1,0) -> 0.29485905 | Q16: =VLOOKUP($B16,'Global Buyout'!$A$4:$S$19,Q$1,0) -> 0.32541666 | R16: =VLOOKUP($B16,'Global Buyout'!$A$4:$S$19,R$1,0) -> 0.2919659 | T16: =VLOOKUP($B16,'Global Buyout'!$A$4:$S$19,T$1,0) -> 0.0022895222 | U16: =VLOOKUP($B16,'Global Buyout'!$A$4:$S$19,U$1,0) -> 0.053852746 | V16: =VLOOKUP($B16,'Global Buyout'!$A$4:$S$19,V$1,0) -> 0.053901393 | W16: =VLOOKUP($B16,'Global Buyout'!$A$4:$S$19,W$1,0) -> 0.2919659
A17: Buyout | B17: =B16+1 -> 14 | C17: Year 14 | D17: =D16+1 -> 2038 | E17: =VLOOKUP($B17,'Global Buyout'!$A$4:$S$19,E$1,0) -> -1.0008108 | F17: =VLOOKUP($B17,'Global Buyout'!$A$4:$S$19,F$1,0) -> 1.626022 | G17: =VLOOKUP($B17,'Global Buyout'!$A$4:$S$19,G$1,0) -> 0.62521126 | H17: =VLOOKUP($B17,'Global Buyout'!$A$4:$S$19,H$1,0) -> 0.15463364 | J17: =VLOOKUP($B17,'Global Buyout'!$A$4:$S$19,J$1,0) -> -9.1196912e-05 | K17: =VLOOKUP($B17,'Global Buyout'!$A$4:$S$19,K$1,0) -> 0.033056808 | L17: =VLOOKUP($B17,'Global Buyout'!$A$4:$S$19,L$1,0) -> 0.032965611 | M17: =VLOOKUP($B17,'Global Buyout'!$A$4:$S$19,M$1,0) -> 0.15463364 | O17: =VLOOKUP($B17,'Global Buyout'!$A$4:$S$19,O$1,0) -> 0.1376747 | P17: =VLOOKUP($B17,'Global Buyout'!$A$4:$S$19,P$1,0) -> 0.29738637 | Q17: =VLOOKUP($B17,'Global Buyout'!$A$4:$S$19,Q$1,0) -> 0.32770867 | R17: =VLOOKUP($B17,'Global Buyout'!$A$4:$S$19,R$1,0) -> 0.29242259 | T17: =VLOOKUP($B17,'Global Buyout'!$A$4:$S$19,T$1,0) -> 0.00042129722 | U17: =VLOOKUP($B17,'Global Buyout'!$A$4:$S$19,U$1,0) -> 0.038688433 | V17: =VLOOKUP($B17,'Global Buyout'!$A$4:$S$19,V$1,0) -> 0.038690727 | W17: =VLOOKUP($B17,'Global Buyout'!$A$4:$S$19,W$1,0) -> 0.29242259
A18: Buyout | B18: =B17+1 -> 15 | C18: Year 15 | D18: =D17+1 -> 2039 | E18: =VLOOKUP($B18,'Global Buyout'!$A$4:$S$19,E$1,0) -> -1.0012032 | F18: =VLOOKUP($B18,'Global Buyout'!$A$4:$S$19,F$1,0) -> 1.6563195 | G18: =VLOOKUP($B18,'Global Buyout'!$A$4:$S$19,G$1,0) -> 0.65511637 | H18: =VLOOKUP($B18,'Global Buyout'!$A$4:$S$19,H$1,0) -> 0.14093299 | J18: =VLOOKUP($B18,'Global Buyout'!$A$4:$S$19,J$1,0) -> -0.00039239188 | K18: =VLOOKUP($B18,'Global Buyout'!$A$4:$S$19,K$1,0) -> 0.030297501 | L18: =VLOOKUP($B18,'Global Buyout'!$A$4:$S$19,L$1,0) -> 0.029905109 | M18: =VLOOKUP($B18,'Global Buyout'!$A$4:$S$19,M$1,0) -> 0.14093299 | O18: =VLOOKUP($B18,'Global Buyout'!$A$4:$S$19,O$1,0) -> 0.13767792 | P18: =VLOOKUP($B18,'Global Buyout'!$A$4:$S$19,P$1,0) -> 0.29965017 | Q18: =VLOOKUP($B18,'Global Buyout'!$A$4:$S$19,Q$1,0) -> 0.32976573 | R18: =VLOOKUP($B18,'Global Buyout'!$A$4:$S$19,R$1,0) -> 0.29284389 | T18: =VLOOKUP($B18,'Global Buyout'!$A$4:$S$19,T$1,0) -> 0.00094170607 | U18: =VLOOKUP($B18,'Global Buyout'!$A$4:$S$19,U$1,0) -> 0.036763758 | V18: =VLOOKUP($B18,'Global Buyout'!$A$4:$S$19,V$1,0) -> 0.036775817 | W18: =VLOOKUP($B18,'Global Buyout'!$A$4:$S$19,W$1,0) -> 0.29284389 | Y18: =SUM(H18,F18)/-E18 -> 1.7950927 | Z18: =SUM(M18,K4:K18)/-SUM(J4:J18) -> 1.7950927 | AA18: =Y18=Z18 -> TRUE
A20: Growth Equity | B20: 1 | C20: Year 1 | D20: =D4 -> 2025 | E20: =VLOOKUP($B20,'Global Growth Equity'!$A$4:$S$19,E$1,0) -> -0.2353498 | F20: =VLOOKUP($B20,'Global Growth Equity'!$A$4:$S$19,F$1,0) -> 0 | G20: =VLOOKUP($B20,'Global Growth Equity'!$A$4:$S$19,G$1,0) -> -0.2353498 | H20: =VLOOKUP($B20,'Global Growth Equity'!$A$4:$S$19,H$1,0) -> 0.21842407 | J20: =VLOOKUP($B20,'Global Growth Equity'!$A$4:$S$19,J$1,0) -> -0.2353498 | K20: =VLOOKUP($B20,'Global Growth Equity'!$A$4:$S$19,K$1,0) -> 0 | L20: =VLOOKUP($B20,'Global Growth Equity'!$A$4:$S$19,L$1,0) -> -0.2353498 | M20: =VLOOKUP($B20,'Global Growth Equity'!$A$4:$S$19,M$1,0) -> 0.21842407 | O20: =VLOOKUP($B20,'Global Growth Equity'!$A$4:$S$19,O$1,0) -> 0.089701165 | P20: =VLOOKUP($B20,'Global Growth Equity'!$A$4:$S$19,P$1,0) -> 0 | Q20: =VLOOKUP($B20,'Global Growth Equity'!$A$4:$S$19,Q$1,0) -> 0.089701165 | R20: =VLOOKUP($B20,'Global Growth Equity'!$A$4:$S$19,R$1,0) -> 0.088806226 | T20: =VLOOKUP($B20,'Global Growth Equity'!$A$4:$S$19,T$1,0) -> 0.08549831 | U20: =VLOOKUP($B20,'Global Growth Equity'!$A$4:$S$19,U$1,0) -> 0 | V20: =VLOOKUP($B20,'Global Growth Equity'!$A$4:$S$19,V$1,0) -> 0.08549831 | W20: =VLOOKUP($B20,'Global Growth Equity'!$A$4:$S$19,W$1,0) -> 0.088806226
A21: Growth Equity | B21: =B20+1 -> 2 | C21: Year 2 | D21: =D5 -> 2026 | E21: =VLOOKUP($B21,'Global Growth Equity'!$A$4:$S$19,E$1,0) -> -0.47043254 | F21: =VLOOKUP($B21,'Global Growth Equity'!$A$4:$S$19,F$1,0) -> 0.00024311022 | G21: =VLOOKUP($B21,'Global Growth Equity'!$A$4:$S$19,G$1,0) -> -0.47018943 | H21: =VLOOKUP($B21,'Global Growth Equity'!$A$4:$S$19,H$1,0) -> 0.45579695 | J21: =VLOOKUP($B21,'Global Growth Equity'!$A$4:$S$19,J$1,0) -> -0.23508274 | K21: =VLOOKUP($B21,'Global Growth Equity'!$A$4:$S$19,K$1,0) -> 0.00024311022 | L21: =VLOOKUP($B21,'Global Growth Equity'!$A$4:$S$19,L$1,0) -> -0.23483963 | M21: =VLOOKUP($B21,'Global Growth Equity'!$A$4:$S$19,M$1,0) -> 0.45579695 | O21: =VLOOKUP($B21,'Global Growth Equity'!$A$4:$S$19,O$1,0) -> 0.11079509 | P21: =VLOOKUP($B21,'Global Growth Equity'!$A$4:$S$19,P$1,0) -> 0.001190992 | Q21: =VLOOKUP($B21,'Global Growth Equity'!$A$4:$S$19,Q$1,0) -> 0.1108015 | R21: =VLOOKUP($B21,'Global Growth Equity'!$A$4:$S$19,R$1,0) -> 0.11935407 | T21: =VLOOKUP($B21,'Global Growth Equity'!$A$4:$S$19,T$1,0) -> 0.065032715 | U21: =VLOOKUP($B21,'Global Growth Equity'!$A$4:$S$19,U$1,0) -> 0.001190992 | V21: =VLOOKUP($B21,'Global Growth Equity'!$A$4:$S$19,V$1,0) -> 0.06504362 | W21: =VLOOKUP($B21,'Global Growth Equity'!$A$4:$S$19,W$1,0) -> 0.11935407
A22: Growth Equity | B22: =B21+1 -> 3 | C22: Year 3 | D22: =D6 -> 2027 | E22: =VLOOKUP($B22,'Global Growth Equity'!$A$4:$S$19,E$1,0) -> -0.69057851 | F22: =VLOOKUP($B22,'Global Growth Equity'!$A$4:$S$19,F$1,0) -> 0.011903643 | G22: =VLOOKUP($B22,'Global Growth Equity'!$A$4:$S$19,G$1,0) -> -0.67867486 | H22: =VLOOKUP($B22,'Global Growth Equity'!$A$4:$S$19,H$1,0) -> 0.69115782 | J22: =VLOOKUP($B22,'Global Growth Equity'!$A$4:$S$19,J$1,0) -> -0.22014597 | K22: =VLOOKUP($B22,'Global Growth Equity'!$A$4:$S$19,K$1,0) -> 0.011660532 | L22: =VLOOKUP($B22,'Global Growth Equity'!$A$4:$S$19,L$1,0) -> -0.20848544 | M22: =VLOOKUP($B22,'Global Growth Equity'!$A$4:$S$19,M$1,0) -> 0.69115782 | O22: =VLOOKUP($B22,'Global Growth Equity'!$A$4:$S$19,O$1,0) -> 0.13942613 | P22: =VLOOKUP($B22,'Global Growth Equity'!$A$4:$S$19,P$1,0) -> 0.015479718 | Q22: =VLOOKUP($B22,'Global Growth Equity'!$A$4:$S$19,Q$1,0) -> 0.14028281 | R22: =VLOOKUP($B22,'Global Growth Equity'!$A$4:$S$19,R$1,0) -> 0.17394611 | T22: =VLOOKUP($B22,'Global Growth Equity'!$A$4:$S$19,T$1,0) -> 0.084640967 | U22: =VLOOKUP($B22,'Global Growth Equity'!$A$4:$S$19,U$1,0) -> 0.015433833 | V22: =VLOOKUP($B22,'Global Growth Equity'!$A$4:$S$19,V$1,0) -> 0.0860366 | W22: =VLOOKUP($B22,'Global Growth Equity'!$A$4:$S$19,W$1,0) -> 0.17394611
A23: Growth Equity | B23: =B22+1 -> 4 | C23: Year 4 | D23: =D7 -> 2028 | E23: =VLOOKUP($B23,'Global Growth Equity'!$A$4:$S$19,E$1,0) -> -0.85917011 | F23: =VLOOKUP($B23,'Global Growth Equity'!$A$4:$S$19,F$1,0) -> 0.063652187 | G23: =VLOOKUP($B23,'Global Growth Equity'!$A$4:$S$19,G$1,0) -> -0.79551793 | H23: =VLOOKUP($B23,'Global Growth Equity'!$A$4:$S$19,H$1,0) -> 0.8910481 | J23: =VLOOKUP($B23,'Global Growth Equity'!$A$4:$S$19,J$1,0) -> -0.16859161 | K23: =VLOOKUP($B23,'Global Growth Equity'!$A$4:$S$19,K$1,0) -> 0.051748545 | L23: =VLOOKUP($B23,'Global Growth Equity'!$A$4:$S$19,L$1,0) -> -0.11684306 | M23: =VLOOKUP($B23,'Global Growth Equity'!$A$4:$S$19,M$1,0) -> 0.8910481 | O23: =VLOOKUP($B23,'Global Growth Equity'!$A$4:$S$19,O$1,0) -> 0.15183577 | P23: =VLOOKUP($B23,'Global Growth Equity'!$A$4:$S$19,P$1,0) -> 0.039524195 | Q23: =VLOOKUP($B23,'Global Growth Equity'!$A$4:$S$19,Q$1,0) -> 0.15689571 | R23: =VLOOKUP($B23,'Global Growth Equity'!$A$4:$S$19,R$1,0) -> 0.21929015 | T23: =VLOOKUP($B23,'Global Growth Equity'!$A$4:$S$19,T$1,0) -> 0.060120332 | U23: =VLOOKUP($B23,'Global Growth Equity'!$A$4:$S$19,U$1,0) -> 0.036366748 | V23: =VLOOKUP($B23,'Global Growth Equity'!$A$4:$S$19,V$1,0) -> 0.070263751 | W23: =VLOOKUP($B23,'Global Growth Equity'!$A$4:$S$19,W$1,0) -> 0.21929015
A24: Growth Equity | B24: =B23+1 -> 5 | C24: Year 5 | D24: =D8 -> 2029 | E24: =VLOOKUP($B24,'Global Growth Equity'!$A$4:$S$19,E$1,0) -> -0.9546117 | F24: =VLOOKUP($B24,'Global Growth Equity'!$A$4:$S$19,F$1,0) -> 0.15858256 | G24: =VLOOKUP($B24,'Global Growth Equity'!$A$4:$S$19,G$1,0) -> -0.79602914 | H24: =VLOOKUP($B24,'Global Growth Equity'!$A$4:$S$19,H$1,0) -> 0.96836953 | J24: =VLOOKUP($B24,'Global Growth Equity'!$A$4:$S$19,J$1,0) -> -0.095441582 | K24: =VLOOKUP($B24,'Global Growth Equity'!$A$4:$S$19,K$1,0) -> 0.094930372 | L24: =VLOOKUP($B24,'Global Growth Equity'!$A$4:$S$19,L$1,0) -> -0.00051121048 | M24: =VLOOKUP($B24,'Global Growth Equity'!$A$4:$S$19,M$1,0) -> 0.96836953 | O24: =VLOOKUP($B24,'Global Growth Equity'!$A$4:$S$19,O$1,0) -> 0.15897928 | P24: =VLOOKUP($B24,'Global Growth Equity'!$A$4:$S$19,P$1,0) -> 0.069805568 | Q24: =VLOOKUP($B24,'Global Growth Equity'!$A$4:$S$19,Q$1,0) -> 0.17362958 | R24: =VLOOKUP($B24,'Global Growth Equity'!$A$4:$S$19,R$1,0) -> 0.25121057 | T24: =VLOOKUP($B24,'Global Growth Equity'!$A$4:$S$19,T$1,0) -> 0.047120184 | U24: =VLOOKUP($B24,'Global Growth Equity'!$A$4:$S$19,U$1,0) -> 0.057538294 | V24: =VLOOKUP($B24,'Global Growth Equity'!$A$4:$S$19,V$1,0) -> 0.074370471 | W24: =VLOOKUP($B24,'Global Growth Equity'!$A$4:$S$19,W$1,0) -> 0.25121057
A25: Growth Equity | B25: =B24+1 -> 6 | C25: Year 6 | D25: =D9 -> 2030 | E25: =VLOOKUP($B25,'Global Growth Equity'!$A$4:$S$19,E$1,0) -> -1.013275 | F25: =VLOOKUP($B25,'Global Growth Equity'!$A$4:$S$19,F$1,0) -> 0.32159416 | G25: =VLOOKUP($B25,'Global Growth Equity'!$A$4:$S$19,G$1,0) -> -0.6916808 | H25: =VLOOKUP($B25,'Global Growth Equity'!$A$4:$S$19,H$1,0) -> 0.98365813 | J25: =VLOOKUP($B25,'Global Growth Equity'!$A$4:$S$19,J$1,0) -> -0.058663269 | K25: =VLOOKUP($B25,'Global Growth Equity'!$A$4:$S$19,K$1,0) -> 0.16301161 | L25: =VLOOKUP($B25,'Global Growth Equity'!$A$4:$S$19,L$1,0) -> 0.10434834 | M25: =VLOOKUP($B25,'Global Growth Equity'!$A$4:$S$19,M$1,0) -> 0.98365813 | O25: =VLOOKUP($B25,'Global Growth Equity'!$A$4:$S$19,O$1,0) -> 0.16248142 | P25: =VLOOKUP($B25,'Global Growth Equity'!$A$4:$S$19,P$1,0) -> 0.11106188 | Q25: =VLOOKUP($B25,'Global Growth Equity'!$A$4:$S$19,Q$1,0) -> 0.19681197 | R25: =VLOOKUP($B25,'Global Growth Equity'!$A$4:$S$19,R$1,0) -> 0.27144531 | T25: =VLOOKUP($B25,'Global Growth Equity'!$A$4:$S$19,T$1,0) -> 0.033552923 | U25: =VLOOKUP($B25,'Global Growth Equity'!$A$4:$S$19,U$1,0) -> 0.086382425 | V25: =VLOOKUP($B25,'Global Growth Equity'!$A$4:$S$19,V$1,0) -> 0.092669962 | W25: =VLOOKUP($B25,'Global Growth Equity'!$A$4:$S$19,W$1,0) -> 0.27144531
A26: Growth Equity | B26: =B25+1 -> 7 | C26: Year 7 | D26: =D10 -> 2031 | E26: =VLOOKUP($B26,'Global Growth Equity'!$A$4:$S$19,E$1,0) -> -1.0370047 | F26: =VLOOKUP($B26,'Global Growth Equity'!$A$4:$S$19,F$1,0) -> 0.46401681 | G26: =VLOOKUP($B26,'Global Growth Equity'!$A$4:$S$19,G$1,0) -> -0.57298789 | H26: =VLOOKUP($B26,'Global Growth Equity'!$A$4:$S$19,H$1,0) -> 0.9800405 | J26: =VLOOKUP($B26,'Global Growth Equity'!$A$4:$S$19,J$1,0) -> -0.023729732 | K26: =VLOOKUP($B26,'Global Growth Equity'!$A$4:$S$19,K$1,0) -> 0.14242264 | L26: =VLOOKUP($B26,'Global Growth Equity'!$A$4:$S$19,L$1,0) -> 0.11869291 | M26: =VLOOKUP($B26,'Global Growth Equity'!$A$4:$S$19,M$1,0) -> 0.9800405 | O26: =VLOOKUP($B26,'Global Growth Equity'!$A$4:$S$19,O$1,0) -> 0.16327326 | P26: =VLOOKUP($B26,'Global Growth Equity'!$A$4:$S$19,P$1,0) -> 0.14666163 | Q26: =VLOOKUP($B26,'Global Growth Equity'!$A$4:$S$19,Q$1,0) -> 0.21947162 | R26: =VLOOKUP($B26,'Global Growth Equity'!$A$4:$S$19,R$1,0) -> 0.29182664 | T26: =VLOOKUP($B26,'Global Growth Equity'!$A$4:$S$19,T$1,0) -> 0.016060683 | U26: =VLOOKUP($B26,'Global Growth Equity'!$A$4:$S$19,U$1,0) -> 0.095785662 | V26: =VLOOKUP($B26,'Global Growth Equity'!$A$4:$S$19,V$1,0) -> 0.097122801 | W26: =VLOOKUP($B26,'Global Growth Equity'!$A$4:$S$19,W$1,0) -> 0.29182664
A27: Growth Equity | B27: =B26+1 -> 8 | C27: Year 8 | D27: =D11 -> 2032 | E27: =VLOOKUP($B27,'Global Growth Equity'!$A$4:$S$19,E$1,0) -> -1.0514974 | F27: =VLOOKUP($B27,'Global Growth Equity'!$A$4:$S$19,F$1,0) -> 0.64288259 | G27: =VLOOKUP($B27,'Global Growth Equity'!$A$4:$S$19,G$1,0) -> -0.40861484 | H27: =VLOOKUP($B27,'Global Growth Equity'!$A$4:$S$19,H$1,0) -> 0.8619287 | J27: =VLOOKUP($B27,'Global Growth Equity'!$A$4:$S$19,J$1,0) -> -0.014492728 | K27: =VLOOKUP($B27,'Global Growth Equity'!$A$4:$S$19,K$1,0) -> 0.17886578 | L27: =VLOOKUP($B27,'Global Growth Equity'!$A$4:$S$19,L$1,0) -> 0.16437305 | M27: =VLOOKUP($B27,'Global Growth Equity'!$A$4:$S$19,M$1,0) -> 0.8619287 | O27: =VLOOKUP($B27,'Global Growth Equity'!$A$4:$S$19,O$1,0) -> 0.1636578 | P27: =VLOOKUP($B27,'Global Growth Equity'!$A$4:$S$19,P$1,0) -> 0.18196616 | Q27: =VLOOKUP($B27,'Global Growth Equity'!$A$4:$S$19,Q$1,0) -> 0.24473569 | R27: =VLOOKUP($B27,'Global Growth Equity'!$A$4:$S$19,R$1,0) -> 0.31195581 | T27: =VLOOKUP($B27,'Global Growth Equity'!$A$4:$S$19,T$1,0) -> 0.011212426 | U27: =VLOOKUP($B27,'Global Growth Equity'!$A$4:$S$19,U$1,0) -> 0.1077128 | V27: =VLOOKUP($B27,'Global Growth Equity'!$A$4:$S$19,V$1,0) -> 0.10829481 | W27: =VLOOKUP($B27,'Global Growth Equity'!$A$4:$S$19,W$1,0) -> 0.31195581
A28: Growth Equity | B28: =B27+1 -> 9 | C28: Year 9 | D28: =D12 -> 2033 | E28: =VLOOKUP($B28,'Global Growth Equity'!$A$4:$S$19,E$1,0) -> -1.0588448 | F28: =VLOOKUP($B28,'Global Growth Equity'!$A$4:$S$19,F$1,0) -> 0.82068178 | G28: =VLOOKUP($B28,'Global Growth Equity'!$A$4:$S$19,G$1,0) -> -0.23816306 | H28: =VLOOKUP($B28,'Global Growth Equity'!$A$4:$S$19,H$1,0) -> 0.74636821 | J28: =VLOOKUP($B28,'Global Growth Equity'!$A$4:$S$19,J$1,0) -> -0.0073474172 | K28: =VLOOKUP($B28,'Global Growth Equity'!$A$4:$S$19,K$1,0) -> 0.17779919 | L28: =VLOOKUP($B28,'Global Growth Equity'!$A$4:$S$19,L$1,0) -> 0.17045178 | M28: =VLOOKUP($B28,'Global Growth Equity'!$A$4:$S$19,M$1,0) -> 0.74636821 | O28: =VLOOKUP($B28,'Global Growth Equity'!$A$4:$S$19,O$1,0) -> 0.16382728 | P28: =VLOOKUP($B28,'Global Growth Equity'!$A$4:$S$19,P$1,0) -> 0.2184713 | Q28: =VLOOKUP($B28,'Global Growth Equity'!$A$4:$S$19,Q$1,0) -> 0.27307341 | R28: =VLOOKUP($B28,'Global Growth Equity'!$A$4:$S$19,R$1,0) -> 0.33221333 | T28: =VLOOKUP($B28,'Global Growth Equity'!$A$4:$S$19,T$1,0) -> 0.0074500777 | U28: =VLOOKUP($B28,'Global Growth Equity'!$A$4:$S$19,U$1,0) -> 0.12090504 | V28: =VLOOKUP($B28,'Global Growth Equity'!$A$4:$S$19,V$1,0) -> 0.12113436 | W28: =VLOOKUP($B28,'Global Growth Equity'!$A$4:$S$19,W$1,0) -> 0.33221333
A29: Growth Equity | B29: =B28+1 -> 10 | C29: Year 10 | D29: =D13 -> 2034 | E29: =VLOOKUP($B29,'Global Growth Equity'!$A$4:$S$19,E$1,0) -> -1.0619245 | F29: =VLOOKUP($B29,'Global Growth Equity'!$A$4:$S$19,F$1,0) -> 0.99435426 | G29: =VLOOKUP($B29,'Global Growth Equity'!$A$4:$S$19,G$1,0) -> -0.067570205 | H29: =VLOOKUP($B29,'Global Growth Equity'!$A$4:$S$19,H$1,0) -> 0.66473165 | J29: =VLOOKUP($B29,'Global Growth Equity'!$A$4:$S$19,J$1,0) -> -0.0030796238 | K29: =VLOOKUP($B29,'Global Growth Equity'!$A$4:$S$19,K$1,0) -> 0.17367248 | L29: =VLOOKUP($B29,'Global Growth Equity'!$A$4:$S$19,L$1,0) -> 0.17059286 | M29: =VLOOKUP($B29,'Global Growth Equity'!$A$4:$S$19,M$1,0) -> 0.66473165 | O29: =VLOOKUP($B29,'Global Growth Equity'!$A$4:$S$19,O$1,0) -> 0.16397989 | P29: =VLOOKUP($B29,'Global Growth Equity'!$A$4:$S$19,P$1,0) -> 0.26494438 | Q29: =VLOOKUP($B29,'Global Growth Equity'!$A$4:$S$19,Q$1,0) -> 0.31158455 | R29: =VLOOKUP($B29,'Global Growth Equity'!$A$4:$S$19,R$1,0) -> 0.34577372 | T29: =VLOOKUP($B29,'Global Growth Equity'!$A$4:$S$19,T$1,0) -> 0.0070728849 | U29: =VLOOKUP($B29,'Global Growth Equity'!$A$4:$S$19,U$1,0) -> 0.14988601 | V29: =VLOOKUP($B29,'Global Growth Equity'!$A$4:$S$19,V$1,0) -> 0.15005279 | W29: =VLOOKUP($B29,'Global Growth Equity'!$A$4:$S$19,W$1,0) -> 0.34577372
A30: Growth Equity | B30: =B29+1 -> 11 | C30: Year 11 | D30: =D14 -> 2035 | E30: =VLOOKUP($B30,'Global Growth Equity'!$A$4:$S$19,E$1,0) -> -1.064584 | F30: =VLOOKUP($B30,'Global Growth Equity'!$A$4:$S$19,F$1,0) -> 1.1115858 | G30: =VLOOKUP($B30,'Global Growth Equity'!$A$4:$S$19,G$1,0) -> 0.047001818 | H30: =VLOOKUP($B30,'Global Growth Equity'!$A$4:$S$19,H$1,0) -> 0.56428378 | J30: =VLOOKUP($B30,'Global Growth Equity'!$A$4:$S$19,J$1,0) -> -0.0026595232 | K30: =VLOOKUP($B30,'Global Growth Equity'!$A$4:$S$19,K$1,0) -> 0.11723155 | L30: =VLOOKUP($B30,'Global Growth Equity'!$A$4:$S$19,L$1,0) -> 0.11457202 | M30: =VLOOKUP($B30,'Global Growth Equity'!$A$4:$S$19,M$1,0) -> 0.56428378 | O30: =VLOOKUP($B30,'Global Growth Equity'!$A$4:$S$19,O$1,0) -> 0.16405372 | P30: =VLOOKUP($B30,'Global Growth Equity'!$A$4:$S$19,P$1,0) -> 0.27569809 | Q30: =VLOOKUP($B30,'Global Growth Equity'!$A$4:$S$19,Q$1,0) -> 0.32081624 | R30: =VLOOKUP($B30,'Global Growth Equity'!$A$4:$S$19,R$1,0) -> 0.35729926 | T30: =VLOOKUP($B30,'Global Growth Equity'!$A$4:$S$19,T$1,0) -> 0.0049213092 | U30: =VLOOKUP($B30,'Global Growth Equity'!$A$4:$S$19,U$1,0) -> 0.076249011 | V30: =VLOOKUP($B30,'Global Growth Equity'!$A$4:$S$19,V$1,0) -> 0.076407663 | W30: =VLOOKUP($B30,'Global Growth Equity'!$A$4:$S$19,W$1,0) -> 0.35729926
A31: Growth Equity | B31: =B30+1 -> 12 | C31: Year 12 | D31: =D15 -> 2036 | E31: =VLOOKUP($B31,'Global Growth Equity'!$A$4:$S$19,E$1,0) -> -1.065492 | F31: =VLOOKUP($B31,'Global Growth Equity'!$A$4:$S$19,F$1,0) -> 1.2014332 | G31: =VLOOKUP($B31,'Global Growth Equity'!$A$4:$S$19,G$1,0) -> 0.13594118 | H31: =VLOOKUP($B31,'Global Growth Equity'!$A$4:$S$19,H$1,0) -> 0.47895942 | J31: =VLOOKUP($B31,'Global Growth Equity'!$A$4:$S$19,J$1,0) -> -0.00090800563 | K31: =VLOOKUP($B31,'Global Growth Equity'!$A$4:$S$19,K$1,0) -> 0.089847365 | L31: =VLOOKUP($B31,'Global Growth Equity'!$A$4:$S$19,L$1,0) -> 0.088939359 | M31: =VLOOKUP($B31,'Global Growth Equity'!$A$4:$S$19,M$1,0) -> 0.47895942 | O31: =VLOOKUP($B31,'Global Growth Equity'!$A$4:$S$19,O$1,0) -> 0.16405983 | P31: =VLOOKUP($B31,'Global Growth Equity'!$A$4:$S$19,P$1,0) -> 0.28544026 | Q31: =VLOOKUP($B31,'Global Growth Equity'!$A$4:$S$19,Q$1,0) -> 0.32922906 | R31: =VLOOKUP($B31,'Global Growth Equity'!$A$4:$S$19,R$1,0) -> 0.36351569 | T31: =VLOOKUP($B31,'Global Growth Equity'!$A$4:$S$19,T$1,0) -> 0.0014161168 | U31: =VLOOKUP($B31,'Global Growth Equity'!$A$4:$S$19,U$1,0) -> 0.073937173 | V31: =VLOOKUP($B31,'Global Growth Equity'!$A$4:$S$19,V$1,0) -> 0.073950733 | W31: =VLOOKUP($B31,'Global Growth Equity'!$A$4:$S$19,W$1,0) -> 0.36351569
A32: Growth Equity | B32: =B31+1 -> 13 | C32: Year 13 | D32: =D16 -> 2037 | E32: =VLOOKUP($B32,'Global Growth Equity'!$A$4:$S$19,E$1,0) -> -1.0655776 | F32: =VLOOKUP($B32,'Global Growth Equity'!$A$4:$S$19,F$1,0) -> 1.2384718 | G32: =VLOOKUP($B32,'Global Growth Equity'!$A$4:$S$19,G$1,0) -> 0.17289425 | H32: =VLOOKUP($B32,'Global Growth Equity'!$A$4:$S$19,H$1,0) -> 0.42438693 | J32: =VLOOKUP($B32,'Global Growth Equity'!$A$4:$S$19,J$1,0) -> -8.5603486e-05 | K32: =VLOOKUP($B32,'Global Growth Equity'!$A$4:$S$19,K$1,0) -> 0.037038676 | L32: =VLOOKUP($B32,'Global Growth Equity'!$A$4:$S$19,L$1,0) -> 0.036953072 | M32: =VLOOKUP($B32,'Global Growth Equity'!$A$4:$S$19,M$1,0) -> 0.42438693 | O32: =VLOOKUP($B32,'Global Growth Equity'!$A$4:$S$19,O$1,0) -> 0.16410068 | P32: =VLOOKUP($B32,'Global Growth Equity'!$A$4:$S$19,P$1,0) -> 0.28821438 | Q32: =VLOOKUP($B32,'Global Growth Equity'!$A$4:$S$19,Q$1,0) -> 0.3316573 | R32: =VLOOKUP($B32,'Global Growth Equity'!$A$4:$S$19,R$1,0) -> 0.36628397 | T32: =VLOOKUP($B32,'Global Growth Equity'!$A$4:$S$19,T$1,0) -> 0.0036611032 | U32: =VLOOKUP($B32,'Global Growth Equity'!$A$4:$S$19,U$1,0) -> 0.039892197 | V32: =VLOOKUP($B32,'Global Growth Equity'!$A$4:$S$19,V$1,0) -> 0.040059843 | W32: =VLOOKUP($B32,'Global Growth Equity'!$A$4:$S$19,W$1,0) -> 0.36628397
A33: Growth Equity | B33: =B32+1 -> 14 | C33: Year 14 | D33: =D17 -> 2038 | E33: =VLOOKUP($B33,'Global Growth Equity'!$A$4:$S$19,E$1,0) -> -1.0663804 | F33: =VLOOKUP($B33,'Global Growth Equity'!$A$4:$S$19,F$1,0) -> 1.2744756 | G33: =VLOOKUP($B33,'Global Growth Equity'!$A$4:$S$19,G$1,0) -> 0.2080952 | H33: =VLOOKUP($B33,'Global Growth Equity'!$A$4:$S$19,H$1,0) -> 0.37783699 | J33: =VLOOKUP($B33,'Global Growth Equity'!$A$4:$S$19,J$1,0) -> -0.00080278324 | K33: =VLOOKUP($B33,'Global Growth Equity'!$A$4:$S$19,K$1,0) -> 0.036003731 | L33: =VLOOKUP($B33,'Global Growth Equity'!$A$4:$S$19,L$1,0) -> 0.035200947 | M33: =VLOOKUP($B33,'Global Growth Equity'!$A$4:$S$19,M$1,0) -> 0.37783699 | O33: =VLOOKUP($B33,'Global Growth Equity'!$A$4:$S$19,O$1,0) -> 0.16412089 | P33: =VLOOKUP($B33,'Global Growth Equity'!$A$4:$S$19,P$1,0) -> 0.2903799 | Q33: =VLOOKUP($B33,'Global Growth Equity'!$A$4:$S$19,Q$1,0) -> 0.33355082 | R33: =VLOOKUP($B33,'Global Growth Equity'!$A$4:$S$19,R$1,0) -> 0.36824532 | T33: =VLOOKUP($B33,'Global Growth Equity'!$A$4:$S$19,T$1,0) -> 0.0025754247 | U33: =VLOOKUP($B33,'Global Growth Equity'!$A$4:$S$19,U$1,0) -> 0.035397104 | V33: =VLOOKUP($B33,'Global Growth Equity'!$A$4:$S$19,V$1,0) -> 0.035490672 | W33: =VLOOKUP($B33,'Global Growth Equity'!$A$4:$S$19,W$1,0) -> 0.36824532
A34: Growth Equity | B34: =B33+1 -> 15 | C34: Year 15 | D34: =D18 -> 2039 | E34: =VLOOKUP($B34,'Global Growth Equity'!$A$4:$S$19,E$1,0) -> -1.0663804 | F34: =VLOOKUP($B34,'Global Growth Equity'!$A$4:$S$19,F$1,0) -> 1.2961159 | G34: =VLOOKUP($B34,'Global Growth Equity'!$A$4:$S$19,G$1,0) -> 0.22973551 | H34: =VLOOKUP($B34,'Global Growth Equity'!$A$4:$S$19,H$1,0) -> 0.35867891 | J34: =VLOOKUP($B34,'Global Growth Equity'!$A$4:$S$19,J$1,0) -> 0 | K34: =VLOOKUP($B34,'Global Growth Equity'!$A$4:$S$19,K$1,0) -> 0.021640318 | L34: =VLOOKUP($B34,'Global Growth Equity'!$A$4:$S$19,L$1,0) -> 0.021640318 | M34: =VLOOKUP($B34,'Global Growth Equity'!$A$4:$S$19,M$1,0) -> 0.35867891 | O34: =VLOOKUP($B34,'Global Growth Equity'!$A$4:$S$19,O$1,0) -> 0.16412089 | P34: =VLOOKUP($B34,'Global Growth Equity'!$A$4:$S$19,P$1,0) -> 0.29186645 | Q34: =VLOOKUP($B34,'Global Growth Equity'!$A$4:$S$19,Q$1,0) -> 0.33484577 | R34: =VLOOKUP($B34,'Global Growth Equity'!$A$4:$S$19,R$1,0) -> 0.36922975 | T34: =VLOOKUP($B34,'Global Growth Equity'!$A$4:$S$19,T$1,0) -> 0 | U34: =VLOOKUP($B34,'Global Growth Equity'!$A$4:$S$19,U$1,0) -> 0.029420073 | V34: =VLOOKUP($B34,'Global Growth Equity'!$A$4:$S$19,V$1,0) -> 0.029420073 | W34: =VLOOKUP($B34,'Global Growth Equity'!$A$4:$S$19,W$1,0) -> 0.36922975 | Y34: =SUM(H34,F34)/-E34 -> 1.5517866 | Z34: =SUM(M34,K20:K34)/-SUM(J20:J34) -> 1.5517866 | AA34: =Y34=Z34 -> TRUE
A36: Venture Capital | B36: 1 | C36: Year 1 | D36: =D4 -> 2025 | E36: =VLOOKUP($B36,'Global Venture Capital'!$A$4:$S$19,E$1,0) -> -0.23728646 | F36: =VLOOKUP($B36,'Global Venture Capital'!$A$4:$S$19,F$1,0) -> 0.00010667405 | G36: =VLOOKUP($B36,'Global Venture Capital'!$A$4:$S$19,G$1,0) -> -0.23717978 | H36: =VLOOKUP($B36,'Global Venture Capital'!$A$4:$S$19,H$1,0) -> 0.22347148 | J36: =VLOOKUP($B36,'Global Venture Capital'!$A$4:$S$19,J$1,0) -> -0.23728646 | K36: =VLOOKUP($B36,'Global Venture Capital'!$A$4:$S$19,K$1,0) -> 0.00010667405 | L36: =VLOOKUP($B36,'Global Venture Capital'!$A$4:$S$19,L$1,0) -> -0.23717978 | M36: =VLOOKUP($B36,'Global Venture Capital'!$A$4:$S$19,M$1,0) -> 0.22347148 | O36: =VLOOKUP($B36,'Global Venture Capital'!$A$4:$S$19,O$1,0) -> 0.12384244 | P36: =VLOOKUP($B36,'Global Venture Capital'!$A$4:$S$19,P$1,0) -> 0.00062014678 | Q36: =VLOOKUP($B36,'Global Venture Capital'!$A$4:$S$19,Q$1,0) -> 0.12384399 | R36: =VLOOKUP($B36,'Global Venture Capital'!$A$4:$S$19,R$1,0) -> 0.12459636 | T36: =VLOOKUP($B36,'Global Venture Capital'!$A$4:$S$19,T$1,0) -> 0.11790839 | U36: =VLOOKUP($B36,'Global Venture Capital'!$A$4:$S$19,U$1,0) -> 0.00062014678 | V36: =VLOOKUP($B36,'Global Venture Capital'!$A$4:$S$19,V$1,0) -> 0.11791002 | W36: =VLOOKUP($B36,'Global Venture Capital'!$A$4:$S$19,W$1,0) -> 0.12459636
A37: Venture Capital | B37: =B36+1 -> 2 | C37: Year 2 | D37: =D5 -> 2026 | E37: =VLOOKUP($B37,'Global Venture Capital'!$A$4:$S$19,E$1,0) -> -0.47002016 | F37: =VLOOKUP($B37,'Global Venture Capital'!$A$4:$S$19,F$1,0) -> 0.00033896352 | G37: =VLOOKUP($B37,'Global Venture Capital'!$A$4:$S$19,G$1,0) -> -0.46968119 | H37: =VLOOKUP($B37,'Global Venture Capital'!$A$4:$S$19,H$1,0) -> 0.47424319 | J37: =VLOOKUP($B37,'Global Venture Capital'!$A$4:$S$19,J$1,0) -> -0.2327337 | K37: =VLOOKUP($B37,'Global Venture Capital'!$A$4:$S$19,K$1,0) -> 0.00023228947 | L37: =VLOOKUP($B37,'Global Venture Capital'!$A$4:$S$19,L$1,0) -> -0.23250141 | M37: =VLOOKUP($B37,'Global Venture Capital'!$A$4:$S$19,M$1,0) -> 0.47424319 | O37: =VLOOKUP($B37,'Global Venture Capital'!$A$4:$S$19,O$1,0) -> 0.14136631 | P37: =VLOOKUP($B37,'Global Venture Capital'!$A$4:$S$19,P$1,0) -> 0.0011973183 | Q37: =VLOOKUP($B37,'Global Venture Capital'!$A$4:$S$19,Q$1,0) -> 0.14137138 | R37: =VLOOKUP($B37,'Global Venture Capital'!$A$4:$S$19,R$1,0) -> 0.16131202 | T37: =VLOOKUP($B37,'Global Venture Capital'!$A$4:$S$19,T$1,0) -> 0.068172464 | U37: =VLOOKUP($B37,'Global Venture Capital'!$A$4:$S$19,U$1,0) -> 0.0010242017 | V37: =VLOOKUP($B37,'Global Venture Capital'!$A$4:$S$19,V$1,0) -> 0.068180157 | W37: =VLOOKUP($B37,'Global Venture Capital'!$A$4:$S$19,W$1,0) -> 0.16131202
A38: Venture Capital | B38: =B37+1 -> 3 | C38: Year 3 | D38: =D6 -> 2027 | E38: =VLOOKUP($B38,'Global Venture Capital'!$A$4:$S$19,E$1,0) -> -0.69319478 | F38: =VLOOKUP($B38,'Global Venture Capital'!$A$4:$S$19,F$1,0) -> 0.023963861 | G38: =VLOOKUP($B38,'Global Venture Capital'!$A$4:$S$19,G$1,0) -> -0.66923092 | H38: =VLOOKUP($B38,'Global Venture Capital'!$A$4:$S$19,H$1,0) -> 0.72963727 | J38: =VLOOKUP($B38,'Global Venture Capital'!$A$4:$S$19,J$1,0) -> -0.22317462 | K38: =VLOOKUP($B38,'Global Venture Capital'!$A$4:$S$19,K$1,0) -> 0.023624898 | L38: =VLOOKUP($B38,'Global Venture Capital'!$A$4:$S$19,L$1,0) -> -0.19954973 | M38: =VLOOKUP($B38,'Global Venture Capital'!$A$4:$S$19,M$1,0) -> 0.72963727 | O38: =VLOOKUP($B38,'Global Venture Capital'!$A$4:$S$19,O$1,0) -> 0.1622147 | P38: =VLOOKUP($B38,'Global Venture Capital'!$A$4:$S$19,P$1,0) -> 0.049267617 | Q38: =VLOOKUP($B38,'Global Venture Capital'!$A$4:$S$19,Q$1,0) -> 0.16953144 | R38: =VLOOKUP($B38,'Global Venture Capital'!$A$4:$S$19,R$1,0) -> 0.2069551 | T38: =VLOOKUP($B38,'Global Venture Capital'!$A$4:$S$19,T$1,0) -> 0.079556117 | U38: =VLOOKUP($B38,'Global Venture Capital'!$A$4:$S$19,U$1,0) -> 0.049253066 | V38: =VLOOKUP($B38,'Global Venture Capital'!$A$4:$S$19,V$1,0) -> 0.093568372 | W38: =VLOOKUP($B38,'Global Venture Capital'!$A$4:$S$19,W$1,0) -> 0.2069551
A39: Venture Capital | B39: =B38+1 -> 4 | C39: Year 4 | D39: =D7 -> 2028 | E39: =VLOOKUP($B39,'Global Venture Capital'!$A$4:$S$19,E$1,0) -> -0.84333541 | F39: =VLOOKUP($B39,'Global Venture Capital'!$A$4:$S$19,F$1,0) -> 0.094652637 | G39: =VLOOKUP($B39,'Global Venture Capital'!$A$4:$S$19,G$1,0) -> -0.74868278 | H39: =VLOOKUP($B39,'Global Venture Capital'!$A$4:$S$19,H$1,0) -> 0.91127213 | J39: =VLOOKUP($B39,'Global Venture Capital'!$A$4:$S$19,J$1,0) -> -0.15014063 | K39: =VLOOKUP($B39,'Global Venture Capital'!$A$4:$S$19,K$1,0) -> 0.070688776 | L39: =VLOOKUP($B39,'Global Venture Capital'!$A$4:$S$19,L$1,0) -> -0.079451857 | M39: =VLOOKUP($B39,'Global Venture Capital'!$A$4:$S$19,M$1,0) -> 0.91127213 | O39: =VLOOKUP($B39,'Global Venture Capital'!$A$4:$S$19,O$1,0) -> 0.17030538 | P39: =VLOOKUP($B39,'Global Venture Capital'!$A$4:$S$19,P$1,0) -> 0.098959577 | Q39: =VLOOKUP($B39,'Global Venture Capital'!$A$4:$S$19,Q$1,0) -> 0.19696934 | R39: =VLOOKUP($B39,'Global Venture Capital'!$A$4:$S$19,R$1,0) -> 0.27025621 | T39: =VLOOKUP($B39,'Global Venture Capital'!$A$4:$S$19,T$1,0) -> 0.051868219 | U39: =VLOOKUP($B39,'Global Venture Capital'!$A$4:$S$19,U$1,0) -> 0.085823656 | V39: =VLOOKUP($B39,'Global Venture Capital'!$A$4:$S$19,V$1,0) -> 0.10027967 | W39: =VLOOKUP($B39,'Global Venture Capital'!$A$4:$S$19,W$1,0) -> 0.27025621
A40: Venture Capital | B40: =B39+1 -> 5 | C40: Year 5 | D40: =D8 -> 2029 | E40: =VLOOKUP($B40,'Global Venture Capital'!$A$4:$S$19,E$1,0) -> -0.94282626 | F40: =VLOOKUP($B40,'Global Venture Capital'!$A$4:$S$19,F$1,0) -> 0.21029658 | G40: =VLOOKUP($B40,'Global Venture Capital'!$A$4:$S$19,G$1,0) -> -0.73252968 | H40: =VLOOKUP($B40,'Global Venture Capital'!$A$4:$S$19,H$1,0) -> 0.9773387 | J40: =VLOOKUP($B40,'Global Venture Capital'!$A$4:$S$19,J$1,0) -> -0.099490848 | K40: =VLOOKUP($B40,'Global Venture Capital'!$A$4:$S$19,K$1,0) -> 0.11564395 | L40: =VLOOKUP($B40,'Global Venture Capital'!$A$4:$S$19,L$1,0) -> 0.016153099 | M40: =VLOOKUP($B40,'Global Venture Capital'!$A$4:$S$19,M$1,0) -> 0.9773387 | O40: =VLOOKUP($B40,'Global Venture Capital'!$A$4:$S$19,O$1,0) -> 0.17450797 | P40: =VLOOKUP($B40,'Global Venture Capital'!$A$4:$S$19,P$1,0) -> 0.13153383 | Q40: =VLOOKUP($B40,'Global Venture Capital'!$A$4:$S$19,Q$1,0) -> 0.2185273 | R40: =VLOOKUP($B40,'Global Venture Capital'!$A$4:$S$19,R$1,0) -> 0.37202331 | T40: =VLOOKUP($B40,'Global Venture Capital'!$A$4:$S$19,T$1,0) -> 0.03806717 | U40: =VLOOKUP($B40,'Global Venture Capital'!$A$4:$S$19,U$1,0) -> 0.086649587 | V40: =VLOOKUP($B40,'Global Venture Capital'!$A$4:$S$19,V$1,0) -> 0.094642804 | W40: =VLOOKUP($B40,'Global Venture Capital'!$A$4:$S$19,W$1,0) -> 0.37202331
A41: Venture Capital | B41: =B40+1 -> 6 | C41: Year 6 | D41: =D9 -> 2030 | E41: =VLOOKUP($B41,'Global Venture Capital'!$A$4:$S$19,E$1,0) -> -0.98949946 | F41: =VLOOKUP($B41,'Global Venture Capital'!$A$4:$S$19,F$1,0) -> 0.37897548 | G41: =VLOOKUP($B41,'Global Venture Capital'!$A$4:$S$19,G$1,0) -> -0.61052398 | H41: =VLOOKUP($B41,'Global Venture Capital'!$A$4:$S$19,H$1,0) -> 0.97298201 | J41: =VLOOKUP($B41,'Global Venture Capital'!$A$4:$S$19,J$1,0) -> -0.046673196 | K41: =VLOOKUP($B41,'Global Venture Capital'!$A$4:$S$19,K$1,0) -> 0.16867889 | L41: =VLOOKUP($B41,'Global Venture Capital'!$A$4:$S$19,L$1,0) -> 0.1220057 | M41: =VLOOKUP($B41,'Global Venture Capital'!$A$4:$S$19,M$1,0) -> 0.97298201 | O41: =VLOOKUP($B41,'Global Venture Capital'!$A$4:$S$19,O$1,0) -> 0.17650037 | P41: =VLOOKUP($B41,'Global Venture Capital'!$A$4:$S$19,P$1,0) -> 0.16930847 | Q41: =VLOOKUP($B41,'Global Venture Capital'!$A$4:$S$19,Q$1,0) -> 0.24457665 | R41: =VLOOKUP($B41,'Global Venture Capital'!$A$4:$S$19,R$1,0) -> 0.3995487 | T41: =VLOOKUP($B41,'Global Venture Capital'!$A$4:$S$19,T$1,0) -> 0.026445213 | U41: =VLOOKUP($B41,'Global Venture Capital'!$A$4:$S$19,U$1,0) -> 0.10660304 | V41: =VLOOKUP($B41,'Global Venture Capital'!$A$4:$S$19,V$1,0) -> 0.10983423 | W41: =VLOOKUP($B41,'Global Venture Capital'!$A$4:$S$19,W$1,0) -> 0.3995487
A42: Venture Capital | B42: =B41+1 -> 7 | C42: Year 7 | D42: =D10 -> 2031 | E42: =VLOOKUP($B42,'Global Venture Capital'!$A$4:$S$19,E$1,0) -> -1.0120027 | F42: =VLOOKUP($B42,'Global Venture Capital'!$A$4:$S$19,F$1,0) -> 0.54990364 | G42: =VLOOKUP($B42,'Global Venture Capital'!$A$4:$S$19,G$1,0) -> -0.46209909 | H42: =VLOOKUP($B42,'Global Venture Capital'!$A$4:$S$19,H$1,0) -> 0.90210478 | J42: =VLOOKUP($B42,'Global Venture Capital'!$A$4:$S$19,J$1,0) -> -0.022503275 | K42: =VLOOKUP($B42,'Global Venture Capital'!$A$4:$S$19,K$1,0) -> 0.17092817 | L42: =VLOOKUP($B42,'Global Venture Capital'!$A$4:$S$19,L$1,0) -> 0.14842489 | M42: =VLOOKUP($B42,'Global Venture Capital'!$A$4:$S$19,M$1,0) -> 0.90210478 | O42: =VLOOKUP($B42,'Global Venture Capital'!$A$4:$S$19,O$1,0) -> 0.17724016 | P42: =VLOOKUP($B42,'Global Venture Capital'!$A$4:$S$19,P$1,0) -> 0.19388613 | Q42: =VLOOKUP($B42,'Global Venture Capital'!$A$4:$S$19,Q$1,0) -> 0.26268975 | R42: =VLOOKUP($B42,'Global Venture Capital'!$A$4:$S$19,R$1,0) -> 0.42161197 | T42: =VLOOKUP($B42,'Global Venture Capital'!$A$4:$S$19,T$1,0) -> 0.01617694 | U42: =VLOOKUP($B42,'Global Venture Capital'!$A$4:$S$19,U$1,0) -> 0.09448003 | V42: =VLOOKUP($B42,'Global Venture Capital'!$A$4:$S$19,V$1,0) -> 0.09585494 | W42: =VLOOKUP($B42,'Global Venture Capital'!$A$4:$S$19,W$1,0) -> 0.42161197
A43: Venture Capital | B43: =B42+1 -> 8 | C43: Year 8 | D43: =D11 -> 2032 | E43: =VLOOKUP($B43,'Global Venture Capital'!$A$4:$S$19,E$1,0) -> -1.0237832 | F43: =VLOOKUP($B43,'Global Venture Capital'!$A$4:$S$19,F$1,0) -> 0.73067667 | G43: =VLOOKUP($B43,'Global Venture Capital'!$A$4:$S$19,G$1,0) -> -0.29310653 | H43: =VLOOKUP($B43,'Global Venture Capital'!$A$4:$S$19,H$1,0) -> 0.84662335 | J43: =VLOOKUP($B43,'Global Venture Capital'!$A$4:$S$19,J$1,0) -> -0.011780469 | K43: =VLOOKUP($B43,'Global Venture Capital'!$A$4:$S$19,K$1,0) -> 0.18077303 | L43: =VLOOKUP($B43,'Global Venture Capital'!$A$4:$S$19,L$1,0) -> 0.16899256 | M43: =VLOOKUP($B43,'Global Venture Capital'!$A$4:$S$19,M$1,0) -> 0.84662335 | O43: =VLOOKUP($B43,'Global Venture Capital'!$A$4:$S$19,O$1,0) -> 0.17754313 | P43: =VLOOKUP($B43,'Global Venture Capital'!$A$4:$S$19,P$1,0) -> 0.22046186 | Q43: =VLOOKUP($B43,'Global Venture Capital'!$A$4:$S$19,Q$1,0) -> 0.28306359 | R43: =VLOOKUP($B43,'Global Venture Capital'!$A$4:$S$19,R$1,0) -> 0.43708939 | T43: =VLOOKUP($B43,'Global Venture Capital'!$A$4:$S$19,T$1,0) -> 0.010367675 | U43: =VLOOKUP($B43,'Global Venture Capital'!$A$4:$S$19,U$1,0) -> 0.10493618 | V43: =VLOOKUP($B43,'Global Venture Capital'!$A$4:$S$19,V$1,0) -> 0.10544709 | W43: =VLOOKUP($B43,'Global Venture Capital'!$A$4:$S$19,W$1,0) -> 0.43708939
A44: Venture Capital | B44: =B43+1 -> 9 | C44: Year 9 | D44: =D12 -> 2033 | E44: =VLOOKUP($B44,'Global Venture Capital'!$A$4:$S$19,E$1,0) -> -1.0301158 | F44: =VLOOKUP($B44,'Global Venture Capital'!$A$4:$S$19,F$1,0) -> 0.92161549 | G44: =VLOOKUP($B44,'Global Venture Capital'!$A$4:$S$19,G$1,0) -> -0.10850034 | H44: =VLOOKUP($B44,'Global Venture Capital'!$A$4:$S$19,H$1,0) -> 0.74842013 | J44: =VLOOKUP($B44,'Global Venture Capital'!$A$4:$S$19,J$1,0) -> -0.006332631 | K44: =VLOOKUP($B44,'Global Venture Capital'!$A$4:$S$19,K$1,0) -> 0.19093882 | L44: =VLOOKUP($B44,'Global Venture Capital'!$A$4:$S$19,L$1,0) -> 0.18460619 | M44: =VLOOKUP($B44,'Global Venture Capital'!$A$4:$S$19,M$1,0) -> 0.74842013 | O44: =VLOOKUP($B44,'Global Venture Capital'!$A$4:$S$19,O$1,0) -> 0.17762925 | P44: =VLOOKUP($B44,'Global Venture Capital'!$A$4:$S$19,P$1,0) -> 0.24694028 | Q44: =VLOOKUP($B44,'Global Venture Capital'!$A$4:$S$19,Q$1,0) -> 0.30419015 | R44: =VLOOKUP($B44,'Global Venture Capital'!$A$4:$S$19,R$1,0) -> 0.45163211 | T44: =VLOOKUP($B44,'Global Venture Capital'!$A$4:$S$19,T$1,0) -> 0.0055305023 | U44: =VLOOKUP($B44,'Global Venture Capital'!$A$4:$S$19,U$1,0) -> 0.11124777 | V44: =VLOOKUP($B44,'Global Venture Capital'!$A$4:$S$19,V$1,0) -> 0.11138516 | W44: =VLOOKUP($B44,'Global Venture Capital'!$A$4:$S$19,W$1,0) -> 0.45163211
A45: Venture Capital | B45: =B44+1 -> 10 | C45: Year 10 | D45: =D13 -> 2034 | E45: =VLOOKUP($B45,'Global Venture Capital'!$A$4:$S$19,E$1,0) -> -1.0347462 | F45: =VLOOKUP($B45,'Global Venture Capital'!$A$4:$S$19,F$1,0) -> 1.0884033 | G45: =VLOOKUP($B45,'Global Venture Capital'!$A$4:$S$19,G$1,0) -> 0.053657147 | H45: =VLOOKUP($B45,'Global Venture Capital'!$A$4:$S$19,H$1,0) -> 0.6497776 | J45: =VLOOKUP($B45,'Global Venture Capital'!$A$4:$S$19,J$1,0) -> -0.004630323 | K45: =VLOOKUP($B45,'Global Venture Capital'!$A$4:$S$19,K$1,0) -> 0.16678781 | L45: =VLOOKUP($B45,'Global Venture Capital'!$A$4:$S$19,L$1,0) -> 0.16215749 | M45: =VLOOKUP($B45,'Global Venture Capital'!$A$4:$S$19,M$1,0) -> 0.6497776 | O45: =VLOOKUP($B45,'Global Venture Capital'!$A$4:$S$19,O$1,0) -> 0.17769893 | P45: =VLOOKUP($B45,'Global Venture Capital'!$A$4:$S$19,P$1,0) -> 0.26572443 | Q45: =VLOOKUP($B45,'Global Venture Capital'!$A$4:$S$19,Q$1,0) -> 0.31966605 | R45: =VLOOKUP($B45,'Global Venture Capital'!$A$4:$S$19,R$1,0) -> 0.46026176 | T45: =VLOOKUP($B45,'Global Venture Capital'!$A$4:$S$19,T$1,0) -> 0.0049758808 | U45: =VLOOKUP($B45,'Global Venture Capital'!$A$4:$S$19,U$1,0) -> 0.098132431 | V45: =VLOOKUP($B45,'Global Venture Capital'!$A$4:$S$19,V$1,0) -> 0.098258503 | W45: =VLOOKUP($B45,'Global Venture Capital'!$A$4:$S$19,W$1,0) -> 0.46026176
A46: Venture Capital | B46: =B45+1 -> 11 | C46: Year 11 | D46: =D14 -> 2035 | E46: =VLOOKUP($B46,'Global Venture Capital'!$A$4:$S$19,E$1,0) -> -1.0369946 | F46: =VLOOKUP($B46,'Global Venture Capital'!$A$4:$S$19,F$1,0) -> 1.226243 | G46: =VLOOKUP($B46,'Global Venture Capital'!$A$4:$S$19,G$1,0) -> 0.18924834 | H46: =VLOOKUP($B46,'Global Venture Capital'!$A$4:$S$19,H$1,0) -> 0.56613933 | J46: =VLOOKUP($B46,'Global Venture Capital'!$A$4:$S$19,J$1,0) -> -0.0022484604 | K46: =VLOOKUP($B46,'Global Venture Capital'!$A$4:$S$19,K$1,0) -> 0.13783965 | L46: =VLOOKUP($B46,'Global Venture Capital'!$A$4:$S$19,L$1,0) -> 0.13559119 | M46: =VLOOKUP($B46,'Global Venture Capital'!$A$4:$S$19,M$1,0) -> 0.56613933 | O46: =VLOOKUP($B46,'Global Venture Capital'!$A$4:$S$19,O$1,0) -> 0.17771496 | P46: =VLOOKUP($B46,'Global Venture Capital'!$A$4:$S$19,P$1,0) -> 0.28127403 | Q46: =VLOOKUP($B46,'Global Venture Capital'!$A$4:$S$19,Q$1,0) -> 0.33271262 | R46: =VLOOKUP($B46,'Global Venture Capital'!$A$4:$S$19,R$1,0) -> 0.46659 | T46: =VLOOKUP($B46,'Global Venture Capital'!$A$4:$S$19,T$1,0) -> 0.0023874369 | U46: =VLOOKUP($B46,'Global Venture Capital'!$A$4:$S$19,U$1,0) -> 0.092225832 | V46: =VLOOKUP($B46,'Global Venture Capital'!$A$4:$S$19,V$1,0) -> 0.092256729 | W46: =VLOOKUP($B46,'Global Venture Capital'!$A$4:$S$19,W$1,0) -> 0.46659
A47: Venture Capital | B47: =B46+1 -> 12 | C47: Year 12 | D47: =D15 -> 2036 | E47: =VLOOKUP($B47,'Global Venture Capital'!$A$4:$S$19,E$1,0) -> -1.0377387 | F47: =VLOOKUP($B47,'Global Venture Capital'!$A$4:$S$19,F$1,0) -> 1.3420955 | G47: =VLOOKUP($B47,'Global Venture Capital'!$A$4:$S$19,G$1,0) -> 0.30435679 | H47: =VLOOKUP($B47,'Global Venture Capital'!$A$4:$S$19,H$1,0) -> 0.48253973 | J47: =VLOOKUP($B47,'Global Venture Capital'!$A$4:$S$19,J$1,0) -> -0.00074406057 | K47: =VLOOKUP($B47,'Global Venture Capital'!$A$4:$S$19,K$1,0) -> 0.11585251 | L47: =VLOOKUP($B47,'Global Venture Capital'!$A$4:$S$19,L$1,0) -> 0.11510845 | M47: =VLOOKUP($B47,'Global Venture Capital'!$A$4:$S$19,M$1,0) -> 0.48253973 | O47: =VLOOKUP($B47,'Global Venture Capital'!$A$4:$S$19,O$1,0) -> 0.17772033 | P47: =VLOOKUP($B47,'Global Venture Capital'!$A$4:$S$19,P$1,0) -> 0.29312446 | Q47: =VLOOKUP($B47,'Global Venture Capital'!$A$4:$S$19,Q$1,0) -> 0.34279216 | R47: =VLOOKUP($B47,'Global Venture Capital'!$A$4:$S$19,R$1,0) -> 0.46972902 | T47: =VLOOKUP($B47,'Global Venture Capital'!$A$4:$S$19,T$1,0) -> 0.0013802839 | U47: =VLOOKUP($B47,'Global Venture Capital'!$A$4:$S$19,U$1,0) -> 0.082503773 | V47: =VLOOKUP($B47,'Global Venture Capital'!$A$4:$S$19,V$1,0) -> 0.082515318 | W47: =VLOOKUP($B47,'Global Venture Capital'!$A$4:$S$19,W$1,0) -> 0.46972902
A48: Venture Capital | B48: =B47+1 -> 13 | C48: Year 13 | D48: =D16 -> 2037 | E48: =VLOOKUP($B48,'Global Venture Capital'!$A$4:$S$19,E$1,0) -> -1.0378949 | F48: =VLOOKUP($B48,'Global Venture Capital'!$A$4:$S$19,F$1,0) -> 1.4229508 | G48: =VLOOKUP($B48,'Global Venture Capital'!$A$4:$S$19,G$1,0) -> 0.38505594 | H48: =VLOOKUP($B48,'Global Venture Capital'!$A$4:$S$19,H$1,0) -> 0.43233375 | J48: =VLOOKUP($B48,'Global Venture Capital'!$A$4:$S$19,J$1,0) -> -0.00015619026 | K48: =VLOOKUP($B48,'Global Venture Capital'!$A$4:$S$19,K$1,0) -> 0.080855341 | L48: =VLOOKUP($B48,'Global Venture Capital'!$A$4:$S$19,L$1,0) -> 0.08069915 | M48: =VLOOKUP($B48,'Global Venture Capital'!$A$4:$S$19,M$1,0) -> 0.43233375 | O48: =VLOOKUP($B48,'Global Venture Capital'!$A$4:$S$19,O$1,0) -> 0.1777208 | P48: =VLOOKUP($B48,'Global Venture Capital'!$A$4:$S$19,P$1,0) -> 0.30027254 | Q48: =VLOOKUP($B48,'Global Venture Capital'!$A$4:$S$19,Q$1,0) -> 0.34892446 | R48: =VLOOKUP($B48,'Global Venture Capital'!$A$4:$S$19,R$1,0) -> 0.471192 | T48: =VLOOKUP($B48,'Global Venture Capital'!$A$4:$S$19,T$1,0) -> 0.00041202907 | U48: =VLOOKUP($B48,'Global Venture Capital'!$A$4:$S$19,U$1,0) -> 0.065127911 | V48: =VLOOKUP($B48,'Global Venture Capital'!$A$4:$S$19,V$1,0) -> 0.065129214 | W48: =VLOOKUP($B48,'Global Venture Capital'!$A$4:$S$19,W$1,0) -> 0.471192
A49: Venture Capital | B49: =B48+1 -> 14 | C49: Year 14 | D49: =D17 -> 2038 | E49: =VLOOKUP($B49,'Global Venture Capital'!$A$4:$S$19,E$1,0) -> -1.0381194 | F49: =VLOOKUP($B49,'Global Venture Capital'!$A$4:$S$19,F$1,0) -> 1.4937047 | G49: =VLOOKUP($B49,'Global Venture Capital'!$A$4:$S$19,G$1,0) -> 0.45558537 | H49: =VLOOKUP($B49,'Global Venture Capital'!$A$4:$S$19,H$1,0) -> 0.39186386 | J49: =VLOOKUP($B49,'Global Venture Capital'!$A$4:$S$19,J$1,0) -> -0.00022448936 | K49: =VLOOKUP($B49,'Global Venture Capital'!$A$4:$S$19,K$1,0) -> 0.070753919 | L49: =VLOOKUP($B49,'Global Venture Capital'!$A$4:$S$19,L$1,0) -> 0.07052943 | M49: =VLOOKUP($B49,'Global Venture Capital'!$A$4:$S$19,M$1,0) -> 0.39186386 | O49: =VLOOKUP($B49,'Global Venture Capital'!$A$4:$S$19,O$1,0) -> 0.17772236 | P49: =VLOOKUP($B49,'Global Venture Capital'!$A$4:$S$19,P$1,0) -> 0.3046104 | Q49: =VLOOKUP($B49,'Global Venture Capital'!$A$4:$S$19,Q$1,0) -> 0.35266518 | R49: =VLOOKUP($B49,'Global Venture Capital'!$A$4:$S$19,R$1,0) -> 0.47189862 | T49: =VLOOKUP($B49,'Global Venture Capital'!$A$4:$S$19,T$1,0) -> 0.0007435071 | U49: =VLOOKUP($B49,'Global Venture Capital'!$A$4:$S$19,U$1,0) -> 0.05122399 | V49: =VLOOKUP($B49,'Global Venture Capital'!$A$4:$S$19,V$1,0) -> 0.051229386 | W49: =VLOOKUP($B49,'Global Venture Capital'!$A$4:$S$19,W$1,0) -> 0.47189862
A50: Venture Capital | B50: =B49+1 -> 15 | C50: Year 15 | D50: =D18 -> 2039 | E50: =VLOOKUP($B50,'Global Venture Capital'!$A$4:$S$19,E$1,0) -> -1.0381272 | F50: =VLOOKUP($B50,'Global Venture Capital'!$A$4:$S$19,F$1,0) -> 1.5411408 | G50: =VLOOKUP($B50,'Global Venture Capital'!$A$4:$S$19,G$1,0) -> 0.50301365 | H50: =VLOOKUP($B50,'Global Venture Capital'!$A$4:$S$19,H$1,0) -> 0.35970177 | J50: =VLOOKUP($B50,'Global Venture Capital'!$A$4:$S$19,J$1,0) -> -7.8131231e-06 | K50: =VLOOKUP($B50,'Global Venture Capital'!$A$4:$S$19,K$1,0) -> 0.047436099 | L50: =VLOOKUP($B50,'Global Venture Capital'!$A$4:$S$19,L$1,0) -> 0.047428286 | M50: =VLOOKUP($B50,'Global Venture Capital'!$A$4:$S$19,M$1,0) -> 0.35970177 | O50: =VLOOKUP($B50,'Global Venture Capital'!$A$4:$S$19,O$1,0) -> 0.17772236 | P50: =VLOOKUP($B50,'Global Venture Capital'!$A$4:$S$19,P$1,0) -> 0.30724474 | Q50: =VLOOKUP($B50,'Global Venture Capital'!$A$4:$S$19,Q$1,0) -> 0.35494305 | R50: =VLOOKUP($B50,'Global Venture Capital'!$A$4:$S$19,R$1,0) -> 0.47255184 | T50: =VLOOKUP($B50,'Global Venture Capital'!$A$4:$S$19,T$1,0) -> 4.0598178e-05 | U50: =VLOOKUP($B50,'Global Venture Capital'!$A$4:$S$19,U$1,0) -> 0.040147675 | V50: =VLOOKUP($B50,'Global Venture Capital'!$A$4:$S$19,V$1,0) -> 0.040147695 | W50: =VLOOKUP($B50,'Global Venture Capital'!$A$4:$S$19,W$1,0) -> 0.47255184 | Y50: =SUM(H50,F50)/-E50 -> 1.8310306 | Z50: =SUM(M50,K36:K50)/-SUM(J36:J50) -> 1.8310306 | AA50: =Y50=Z50 -> TRUE
A52: Fund of Funds | B52: 1 | C52: Year 1 | D52: =D4 -> 2025 | E52: =VLOOKUP($B52,'Global Fund of Funds'!$A$4:$S$19,E$1,0) -> -0.11518235 | F52: =VLOOKUP($B52,'Global Fund of Funds'!$A$4:$S$19,F$1,0) -> 0 | G52: =VLOOKUP($B52,'Global Fund of Funds'!$A$4:$S$19,G$1,0) -> -0.11518235 | H52: =VLOOKUP($B52,'Global Fund of Funds'!$A$4:$S$19,H$1,0) -> 0.10659817 | J52: =VLOOKUP($B52,'Global Fund of Funds'!$A$4:$S$19,J$1,0) -> -0.11518235 | K52: =VLOOKUP($B52,'Global Fund of Funds'!$A$4:$S$19,K$1,0) -> 0 | L52: =VLOOKUP($B52,'Global Fund of Funds'!$A$4:$S$19,L$1,0) -> -0.11518235 | M52: =VLOOKUP($B52,'Global Fund of Funds'!$A$4:$S$19,M$1,0) -> 0.10659817 | O52: =VLOOKUP($B52,'Global Fund of Funds'!$A$4:$S$19,O$1,0) -> 0.030010169 | P52: =VLOOKUP($B52,'Global Fund of Funds'!$A$4:$S$19,P$1,0) -> 0 | Q52: =VLOOKUP($B52,'Global Fund of Funds'!$A$4:$S$19,Q$1,0) -> 0.030010169 | R52: =VLOOKUP($B52,'Global Fund of Funds'!$A$4:$S$19,R$1,0) -> 0.030850918 | T52: =VLOOKUP($B52,'Global Fund of Funds'!$A$4:$S$19,T$1,0) -> 0.028137888 | U52: =VLOOKUP($B52,'Global Fund of Funds'!$A$4:$S$19,U$1,0) -> 0 | V52: =VLOOKUP($B52,'Global Fund of Funds'!$A$4:$S$19,V$1,0) -> 0.028137888 | W52: =VLOOKUP($B52,'Global Fund of Funds'!$A$4:$S$19,W$1,0) -> 0.030850918
A53: Fund of Funds | B53: =B52+1 -> 2 | C53: Year 2 | D53: =D5 -> 2026 | E53: =VLOOKUP($B53,'Global Fund of Funds'!$A$4:$S$19,E$1,0) -> -0.27115225 | F53: =VLOOKUP($B53,'Global Fund of Funds'!$A$4:$S$19,F$1,0) -> 0.00014131239 | G53: =VLOOKUP($B53,'Global Fund of Funds'!$A$4:$S$19,G$1,0) -> -0.27101093 | H53: =VLOOKUP($B53,'Global Fund of Funds'!$A$4:$S$19,H$1,0) -> 0.26700232 | J53: =VLOOKUP($B53,'Global Fund of Funds'!$A$4:$S$19,J$1,0) -> -0.1559699 | K53: =VLOOKUP($B53,'Global Fund of Funds'!$A$4:$S$19,K$1,0) -> 0.00014131239 | L53: =VLOOKUP($B53,'Global Fund of Funds'!$A$4:$S$19,L$1,0) -> -0.15582858 | M53: =VLOOKUP($B53,'Global Fund of Funds'!$A$4:$S$19,M$1,0) -> 0.26700232 | O53: =VLOOKUP($B53,'Global Fund of Funds'!$A$4:$S$19,O$1,0) -> 0.049774526 | P53: =VLOOKUP($B53,'Global Fund of Funds'!$A$4:$S$19,P$1,0) -> 0.00032633474 | Q53: =VLOOKUP($B53,'Global Fund of Funds'!$A$4:$S$19,Q$1,0) -> 0.049775596 | R53: =VLOOKUP($B53,'Global Fund of Funds'!$A$4:$S$19,R$1,0) -> 0.062918825 | T53: =VLOOKUP($B53,'Global Fund of Funds'!$A$4:$S$19,T$1,0) -> 0.039710115 | U53: =VLOOKUP($B53,'Global Fund of Funds'!$A$4:$S$19,U$1,0) -> 0.00032633474 | V53: =VLOOKUP($B53,'Global Fund of Funds'!$A$4:$S$19,V$1,0) -> 0.039711456 | W53: =VLOOKUP($B53,'Global Fund of Funds'!$A$4:$S$19,W$1,0) -> 0.062918825
A54: Fund of Funds | B54: =B53+1 -> 3 | C54: Year 3 | D54: =D6 -> 2027 | E54: =VLOOKUP($B54,'Global Fund of Funds'!$A$4:$S$19,E$1,0) -> -0.47009771 | F54: =VLOOKUP($B54,'Global Fund of Funds'!$A$4:$S$19,F$1,0) -> 0.010309711 | G54: =VLOOKUP($B54,'Global Fund of Funds'!$A$4:$S$19,G$1,0) -> -0.459788 | H54: =VLOOKUP($B54,'Global Fund of Funds'!$A$4:$S$19,H$1,0) -> 0.4964324 | J54: =VLOOKUP($B54,'Global Fund of Funds'!$A$4:$S$19,J$1,0) -> -0.19894546 | K54: =VLOOKUP($B54,'Global Fund of Funds'!$A$4:$S$19,K$1,0) -> 0.010168398 | L54: =VLOOKUP($B54,'Global Fund of Funds'!$A$4:$S$19,L$1,0) -> -0.18877706 | M54: =VLOOKUP($B54,'Global Fund of Funds'!$A$4:$S$19,M$1,0) -> 0.4964324 | O54: =VLOOKUP($B54,'Global Fund of Funds'!$A$4:$S$19,O$1,0) -> 0.072044206 | P54: =VLOOKUP($B54,'Global Fund of Funds'!$A$4:$S$19,P$1,0) -> 0.0083802638 | Q54: =VLOOKUP($B54,'Global Fund of Funds'!$A$4:$S$19,Q$1,0) -> 0.072529969 | R54: =VLOOKUP($B54,'Global Fund of Funds'!$A$4:$S$19,R$1,0) -> 0.12865934 | T54: =VLOOKUP($B54,'Global Fund of Funds'!$A$4:$S$19,T$1,0) -> 0.052085163 | U54: =VLOOKUP($B54,'Global Fund of Funds'!$A$4:$S$19,U$1,0) -> 0.0083739075 | V54: =VLOOKUP($B54,'Global Fund of Funds'!$A$4:$S$19,V$1,0) -> 0.052754019 | W54: =VLOOKUP($B54,'Global Fund of Funds'!$A$4:$S$19,W$1,0) -> 0.12865934
A55: Fund of Funds | B55: =B54+1 -> 4 | C55: Year 4 | D55: =D7 -> 2028 | E55: =VLOOKUP($B55,'Global Fund of Funds'!$A$4:$S$19,E$1,0) -> -0.65368453 | F55: =VLOOKUP($B55,'Global Fund of Funds'!$A$4:$S$19,F$1,0) -> 0.051436872 | G55: =VLOOKUP($B55,'Global Fund of Funds'!$A$4:$S$19,G$1,0) -> -0.60224766 | H55: =VLOOKUP($B55,'Global Fund of Funds'!$A$4:$S$19,H$1,0) -> 0.68604779 | J55: =VLOOKUP($B55,'Global Fund of Funds'!$A$4:$S$19,J$1,0) -> -0.18358682 | K55: =VLOOKUP($B55,'Global Fund of Funds'!$A$4:$S$19,K$1,0) -> 0.041127162 | L55: =VLOOKUP($B55,'Global Fund of Funds'!$A$4:$S$19,L$1,0) -> -0.14245966 | M55: =VLOOKUP($B55,'Global Fund of Funds'!$A$4:$S$19,M$1,0) -> 0.68604779 | O55: =VLOOKUP($B55,'Global Fund of Funds'!$A$4:$S$19,O$1,0) -> 0.079698444 | P55: =VLOOKUP($B55,'Global Fund of Funds'!$A$4:$S$19,P$1,0) -> 0.041100169 | Q55: =VLOOKUP($B55,'Global Fund of Funds'!$A$4:$S$19,Q$1,0) -> 0.08967199 | R55: =VLOOKUP($B55,'Global Fund of Funds'!$A$4:$S$19,R$1,0) -> 0.1677837 | T55: =VLOOKUP($B55,'Global Fund of Funds'!$A$4:$S$19,T$1,0) -> 0.034080409 | U55: =VLOOKUP($B55,'Global Fund of Funds'!$A$4:$S$19,U$1,0) -> 0.040236738 | V55: =VLOOKUP($B55,'Global Fund of Funds'!$A$4:$S$19,V$1,0) -> 0.052730156 | W55: =VLOOKUP($B55,'Global Fund of Funds'!$A$4:$S$19,W$1,0) -> 0.1677837
A56: Fund of Funds | B56: =B55+1 -> 5 | C56: Year 5 | D56: =D8 -> 2029 | E56: =VLOOKUP($B56,'Global Fund of Funds'!$A$4:$S$19,E$1,0) -> -0.78082091 | F56: =VLOOKUP($B56,'Global Fund of Funds'!$A$4:$S$19,F$1,0) -> 0.11430678 | G56: =VLOOKUP($B56,'Global Fund of Funds'!$A$4:$S$19,G$1,0) -> -0.66651413 | H56: =VLOOKUP($B56,'Global Fund of Funds'!$A$4:$S$19,H$1,0) -> 0.82698154 | J56: =VLOOKUP($B56,'Global Fund of Funds'!$A$4:$S$19,J$1,0) -> -0.12713638 | K56: =VLOOKUP($B56,'Global Fund of Funds'!$A$4:$S$19,K$1,0) -> 0.062869906 | L56: =VLOOKUP($B56,'Global Fund of Funds'!$A$4:$S$19,L$1,0) -> -0.064266471 | M56: =VLOOKUP($B56,'Global Fund of Funds'!$A$4:$S$19,M$1,0) -> 0.82698154 | O56: =VLOOKUP($B56,'Global Fund of Funds'!$A$4:$S$19,O$1,0) -> 0.088773278 | P56: =VLOOKUP($B56,'Global Fund of Funds'!$A$4:$S$19,P$1,0) -> 0.051606205 | Q56: =VLOOKUP($B56,'Global Fund of Funds'!$A$4:$S$19,Q$1,0) -> 0.10268347 | R56: =VLOOKUP($B56,'Global Fund of Funds'!$A$4:$S$19,R$1,0) -> 0.19436939 | T56: =VLOOKUP($B56,'Global Fund of Funds'!$A$4:$S$19,T$1,0) -> 0.03910055 | U56: =VLOOKUP($B56,'Global Fund of Funds'!$A$4:$S$19,U$1,0) -> 0.031208595 | V56: =VLOOKUP($B56,'Global Fund of Funds'!$A$4:$S$19,V$1,0) -> 0.050028286 | W56: =VLOOKUP($B56,'Global Fund of Funds'!$A$4:$S$19,W$1,0) -> 0.19436939
A57: Fund of Funds | B57: =B56+1 -> 6 | C57: Year 6 | D57: =D9 -> 2030 | E57: =VLOOKUP($B57,'Global Fund of Funds'!$A$4:$S$19,E$1,0) -> -0.86832056 | F57: =VLOOKUP($B57,'Global Fund of Funds'!$A$4:$S$19,F$1,0) -> 0.20061372 | G57: =VLOOKUP($B57,'Global Fund of Funds'!$A$4:$S$19,G$1,0) -> -0.66770684 | H57: =VLOOKUP($B57,'Global Fund of Funds'!$A$4:$S$19,H$1,0) -> 0.93955779 | J57: =VLOOKUP($B57,'Global Fund of Funds'!$A$4:$S$19,J$1,0) -> -0.087499649 | K57: =VLOOKUP($B57,'Global Fund of Funds'!$A$4:$S$19,K$1,0) -> 0.08630694 | L57: =VLOOKUP($B57,'Global Fund of Funds'!$A$4:$S$19,L$1,0) -> -0.0011927092 | M57: =VLOOKUP($B57,'Global Fund of Funds'!$A$4:$S$19,M$1,0) -> 0.93955779 | O57: =VLOOKUP($B57,'Global Fund of Funds'!$A$4:$S$19,O$1,0) -> 0.09280891 | P57: =VLOOKUP($B57,'Global Fund of Funds'!$A$4:$S$19,P$1,0) -> 0.064103806 | Q57: =VLOOKUP($B57,'Global Fund of Funds'!$A$4:$S$19,Q$1,0) -> 0.11279535 | R57: =VLOOKUP($B57,'Global Fund of Funds'!$A$4:$S$19,R$1,0) -> 0.21355329 | T57: =VLOOKUP($B57,'Global Fund of Funds'!$A$4:$S$19,T$1,0) -> 0.027070257 | U57: =VLOOKUP($B57,'Global Fund of Funds'!$A$4:$S$19,U$1,0) -> 0.03802759 | V57: =VLOOKUP($B57,'Global Fund of Funds'!$A$4:$S$19,V$1,0) -> 0.046678651 | W57: =VLOOKUP($B57,'Global Fund of Funds'!$A$4:$S$19,W$1,0) -> 0.21355329
A58: Fund of Funds | B58: =B57+1 -> 7 | C58: Year 7 | D58: =D10 -> 2031 | E58: =VLOOKUP($B58,'Global Fund of Funds'!$A$4:$S$19,E$1,0) -> -0.92071816 | F58: =VLOOKUP($B58,'Global Fund of Funds'!$A$4:$S$19,F$1,0) -> 0.3289331 | G58: =VLOOKUP($B58,'Global Fund of Funds'!$A$4:$S$19,G$1,0) -> -0.59178506 | H58: =VLOOKUP($B58,'Global Fund of Funds'!$A$4:$S$19,H$1,0) -> 0.99273251 | J58: =VLOOKUP($B58,'Global Fund of Funds'!$A$4:$S$19,J$1,0) -> -0.052397606 | K58: =VLOOKUP($B58,'Global Fund of Funds'!$A$4:$S$19,K$1,0) -> 0.12831939 | L58: =VLOOKUP($B58,'Global Fund of Funds'!$A$4:$S$19,L$1,0) -> 0.075921781 | M58: =VLOOKUP($B58,'Global Fund of Funds'!$A$4:$S$19,M$1,0) -> 0.99273251 | O58: =VLOOKUP($B58,'Global Fund of Funds'!$A$4:$S$19,O$1,0) -> 0.095512947 | P58: =VLOOKUP($B58,'Global Fund of Funds'!$A$4:$S$19,P$1,0) -> 0.076287415 | Q58: =VLOOKUP($B58,'Global Fund of Funds'!$A$4:$S$19,Q$1,0) -> 0.12223949 | R58: =VLOOKUP($B58,'Global Fund of Funds'!$A$4:$S$19,R$1,0) -> 0.2300484 | T58: =VLOOKUP($B58,'Global Fund of Funds'!$A$4:$S$19,T$1,0) -> 0.022566108 | U58: =VLOOKUP($B58,'Global Fund of Funds'!$A$4:$S$19,U$1,0) -> 0.04135785 | V58: =VLOOKUP($B58,'Global Fund of Funds'!$A$4:$S$19,V$1,0) -> 0.047113703 | W58: =VLOOKUP($B58,'Global Fund of Funds'!$A$4:$S$19,W$1,0) -> 0.2300484
A59: Fund of Funds | B59: =B58+1 -> 8 | C59: Year 8 | D59: =D11 -> 2032 | E59: =VLOOKUP($B59,'Global Fund of Funds'!$A$4:$S$19,E$1,0) -> -0.9593627 | F59: =VLOOKUP($B59,'Global Fund of Funds'!$A$4:$S$19,F$1,0) -> 0.47973239 | G59: =VLOOKUP($B59,'Global Fund of Funds'!$A$4:$S$19,G$1,0) -> -0.47963032 | H59: =VLOOKUP($B59,'Global Fund of Funds'!$A$4:$S$19,H$1,0) -> 1.0139481 | J59: =VLOOKUP($B59,'Global Fund of Funds'!$A$4:$S$19,J$1,0) -> -0.038644543 | K59: =VLOOKUP($B59,'Global Fund of Funds'!$A$4:$S$19,K$1,0) -> 0.15079928 | L59: =VLOOKUP($B59,'Global Fund of Funds'!$A$4:$S$19,L$1,0) -> 0.11215474 | M59: =VLOOKUP($B59,'Global Fund of Funds'!$A$4:$S$19,M$1,0) -> 1.0139481 | O59: =VLOOKUP($B59,'Global Fund of Funds'!$A$4:$S$19,O$1,0) -> 0.096960701 | P59: =VLOOKUP($B59,'Global Fund of Funds'!$A$4:$S$19,P$1,0) -> 0.088197542 | Q59: =VLOOKUP($B59,'Global Fund of Funds'!$A$4:$S$19,Q$1,0) -> 0.1310732 | R59: =VLOOKUP($B59,'Global Fund of Funds'!$A$4:$S$19,R$1,0) -> 0.25027587 | T59: =VLOOKUP($B59,'Global Fund of Funds'!$A$4:$S$19,T$1,0) -> 0.01669295 | U59: =VLOOKUP($B59,'Global Fund of Funds'!$A$4:$S$19,U$1,0) -> 0.044261006 | V59: =VLOOKUP($B59,'Global Fund of Funds'!$A$4:$S$19,V$1,0) -> 0.047304241 | W59: =VLOOKUP($B59,'Global Fund of Funds'!$A$4:$S$19,W$1,0) -> 0.25027587
A60: Fund of Funds | B60: =B59+1 -> 9 | C60: Year 9 | D60: =D12 -> 2033 | E60: =VLOOKUP($B60,'Global Fund of Funds'!$A$4:$S$19,E$1,0) -> -0.97937018 | F60: =VLOOKUP($B60,'Global Fund of Funds'!$A$4:$S$19,F$1,0) -> 0.64560129 | G60: =VLOOKUP($B60,'Global Fund of Funds'!$A$4:$S$19,G$1,0) -> -0.33376889 | H60: =VLOOKUP($B60,'Global Fund of Funds'!$A$4:$S$19,H$1,0) -> 0.97084216 | J60: =VLOOKUP($B60,'Global Fund of Funds'!$A$4:$S$19,J$1,0) -> -0.020007475 | K60: =VLOOKUP($B60,'Global Fund of Funds'!$A$4:$S$19,K$1,0) -> 0.16586891 | L60: =VLOOKUP($B60,'Global Fund of Funds'!$A$4:$S$19,L$1,0) -> 0.14586143 | M60: =VLOOKUP($B60,'Global Fund of Funds'!$A$4:$S$19,M$1,0) -> 0.97084216 | O60: =VLOOKUP($B60,'Global Fund of Funds'!$A$4:$S$19,O$1,0) -> 0.097512172 | P60: =VLOOKUP($B60,'Global Fund of Funds'!$A$4:$S$19,P$1,0) -> 0.10057853 | Q60: =VLOOKUP($B60,'Global Fund of Funds'!$A$4:$S$19,Q$1,0) -> 0.14008806 | R60: =VLOOKUP($B60,'Global Fund of Funds'!$A$4:$S$19,R$1,0) -> 0.25833195 | T60: =VLOOKUP($B60,'Global Fund of Funds'!$A$4:$S$19,T$1,0) -> 0.010355969 | U60: =VLOOKUP($B60,'Global Fund of Funds'!$A$4:$S$19,U$1,0) -> 0.048344954 | V60: =VLOOKUP($B60,'Global Fund of Funds'!$A$4:$S$19,V$1,0) -> 0.049441689 | W60: =VLOOKUP($B60,'Global Fund of Funds'!$A$4:$S$19,W$1,0) -> 0.25833195
A61: Fund of Funds | B61: =B60+1 -> 10 | C61: Year 10 | D61: =D13 -> 2034 | E61: =VLOOKUP($B61,'Global Fund of Funds'!$A$4:$S$19,E$1,0) -> -0.98785222 | F61: =VLOOKUP($B61,'Global Fund of Funds'!$A$4:$S$19,F$1,0) -> 0.81219372 | G61: =VLOOKUP($B61,'Global Fund of Funds'!$A$4:$S$19,G$1,0) -> -0.1756585 | H61: =VLOOKUP($B61,'Global Fund of Funds'!$A$4:$S$19,H$1,0) -> 0.89305728 | J61: =VLOOKUP($B61,'Global Fund of Funds'!$A$4:$S$19,J$1,0) -> -0.008482041 | K61: =VLOOKUP($B61,'Global Fund of Funds'!$A$4:$S$19,K$1,0) -> 0.16659243 | L61: =VLOOKUP($B61,'Global Fund of Funds'!$A$4:$S$19,L$1,0) -> 0.15811038 | M61: =VLOOKUP($B61,'Global Fund of Funds'!$A$4:$S$19,M$1,0) -> 0.89305728 | O61: =VLOOKUP($B61,'Global Fund of Funds'!$A$4:$S$19,O$1,0) -> 0.097713054 | P61: =VLOOKUP($B61,'Global Fund of Funds'!$A$4:$S$19,P$1,0) -> 0.11449169 | Q61: =VLOOKUP($B61,'Global Fund of Funds'!$A$4:$S$19,Q$1,0) -> 0.15051973 | R61: =VLOOKUP($B61,'Global Fund of Funds'!$A$4:$S$19,R$1,0) -> 0.26693549 | T61: =VLOOKUP($B61,'Global Fund of Funds'!$A$4:$S$19,T$1,0) -> 0.0062623684 | U61: =VLOOKUP($B61,'Global Fund of Funds'!$A$4:$S$19,U$1,0) -> 0.054701979 | V61: =VLOOKUP($B61,'Global Fund of Funds'!$A$4:$S$19,V$1,0) -> 0.055059275 | W61: =VLOOKUP($B61,'Global Fund of Funds'!$A$4:$S$19,W$1,0) -> 0.26693549
A62: Fund of Funds | B62: =B61+1 -> 11 | C62: Year 11 | D62: =D14 -> 2035 | E62: =VLOOKUP($B62,'Global Fund of Funds'!$A$4:$S$19,E$1,0) -> -0.99443709 | F62: =VLOOKUP($B62,'Global Fund of Funds'!$A$4:$S$19,F$1,0) -> 0.95582541 | G62: =VLOOKUP($B62,'Global Fund of Funds'!$A$4:$S$19,G$1,0) -> -0.038611682 | H62: =VLOOKUP($B62,'Global Fund of Funds'!$A$4:$S$19,H$1,0) -> 0.80919076 | J62: =VLOOKUP($B62,'Global Fund of Funds'!$A$4:$S$19,J$1,0) -> -0.0065848683 | K62: =VLOOKUP($B62,'Global Fund of Funds'!$A$4:$S$19,K$1,0) -> 0.14363169 | L62: =VLOOKUP($B62,'Global Fund of Funds'!$A$4:$S$19,L$1,0) -> 0.13704682 | M62: =VLOOKUP($B62,'Global Fund of Funds'!$A$4:$S$19,M$1,0) -> 0.80919076 | O62: =VLOOKUP($B62,'Global Fund of Funds'!$A$4:$S$19,O$1,0) -> 0.097859014 | P62: =VLOOKUP($B62,'Global Fund of Funds'!$A$4:$S$19,P$1,0) -> 0.12305947 | Q62: =VLOOKUP($B62,'Global Fund of Funds'!$A$4:$S$19,Q$1,0) -> 0.15722601 | R62: =VLOOKUP($B62,'Global Fund of Funds'!$A$4:$S$19,R$1,0) -> 0.27159505 | T62: =VLOOKUP($B62,'Global Fund of Funds'!$A$4:$S$19,T$1,0) -> 0.0053428118 | U62: =VLOOKUP($B62,'Global Fund of Funds'!$A$4:$S$19,U$1,0) -> 0.045114141 | V62: =VLOOKUP($B62,'Global Fund of Funds'!$A$4:$S$19,V$1,0) -> 0.045429411 | W62: =VLOOKUP($B62,'Global Fund of Funds'!$A$4:$S$19,W$1,0) -> 0.27159505
A63: Fund of Funds | B63: =B62+1 -> 12 | C63: Year 12 | D63: =D15 -> 2036 | E63: =VLOOKUP($B63,'Global Fund of Funds'!$A$4:$S$19,E$1,0) -> -0.99835989 | F63: =VLOOKUP($B63,'Global Fund of Funds'!$A$4:$S$19,F$1,0) -> 1.0809484 | G63: =VLOOKUP($B63,'Global Fund of Funds'!$A$4:$S$19,G$1,0) -> 0.082588483 | H63: =VLOOKUP($B63,'Global Fund of Funds'!$A$4:$S$19,H$1,0) -> 0.71837628 | J63: =VLOOKUP($B63,'Global Fund of Funds'!$A$4:$S$19,J$1,0) -> -0.0039228015 | K63: =VLOOKUP($B63,'Global Fund of Funds'!$A$4:$S$19,K$1,0) -> 0.12512297 | L63: =VLOOKUP($B63,'Global Fund of Funds'!$A$4:$S$19,L$1,0) -> 0.12120016 | M63: =VLOOKUP($B63,'Global Fund of Funds'!$A$4:$S$19,M$1,0) -> 0.71837628 | O63: =VLOOKUP($B63,'Global Fund of Funds'!$A$4:$S$19,O$1,0) -> 0.097932772 | P63: =VLOOKUP($B63,'Global Fund of Funds'!$A$4:$S$19,P$1,0) -> 0.12982151 | Q63: =VLOOKUP($B63,'Global Fund of Funds'!$A$4:$S$19,Q$1,0) -> 0.1626175 | R63: =VLOOKUP($B63,'Global Fund of Funds'!$A$4:$S$19,R$1,0) -> 0.27711438 | T63: =VLOOKUP($B63,'Global Fund of Funds'!$A$4:$S$19,T$1,0) -> 0.0038001831 | U63: =VLOOKUP($B63,'Global Fund of Funds'!$A$4:$S$19,U$1,0) -> 0.041352046 | V63: =VLOOKUP($B63,'Global Fund of Funds'!$A$4:$S$19,V$1,0) -> 0.041526294 | W63: =VLOOKUP($B63,'Global Fund of Funds'!$A$4:$S$19,W$1,0) -> 0.27711438
A64: Fund of Funds | B64: =B63+1 -> 13 | C64: Year 13 | D64: =D16 -> 2037 | E64: =VLOOKUP($B64,'Global Fund of Funds'!$A$4:$S$19,E$1,0) -> -1.0006304 | F64: =VLOOKUP($B64,'Global Fund of Funds'!$A$4:$S$19,F$1,0) -> 1.1920969 | G64: =VLOOKUP($B64,'Global Fund of Funds'!$A$4:$S$19,G$1,0) -> 0.19146651 | H64: =VLOOKUP($B64,'Global Fund of Funds'!$A$4:$S$19,H$1,0) -> 0.63724883 | J64: =VLOOKUP($B64,'Global Fund of Funds'!$A$4:$S$19,J$1,0) -> -0.0022704789 | K64: =VLOOKUP($B64,'Global Fund of Funds'!$A$4:$S$19,K$1,0) -> 0.11114851 | L64: =VLOOKUP($B64,'Global Fund of Funds'!$A$4:$S$19,L$1,0) -> 0.10887803 | M64: =VLOOKUP($B64,'Global Fund of Funds'!$A$4:$S$19,M$1,0) -> 0.63724883 | O64: =VLOOKUP($B64,'Global Fund of Funds'!$A$4:$S$19,O$1,0) -> 0.097991471 | P64: =VLOOKUP($B64,'Global Fund of Funds'!$A$4:$S$19,P$1,0) -> 0.13423703 | Q64: =VLOOKUP($B64,'Global Fund of Funds'!$A$4:$S$19,Q$1,0) -> 0.1661984 | R64: =VLOOKUP($B64,'Global Fund of Funds'!$A$4:$S$19,R$1,0) -> 0.2799575 | T64: =VLOOKUP($B64,'Global Fund of Funds'!$A$4:$S$19,T$1,0) -> 0.0033912334 | U64: =VLOOKUP($B64,'Global Fund of Funds'!$A$4:$S$19,U$1,0) -> 0.034146072 | V64: =VLOOKUP($B64,'Global Fund of Funds'!$A$4:$S$19,V$1,0) -> 0.03431406 | W64: =VLOOKUP($B64,'Global Fund of Funds'!$A$4:$S$19,W$1,0) -> 0.2799575
A65: Fund of Funds | B65: =B64+1 -> 14 | C65: Year 14 | D65: =D17 -> 2038 | E65: =VLOOKUP($B65,'Global Fund of Funds'!$A$4:$S$19,E$1,0) -> -1.0033847 | F65: =VLOOKUP($B65,'Global Fund of Funds'!$A$4:$S$19,F$1,0) -> 1.2774828 | G65: =VLOOKUP($B65,'Global Fund of Funds'!$A$4:$S$19,G$1,0) -> 0.27409813 | H65: =VLOOKUP($B65,'Global Fund of Funds'!$A$4:$S$19,H$1,0) -> 0.57623795 | J65: =VLOOKUP($B65,'Global Fund of Funds'!$A$4:$S$19,J$1,0) -> -0.0027543279 | K65: =VLOOKUP($B65,'Global Fund of Funds'!$A$4:$S$19,K$1,0) -> 0.085385946 | L65: =VLOOKUP($B65,'Global Fund of Funds'!$A$4:$S$19,L$1,0) -> 0.082631618 | M65: =VLOOKUP($B65,'Global Fund of Funds'!$A$4:$S$19,M$1,0) -> 0.57623795 | O65: =VLOOKUP($B65,'Global Fund of Funds'!$A$4:$S$19,O$1,0) -> 0.098044944 | P65: =VLOOKUP($B65,'Global Fund of Funds'!$A$4:$S$19,P$1,0) -> 0.13755806 | Q65: =VLOOKUP($B65,'Global Fund of Funds'!$A$4:$S$19,Q$1,0) -> 0.16892315 | R65: =VLOOKUP($B65,'Global Fund of Funds'!$A$4:$S$19,R$1,0) -> 0.28169973 | T65: =VLOOKUP($B65,'Global Fund of Funds'!$A$4:$S$19,T$1,0) -> 0.0032376902 | U65: =VLOOKUP($B65,'Global Fund of Funds'!$A$4:$S$19,U$1,0) -> 0.030044005 | V65: =VLOOKUP($B65,'Global Fund of Funds'!$A$4:$S$19,V$1,0) -> 0.030217956 | W65: =VLOOKUP($B65,'Global Fund of Funds'!$A$4:$S$19,W$1,0) -> 0.28169973
A66: Fund of Funds | B66: =B65+1 -> 15 | C66: Year 15 | D66: =D18 -> 2039 | E66: =VLOOKUP($B66,'Global Fund of Funds'!$A$4:$S$19,E$1,0) -> -1.0064449 | F66: =VLOOKUP($B66,'Global Fund of Funds'!$A$4:$S$19,F$1,0) -> 1.3456091 | G66: =VLOOKUP($B66,'Global Fund of Funds'!$A$4:$S$19,G$1,0) -> 0.33916416 | H66: =VLOOKUP($B66,'Global Fund of Funds'!$A$4:$S$19,H$1,0) -> 0.51694479 | J66: =VLOOKUP($B66,'Global Fund of Funds'!$A$4:$S$19,J$1,0) -> -0.0030602363 | K66: =VLOOKUP($B66,'Global Fund of Funds'!$A$4:$S$19,K$1,0) -> 0.068126263 | L66: =VLOOKUP($B66,'Global Fund of Funds'!$A$4:$S$19,L$1,0) -> 0.065066027 | M66: =VLOOKUP($B66,'Global Fund of Funds'!$A$4:$S$19,M$1,0) -> 0.51694479 | O66: =VLOOKUP($B66,'Global Fund of Funds'!$A$4:$S$19,O$1,0) -> 0.098127751 | P66: =VLOOKUP($B66,'Global Fund of Funds'!$A$4:$S$19,P$1,0) -> 0.14016019 | Q66: =VLOOKUP($B66,'Global Fund of Funds'!$A$4:$S$19,Q$1,0) -> 0.17109627 | R66: =VLOOKUP($B66,'Global Fund of Funds'!$A$4:$S$19,R$1,0) -> 0.28223835 | T66: =VLOOKUP($B66,'Global Fund of Funds'!$A$4:$S$19,T$1,0) -> 0.0040304519 | U66: =VLOOKUP($B66,'Global Fund of Funds'!$A$4:$S$19,U$1,0) -> 0.026882296 | V66: =VLOOKUP($B66,'Global Fund of Funds'!$A$4:$S$19,V$1,0) -> 0.027182759 | W66: =VLOOKUP($B66,'Global Fund of Funds'!$A$4:$S$19,W$1,0) -> 0.28223835 | Y66: =SUM(H66,F66)/-E66 -> 1.8506267 | Z66: =SUM(M66,K52:K66)/-SUM(J52:J66) -> 1.8506267 | AA66: =Y66=Z66 -> TRUE
A68: Secondary Funds | B68: 1 | C68: Year 1 | D68: =D4 -> 2025 | E68: =VLOOKUP($B68,'Global Secondary Funds'!$A$4:$S$19,E$1,0) -> -0.040860417 | F68: =VLOOKUP($B68,'Global Secondary Funds'!$A$4:$S$19,F$1,0) -> 0.0008078882 | G68: =VLOOKUP($B68,'Global Secondary Funds'!$A$4:$S$19,G$1,0) -> -0.040052529 | H68: =VLOOKUP($B68,'Global Secondary Funds'!$A$4:$S$19,H$1,0) -> 0.04628579 | J68: =VLOOKUP($B68,'Global Secondary Funds'!$A$4:$S$19,J$1,0) -> -0.040860417 | K68: =VLOOKUP($B68,'Global Secondary Funds'!$A$4:$S$19,K$1,0) -> 0.0008078882 | L68: =VLOOKUP($B68,'Global Secondary Funds'!$A$4:$S$19,L$1,0) -> -0.040052529 | M68: =VLOOKUP($B68,'Global Secondary Funds'!$A$4:$S$19,M$1,0) -> 0.04628579 | O68: =VLOOKUP($B68,'Global Secondary Funds'!$A$4:$S$19,O$1,0) -> 0.027279152 | P68: =VLOOKUP($B68,'Global Secondary Funds'!$A$4:$S$19,P$1,0) -> 0.0021310926 | Q68: =VLOOKUP($B68,'Global Secondary Funds'!$A$4:$S$19,Q$1,0) -> 0.027362268 | R68: =VLOOKUP($B68,'Global Secondary Funds'!$A$4:$S$19,R$1,0) -> 0.031204142 | T68: =VLOOKUP($B68,'Global Secondary Funds'!$A$4:$S$19,T$1,0) -> 0.027279152 | U68: =VLOOKUP($B68,'Global Secondary Funds'!$A$4:$S$19,U$1,0) -> 0.0021310926 | V68: =VLOOKUP($B68,'Global Secondary Funds'!$A$4:$S$19,V$1,0) -> 0.027362268 | W68: =VLOOKUP($B68,'Global Secondary Funds'!$A$4:$S$19,W$1,0) -> 0.031204142
A69: Secondary Funds | B69: =B68+1 -> 2 | C69: Year 2 | D69: =D5 -> 2026 | E69: =VLOOKUP($B69,'Global Secondary Funds'!$A$4:$S$19,E$1,0) -> -0.27071453 | F69: =VLOOKUP($B69,'Global Secondary Funds'!$A$4:$S$19,F$1,0) -> 0.032251884 | G69: =VLOOKUP($B69,'Global Secondary Funds'!$A$4:$S$19,G$1,0) -> -0.23846265 | H69: =VLOOKUP($B69,'Global Secondary Funds'!$A$4:$S$19,H$1,0) -> 0.30324857 | J69: =VLOOKUP($B69,'Global Secondary Funds'!$A$4:$S$19,J$1,0) -> -0.22985412 | K69: =VLOOKUP($B69,'Global Secondary Funds'!$A$4:$S$19,K$1,0) -> 0.031443996 | L69: =VLOOKUP($B69,'Global Secondary Funds'!$A$4:$S$19,L$1,0) -> -0.19841012 | M69: =VLOOKUP($B69,'Global Secondary Funds'!$A$4:$S$19,M$1,0) -> 0.30324857 | O69: =VLOOKUP($B69,'Global Secondary Funds'!$A$4:$S$19,O$1,0) -> 0.08826231 | P69: =VLOOKUP($B69,'Global Secondary Funds'!$A$4:$S$19,P$1,0) -> 0.019483778 | Q69: =VLOOKUP($B69,'Global Secondary Funds'!$A$4:$S$19,Q$1,0) -> 0.090387239 | R69: =VLOOKUP($B69,'Global Secondary Funds'!$A$4:$S$19,R$1,0) -> 0.097869628 | T69: =VLOOKUP($B69,'Global Secondary Funds'!$A$4:$S$19,T$1,0) -> 0.083940951 | U69: =VLOOKUP($B69,'Global Secondary Funds'!$A$4:$S$19,U$1,0) -> 0.01936688 | V69: =VLOOKUP($B69,'Global Secondary Funds'!$A$4:$S$19,V$1,0) -> 0.086146151 | W69: =VLOOKUP($B69,'Global Secondary Funds'!$A$4:$S$19,W$1,0) -> 0.097869628
A70: Secondary Funds | B70: =B69+1 -> 3 | C70: Year 3 | D70: =D6 -> 2027 | E70: =VLOOKUP($B70,'Global Secondary Funds'!$A$4:$S$19,E$1,0) -> -0.49076064 | F70: =VLOOKUP($B70,'Global Secondary Funds'!$A$4:$S$19,F$1,0) -> 0.11922804 | G70: =VLOOKUP($B70,'Global Secondary Funds'!$A$4:$S$19,G$1,0) -> -0.3715326 | H70: =VLOOKUP($B70,'Global Secondary Funds'!$A$4:$S$19,H$1,0) -> 0.52996946 | J70: =VLOOKUP($B70,'Global Secondary Funds'!$A$4:$S$19,J$1,0) -> -0.22004611 | K70: =VLOOKUP($B70,'Global Secondary Funds'!$A$4:$S$19,K$1,0) -> 0.08697616 | L70: =VLOOKUP($B70,'Global Secondary Funds'!$A$4:$S$19,L$1,0) -> -0.13306995 | M70: =VLOOKUP($B70,'Global Secondary Funds'!$A$4:$S$19,M$1,0) -> 0.52996946 | O70: =VLOOKUP($B70,'Global Secondary Funds'!$A$4:$S$19,O$1,0) -> 0.12145538 | P70: =VLOOKUP($B70,'Global Secondary Funds'!$A$4:$S$19,P$1,0) -> 0.038080664 | Q70: =VLOOKUP($B70,'Global Secondary Funds'!$A$4:$S$19,Q$1,0) -> 0.1272853 | R70: =VLOOKUP($B70,'Global Secondary Funds'!$A$4:$S$19,R$1,0) -> 0.15783217 | T70: =VLOOKUP($B70,'Global Secondary Funds'!$A$4:$S$19,T$1,0) -> 0.083433656 | U70: =VLOOKUP($B70,'Global Secondary Funds'!$A$4:$S$19,U$1,0) -> 0.032718793 | V70: =VLOOKUP($B70,'Global Secondary Funds'!$A$4:$S$19,V$1,0) -> 0.089619721 | W70: =VLOOKUP($B70,'Global Secondary Funds'!$A$4:$S$19,W$1,0) -> 0.15783217
A71: Secondary Funds | B71: =B70+1 -> 4 | C71: Year 4 | D71: =D7 -> 2028 | E71: =VLOOKUP($B71,'Global Secondary Funds'!$A$4:$S$19,E$1,0) -> -0.63010535 | F71: =VLOOKUP($B71,'Global Secondary Funds'!$A$4:$S$19,F$1,0) -> 0.24483589 | G71: =VLOOKUP($B71,'Global Secondary Funds'!$A$4:$S$19,G$1,0) -> -0.38526945 | H71: =VLOOKUP($B71,'Global Secondary Funds'!$A$4:$S$19,H$1,0) -> 0.63572724 | J71: =VLOOKUP($B71,'Global Secondary Funds'!$A$4:$S$19,J$1,0) -> -0.13934471 | K71: =VLOOKUP($B71,'Global Secondary Funds'!$A$4:$S$19,K$1,0) -> 0.12560785 | L71: =VLOOKUP($B71,'Global Secondary Funds'!$A$4:$S$19,L$1,0) -> -0.013736856 | M71: =VLOOKUP($B71,'Global Secondary Funds'!$A$4:$S$19,M$1,0) -> 0.63572724 | O71: =VLOOKUP($B71,'Global Secondary Funds'!$A$4:$S$19,O$1,0) -> 0.1372542 | P71: =VLOOKUP($B71,'Global Secondary Funds'!$A$4:$S$19,P$1,0) -> 0.061307246 | Q71: =VLOOKUP($B71,'Global Secondary Funds'!$A$4:$S$19,Q$1,0) -> 0.15032396 | R71: =VLOOKUP($B71,'Global Secondary Funds'!$A$4:$S$19,R$1,0) -> 0.18162407 | T71: =VLOOKUP($B71,'Global Secondary Funds'!$A$4:$S$19,T$1,0) -> 0.063932025 | U71: =VLOOKUP($B71,'Global Secondary Funds'!$A$4:$S$19,U$1,0) -> 0.048046242 | V71: =VLOOKUP($B71,'Global Secondary Funds'!$A$4:$S$19,V$1,0) -> 0.079973403 | W71: =VLOOKUP($B71,'Global Secondary Funds'!$A$4:$S$19,W$1,0) -> 0.18162407
A72: Secondary Funds | B72: =B71+1 -> 5 | C72: Year 5 | D72: =D8 -> 2029 | E72: =VLOOKUP($B72,'Global Secondary Funds'!$A$4:$S$19,E$1,0) -> -0.72293806 | F72: =VLOOKUP($B72,'Global Secondary Funds'!$A$4:$S$19,F$1,0) -> 0.39334244 | G72: =VLOOKUP($B72,'Global Secondary Funds'!$A$4:$S$19,G$1,0) -> -0.32959562 | H72: =VLOOKUP($B72,'Global Secondary Funds'!$A$4:$S$19,H$1,0) -> 0.65114096 | J72: =VLOOKUP($B72,'Global Secondary Funds'!$A$4:$S$19,J$1,0) -> -0.092832714 | K72: =VLOOKUP($B72,'Global Secondary Funds'!$A$4:$S$19,K$1,0) -> 0.14850655 | L72: =VLOOKUP($B72,'Global Secondary Funds'!$A$4:$S$19,L$1,0) -> 0.055673831 | M72: =VLOOKUP($B72,'Global Secondary Funds'!$A$4:$S$19,M$1,0) -> 0.65114096 | O72: =VLOOKUP($B72,'Global Secondary Funds'!$A$4:$S$19,O$1,0) -> 0.14591231 | P72: =VLOOKUP($B72,'Global Secondary Funds'!$A$4:$S$19,P$1,0) -> 0.079115328 | Q72: =VLOOKUP($B72,'Global Secondary Funds'!$A$4:$S$19,Q$1,0) -> 0.16598084 | R72: =VLOOKUP($B72,'Global Secondary Funds'!$A$4:$S$19,R$1,0) -> 0.20839512 | T72: =VLOOKUP($B72,'Global Secondary Funds'!$A$4:$S$19,T$1,0) -> 0.049514528 | U72: =VLOOKUP($B72,'Global Secondary Funds'!$A$4:$S$19,U$1,0) -> 0.050006566 | V72: =VLOOKUP($B72,'Global Secondary Funds'!$A$4:$S$19,V$1,0) -> 0.070372901 | W72: =VLOOKUP($B72,'Global Secondary Funds'!$A$4:$S$19,W$1,0) -> 0.20839512
A73: Secondary Funds | B73: =B72+1 -> 6 | C73: Year 6 | D73: =D9 -> 2030 | E73: =VLOOKUP($B73,'Global Secondary Funds'!$A$4:$S$19,E$1,0) -> -0.75695581 | F73: =VLOOKUP($B73,'Global Secondary Funds'!$A$4:$S$19,F$1,0) -> 0.5995609 | G73: =VLOOKUP($B73,'Global Secondary Funds'!$A$4:$S$19,G$1,0) -> -0.15739491 | H73: =VLOOKUP($B73,'Global Secondary Funds'!$A$4:$S$19,H$1,0) -> 0.57299201 | J73: =VLOOKUP($B73,'Global Secondary Funds'!$A$4:$S$19,J$1,0) -> -0.034017744 | K73: =VLOOKUP($B73,'Global Secondary Funds'!$A$4:$S$19,K$1,0) -> 0.20621846 | L73: =VLOOKUP($B73,'Global Secondary Funds'!$A$4:$S$19,L$1,0) -> 0.17220071 | M73: =VLOOKUP($B73,'Global Secondary Funds'!$A$4:$S$19,M$1,0) -> 0.57299201 | O73: =VLOOKUP($B73,'Global Secondary Funds'!$A$4:$S$19,O$1,0) -> 0.14975986 | P73: =VLOOKUP($B73,'Global Secondary Funds'!$A$4:$S$19,P$1,0) -> 0.13219012 | Q73: =VLOOKUP($B73,'Global Secondary Funds'!$A$4:$S$19,Q$1,0) -> 0.19975546 | R73: =VLOOKUP($B73,'Global Secondary Funds'!$A$4:$S$19,R$1,0) -> 0.22425921 | T73: =VLOOKUP($B73,'Global Secondary Funds'!$A$4:$S$19,T$1,0) -> 0.033728532 | U73: =VLOOKUP($B73,'Global Secondary Funds'!$A$4:$S$19,U$1,0) -> 0.10590086 | V73: =VLOOKUP($B73,'Global Secondary Funds'!$A$4:$S$19,V$1,0) -> 0.11114228 | W73: =VLOOKUP($B73,'Global Secondary Funds'!$A$4:$S$19,W$1,0) -> 0.22425921
A74: Secondary Funds | B74: =B73+1 -> 7 | C74: Year 7 | D74: =D10 -> 2031 | E74: =VLOOKUP($B74,'Global Secondary Funds'!$A$4:$S$19,E$1,0) -> -0.78034505 | F74: =VLOOKUP($B74,'Global Secondary Funds'!$A$4:$S$19,F$1,0) -> 0.73860834 | G74: =VLOOKUP($B74,'Global Secondary Funds'!$A$4:$S$19,G$1,0) -> -0.041736708 | H74: =VLOOKUP($B74,'Global Secondary Funds'!$A$4:$S$19,H$1,0) -> 0.48874109 | J74: =VLOOKUP($B74,'Global Secondary Funds'!$A$4:$S$19,J$1,0) -> -0.023389241 | K74: =VLOOKUP($B74,'Global Secondary Funds'!$A$4:$S$19,K$1,0) -> 0.13904744 | L74: =VLOOKUP($B74,'Global Secondary Funds'!$A$4:$S$19,L$1,0) -> 0.1156582 | M74: =VLOOKUP($B74,'Global Secondary Funds'!$A$4:$S$19,M$1,0) -> 0.48874109 | O74: =VLOOKUP($B74,'Global Secondary Funds'!$A$4:$S$19,O$1,0) -> 0.15144058 | P74: =VLOOKUP($B74,'Global Secondary Funds'!$A$4:$S$19,P$1,0) -> 0.14301068 | Q74: =VLOOKUP($B74,'Global Secondary Funds'!$A$4:$S$19,Q$1,0) -> 0.20829379 | R74: =VLOOKUP($B74,'Global Secondary Funds'!$A$4:$S$19,R$1,0) -> 0.23338132 | T74: =VLOOKUP($B74,'Global Secondary Funds'!$A$4:$S$19,T$1,0) -> 0.022499621 | U74: =VLOOKUP($B74,'Global Secondary Funds'!$A$4:$S$19,U$1,0) -> 0.05456947 | V74: =VLOOKUP($B74,'Global Secondary Funds'!$A$4:$S$19,V$1,0) -> 0.059025927 | W74: =VLOOKUP($B74,'Global Secondary Funds'!$A$4:$S$19,W$1,0) -> 0.23338132
A75: Secondary Funds | B75: =B74+1 -> 8 | C75: Year 8 | D75: =D11 -> 2032 | E75: =VLOOKUP($B75,'Global Secondary Funds'!$A$4:$S$19,E$1,0) -> -0.78626492 | F75: =VLOOKUP($B75,'Global Secondary Funds'!$A$4:$S$19,F$1,0) -> 0.87593519 | G75: =VLOOKUP($B75,'Global Secondary Funds'!$A$4:$S$19,G$1,0) -> 0.08967027 | H75: =VLOOKUP($B75,'Global Secondary Funds'!$A$4:$S$19,H$1,0) -> 0.38330054 | J75: =VLOOKUP($B75,'Global Secondary Funds'!$A$4:$S$19,J$1,0) -> -0.0059198721 | K75: =VLOOKUP($B75,'Global Secondary Funds'!$A$4:$S$19,K$1,0) -> 0.13732685 | L75: =VLOOKUP($B75,'Global Secondary Funds'!$A$4:$S$19,L$1,0) -> 0.13140698 | M75: =VLOOKUP($B75,'Global Secondary Funds'!$A$4:$S$19,M$1,0) -> 0.38330054 | O75: =VLOOKUP($B75,'Global Secondary Funds'!$A$4:$S$19,O$1,0) -> 0.15165721 | P75: =VLOOKUP($B75,'Global Secondary Funds'!$A$4:$S$19,P$1,0) -> 0.16322422 | Q75: =VLOOKUP($B75,'Global Secondary Funds'!$A$4:$S$19,Q$1,0) -> 0.22280497 | R75: =VLOOKUP($B75,'Global Secondary Funds'!$A$4:$S$19,R$1,0) -> 0.23932414 | T75: =VLOOKUP($B75,'Global Secondary Funds'!$A$4:$S$19,T$1,0) -> 0.0081031617 | U75: =VLOOKUP($B75,'Global Secondary Funds'!$A$4:$S$19,U$1,0) -> 0.078677127 | V75: =VLOOKUP($B75,'Global Secondary Funds'!$A$4:$S$19,V$1,0) -> 0.079093309 | W75: =VLOOKUP($B75,'Global Secondary Funds'!$A$4:$S$19,W$1,0) -> 0.23932414
A76: Secondary Funds | B76: =B75+1 -> 9 | C76: Year 9 | D76: =D12 -> 2033 | E76: =VLOOKUP($B76,'Global Secondary Funds'!$A$4:$S$19,E$1,0) -> -0.79285052 | F76: =VLOOKUP($B76,'Global Secondary Funds'!$A$4:$S$19,F$1,0) -> 0.98843054 | G76: =VLOOKUP($B76,'Global Secondary Funds'!$A$4:$S$19,G$1,0) -> 0.19558002 | H76: =VLOOKUP($B76,'Global Secondary Funds'!$A$4:$S$19,H$1,0) -> 0.32645179 | J76: =VLOOKUP($B76,'Global Secondary Funds'!$A$4:$S$19,J$1,0) -> -0.0065856017 | K76: =VLOOKUP($B76,'Global Secondary Funds'!$A$4:$S$19,K$1,0) -> 0.11249535 | L76: =VLOOKUP($B76,'Global Secondary Funds'!$A$4:$S$19,L$1,0) -> 0.10590975 | M76: =VLOOKUP($B76,'Global Secondary Funds'!$A$4:$S$19,M$1,0) -> 0.32645179 | O76: =VLOOKUP($B76,'Global Secondary Funds'!$A$4:$S$19,O$1,0) -> 0.15189919 | P76: =VLOOKUP($B76,'Global Secondary Funds'!$A$4:$S$19,P$1,0) -> 0.17610303 | Q76: =VLOOKUP($B76,'Global Secondary Funds'!$A$4:$S$19,Q$1,0) -> 0.2325632 | R76: =VLOOKUP($B76,'Global Secondary Funds'!$A$4:$S$19,R$1,0) -> 0.24535363 | T76: =VLOOKUP($B76,'Global Secondary Funds'!$A$4:$S$19,T$1,0) -> 0.0085705754 | U76: =VLOOKUP($B76,'Global Secondary Funds'!$A$4:$S$19,U$1,0) -> 0.066106977 | V76: =VLOOKUP($B76,'Global Secondary Funds'!$A$4:$S$19,V$1,0) -> 0.066660237 | W76: =VLOOKUP($B76,'Global Secondary Funds'!$A$4:$S$19,W$1,0) -> 0.24535363
